Workbook

Sheet Livro Diario - FC
E1: 0
C3: Livro Diário - Lançamento das Contas
AA4: ocultar
C9: =TODAY() -> 46144 | AE9: Plano Contas | AH9: Contas
C10: Status | D10: Data | E10: Contas | F10: Volume da Embalagem | G10: Und. Medida | H10: Cliente / Fornecedor | I10: Histórico | J10: A Receber | K10: A Pagar | L10: Entrada | M10: Saída | N10: Orig/Dest | P10: Falta Receber | Q10: Falta Pagar | AA10: A pagar | AB10: A receber
D11: 46027 | E11: 3.1.1 Receita com Cash - Diaria | F11: . | G11: . | H11: Vendas Diarias | I11: Deposito Dinheiro | J11: 260 | L11: 260 | N11: DINHEIRO | O11: =IF(K11=0,"",IF(AND(K11>0,K11>M11),K11-M11,"")) | P11: =IF(J11="","",J11-L11) -> 0 | Q11: =IF(K11="","",K11-M11) | AA11: =IF(K11=0,"",IF(AND(K11>0,K11>M11),K11-M11,"")) | AB11: =IF(J11=0,"",IF(AND(J11>0,J11>L11),J11-L11,"")) | AE11: 3.1 Receita de Vendas | AH11: DINHEIRO
D12: 46027 | E12: 3.1.2 Receita com Cartão (Caixa) | F12: . | G12: . | H12: Vendas Cartão | I12: Recebiveis Cartão | N12: CAIXA ECONOMICA | P12: =IF(J12="","",J12-L12) | Q12: =IF(K12="","",K12-M12) | AA12: =IF(K12=0,"",IF(AND(K12>0,K12>M12),K12-M12,"")) | AB12: =IF(J12=0,"",IF(AND(J12>0,J12>L12),J12-L12,"")) | AE12: 3.1.1 Receita com Cash - Diaria | AH12: Fundo de Investimento - Ifood
D13: 46027 | E13: 3.1.3 Receita Ifood | F13: . | G13: . | H13: Vendas Ifood | I13: Recebimento Ifood | N13: IFOOD | P13: =IF(J13="","",J13-L13) | Q13: =IF(K13="","",K13-M13) | AA13: =IF(K13=0,"",IF(AND(K13>0,K13>M13),K13-M13,"")) | AB13: =IF(J13=0,"",IF(AND(J13>0,J13>L13),J13-L13,"")) | AE13: 3.1.2 Receita com Cartão (Caixa) | AH13: Capital de Giro - Caixa Economica
D14: 46027 | E14: 3.1.4 Receita com Cartão - (Infinity Emp) | F14: . | G14: . | H14: Vendas na Infinity | I14: Recebiveis Cartão/Pix | N14: INFINITY EMPORIO | P14: =IF(J14="","",J14-L14) | Q14: =IF(K14="","",K14-M14) | AA14: =IF(K14=0,"",IF(AND(K14>0,K14>M14),K14-M14,"")) | AB14: =IF(J14=0,"",IF(AND(J14>0,J14>L14),J14-L14,"")) | AE14: 3.1.3 Receita Ifood | AH14: Fundo de Reserva - Cash
D15: 46027 | E15: 3.1.5 Receita com Cartão - (Infinity Sil) | F15: . | G15: . | H15: Vendas na Infinity | I15: Recebiveis Cartão/Pix | N15: INFINITY SILVIO | P15: =IF(J15="","",J15-L15) | Q15: =IF(K15="","",K15-M15) | AA15: =IF(K15=0,"",IF(AND(K15>0,K15>M15),K15-M15,"")) | AB15: =IF(J15=0,"",IF(AND(J15>0,J15>L15),J15-L15,"")) | AE15: 3.1.4 Receita com Cartão - (Infinity Emp) | AH15: CAIXA ECONOMICA
D16: 46027 | E16: Toscana Frango | F16: 3,030 | G16: kg | H16: Só Frios | I16: Proteina | K16: 69.66 | M16: 69.66 | P16: =IF(J16="","",J16-L16) | Q16: =IF(K16="","",K16-M16) -> 0 | AA16: =IF(K16=0,"",IF(AND(K16>0,K16>M16),K16-M16,"")) | AB16: =IF(J16=0,"",IF(AND(J16>0,J16>L16),J16-L16,"")) | AE16: 3.1.5 Receita com Cartão - (Infinity Sil) | AH16: INFINITY EMPORIO
D17: 46027 | E17: Coxão Mole (Bife) | F17: 2,816 | G17: kg | H17: Só Frios | I17: Proteina | K17: 87.27 | M17: 87.27 | P17: =IF(J17="","",J17-L17) | Q17: =IF(K17="","",K17-M17) -> 0 | AA17: =IF(K17=0,"",IF(AND(K17>0,K17>M17),K17-M17,"")) | AB17: =IF(J17=0,"",IF(AND(J17>0,J17>L17),J17-L17,"")) | AE17: 3.1.6 - | AH17: IFOOD
D18: 46027 | E18: Carne para Guisada (picadão) | F18: 2,686 | G18: kg | H18: Só Frios | I18: Proteina | K18: 77.87 | M18: 77.87 | P18: =IF(J18="","",J18-L18) | Q18: =IF(K18="","",K18-M18) -> 0 | AA18: =IF(K18=0,"",IF(AND(K18>0,K18>M18),K18-M18,"")) | AB18: =IF(J18=0,"",IF(AND(J18>0,J18>L18),J18-L18,"")) | AE18: 3.1.7 - | AH18: INFINITY SILVIO
D19: 46027 | E19: Figado Bovino | F19: 0,992 | G19: kg | H19: Só Frios | I19: Proteina | K19: 15.86 | M19: 15.86 | P19: =IF(J19="","",J19-L19) | Q19: =IF(K19="","",K19-M19) -> 0 | AA19: =IF(K19=0,"",IF(AND(K19>0,K19>M19),K19-M19,"")) | AB19: =IF(J19=0,"",IF(AND(J19>0,J19>L19),J19-L19,"")) | AE19: 3.1.8 - | AH19: -
D20: 46027 | E20: Compras Diversos | F20: . | G20: . | H20: Só Frios | I20: Abacate | K20: 11.29 | M20: 11.29 | P20: =IF(J20="","",J20-L20) | Q20: =IF(K20="","",K20-M20) -> 0 | AA20: =IF(K20=0,"",IF(AND(K20>0,K20>M20),K20-M20,"")) | AB20: =IF(J20=0,"",IF(AND(J20>0,J20>L20),J20-L20,"")) | AE20: 3.1.9 .
D21: 46027 | E21: Compras Diversos | F21: . | G21: . | H21: Só Frios | I21: Maça | K21: 6.16 | M21: 6.16 | P21: =IF(J21="","",J21-L21) | Q21: =IF(K21="","",K21-M21) -> 0 | AA21: =IF(K21=0,"",IF(AND(K21>0,K21>M21),K21-M21,"")) | AB21: =IF(J21=0,"",IF(AND(J21>0,J21>L21),J21-L21,"")) | AE21: 3.1.10 Acerto
D22: 46026 | E22: Tomate | F22: 23,000 | G22: kg | H22: Ceasa | I22: Verduras | K22: 40 | M22: 40 | N22: DINHEIRO | P22: =IF(J22="","",J22-L22) | Q22: =IF(K22="","",K22-M22) -> 0 | AA22: =IF(K22=0,"",IF(AND(K22>0,K22>M22),K22-M22,"")) | AB22: =IF(J22=0,"",IF(AND(J22>0,J22>L22),J22-L22,"")) | AE22: 3.1.11 -
D23: 46026 | E23: Cebola | F23: 20,000 | G23: kg | H23: Ceasa | I23: Verduras | K23: 50 | M23: 50 | N23: DINHEIRO | P23: =IF(J23="","",J23-L23) | Q23: =IF(K23="","",K23-M23) -> 0 | AA23: =IF(K23=0,"",IF(AND(K23>0,K23>M23),K23-M23,"")) | AB23: =IF(J23=0,"",IF(AND(J23>0,J23>L23),J23-L23,"")) | AE23: 3.1.12 -
D24: 46026 | E24: Batata Inglesa | F24: 25,000 | G24: kg | H24: Ceasa | I24: Verduras | K24: 80 | M24: 80 | N24: DINHEIRO | P24: =IF(J24="","",J24-L24) | Q24: =IF(K24="","",K24-M24) -> 0 | AA24: =IF(K24=0,"",IF(AND(K24>0,K24>M24),K24-M24,"")) | AB24: =IF(J24=0,"",IF(AND(J24>0,J24>L24),J24-L24,"")) | AE24: 3.1.13 -
D25: 46026 | E25: Pimenta Cheiro | F25: 1,000 | G25: kg | H25: Ceasa | I25: Temperos | P25: =IF(J25="","",J25-L25) | Q25: =IF(K25="","",K25-M25) | AA25: =IF(K25=0,"",IF(AND(K25>0,K25>M25),K25-M25,"")) | AB25: =IF(J25=0,"",IF(AND(J25>0,J25>L25),J25-L25,"")) | AE25: 3.1.14 -
D26: 46026 | E26: Cenoura | F26: 10,000 | G26: kg | H26: Ceasa | I26: Verduras | P26: =IF(J26="","",J26-L26) | Q26: =IF(K26="","",K26-M26) | AA26: =IF(K26=0,"",IF(AND(K26>0,K26>M26),K26-M26,"")) | AB26: =IF(J26=0,"",IF(AND(J26>0,J26>L26),J26-L26,"")) | AE26: 3.1.15 -
D27: 46026 | E27: Chuchu | F27: 12,000 | G27: kg | H27: Ceasa | I27: Verduras | P27: =IF(J27="","",J27-L27) | Q27: =IF(K27="","",K27-M27) | AA27: =IF(K27=0,"",IF(AND(K27>0,K27>M27),K27-M27,"")) | AB27: =IF(J27=0,"",IF(AND(J27>0,J27>L27),J27-L27,"")) | AE27: DESPESAS/CUSTOS VARIÁVEIS
D28: 46026 | E28: Abobora | F28: 7,000 | G28: kg | H28: Ceasa | I28: Verduras | K28: 22 | M28: 22 | N28: DINHEIRO | P28: =IF(J28="","",J28-L28) | Q28: =IF(K28="","",K28-M28) -> 0 | AA28: =IF(K28=0,"",IF(AND(K28>0,K28>M28),K28-M28,"")) | AB28: =IF(J28=0,"",IF(AND(J28>0,J28>L28),J28-L28,"")) | AE28: 4.1 Custos Tributários e Financeiros
D29: 46026 | E29: Coentro | F29: 6,000 | G29: kg | H29: Ceasa | I29: Temperos | K29: 20 | M29: 20 | N29: DINHEIRO | P29: =IF(J29="","",J29-L29) | Q29: =IF(K29="","",K29-M29) -> 0 | AA29: =IF(K29=0,"",IF(AND(K29>0,K29>M29),K29-M29,"")) | AB29: =IF(J29=0,"",IF(AND(J29>0,J29>L29),J29-L29,"")) | AE29: 4.1.1 Simples Federal
D30: 46026 | E30: Limão | F30: 100 | G30: und | H30: Ceasa | I30: Frutas | P30: =IF(J30="","",J30-L30) | Q30: =IF(K30="","",K30-M30) | AA30: =IF(K30=0,"",IF(AND(K30>0,K30>M30),K30-M30,"")) | AB30: =IF(J30=0,"",IF(AND(J30>0,J30>L30),J30-L30,"")) | AE30: 4.1.2 Mercantil
D31: 46026 | E31: Laranja | F31: 100 | G31: und | H31: Ceasa | I31: Frutas | K31: 40 | M31: 40 | N31: DINHEIRO | P31: =IF(J31="","",J31-L31) | Q31: =IF(K31="","",K31-M31) -> 0 | AA31: =IF(K31=0,"",IF(AND(K31>0,K31>M31),K31-M31,"")) | AB31: =IF(J31=0,"",IF(AND(J31>0,J31>L31),J31-L31,"")) | AE31: 4.1.3 IPTU
D32: 46026 | E32: Pão ou Torrada | F32: 30 | G32: pct | H32: Ceasa | I32: Insumos | K32: 90 | M32: 90 | N32: DINHEIRO | P32: =IF(J32="","",J32-L32) | Q32: =IF(K32="","",K32-M32) -> 0 | AA32: =IF(K32=0,"",IF(AND(K32>0,K32>M32),K32-M32,"")) | AB32: =IF(J32=0,"",IF(AND(J32>0,J32>L32),J32-L32,"")) | AE32: 4.1.4 FGTS
D33: 46026 | E33: Bolo de Noiva | F33: 1,000 | G33: kg | H33: Ceasa | I33: SobreMesas | K33: 35 | M33: 35 | N33: DINHEIRO | P33: =IF(J33="","",J33-L33) | Q33: =IF(K33="","",K33-M33) -> 0 | AA33: =IF(K33=0,"",IF(AND(K33>0,K33>M33),K33-M33,"")) | AB33: =IF(J33=0,"",IF(AND(J33>0,J33>L33),J33-L33,"")) | AE33: 4.1.5 INSS
D34: 46026 | E34: Cocada | F34: 28 | G34: und | H34: Ceasa | I34: SobreMesas | K34: 48 | M34: 48 | N34: DINHEIRO | P34: =IF(J34="","",J34-L34) | Q34: =IF(K34="","",K34-M34) -> 0 | AA34: =IF(K34=0,"",IF(AND(K34>0,K34>M34),K34-M34,"")) | AB34: =IF(J34=0,"",IF(AND(J34>0,J34>L34),J34-L34,"")) | AE34: 4.1.6 Parcelamento Imposto
D35: 46026 | E35: Ovos de Galinha | F35: 30 | G35: und | H35: Ceasa | I35: Proteina | P35: =IF(J35="","",J35-L35) | Q35: =IF(K35="","",K35-M35) | AA35: =IF(K35=0,"",IF(AND(K35>0,K35>M35),K35-M35,"")) | AB35: =IF(J35=0,"",IF(AND(J35>0,J35>L35),J35-L35,"")) | AE35: 4.1.7 Parcelamento Imposto
D36: 46026 | E36: Macaxeira | F36: 25 | G36: kg | H36: Ceasa | I36: Raiz | K36: 75 | M36: 75 | N36: DINHEIRO | P36: =IF(J36="","",J36-L36) | Q36: =IF(K36="","",K36-M36) -> 0 | AA36: =IF(K36=0,"",IF(AND(K36>0,K36>M36),K36-M36,"")) | AB36: =IF(J36=0,"",IF(AND(J36>0,J36>L36),J36-L36,"")) | AE36: 4.1.8 .
D37: 46026 | E37: Inhame | F37: 15 | G37: kg | H37: Ceasa | I37: Raiz | K37: 50 | M37: 50 | N37: DINHEIRO | P37: =IF(J37="","",J37-L37) | Q37: =IF(K37="","",K37-M37) -> 0 | AA37: =IF(K37=0,"",IF(AND(K37>0,K37>M37),K37-M37,"")) | AB37: =IF(J37=0,"",IF(AND(J37>0,J37>L37),J37-L37,"")) | AE37: 4.1.9 .
D38: 46026 | E38: Bucha de Prato | F38: 20 | G38: und | H38: Assaí | I38: Limpeza | K38: R$ 31,00 | M38: R$ 31,00 | N38: CAIXA ECONOMICA | P38: =IF(J38="","",J38-L38) | Q38: =IF(K38="","",K38-M38) -> #VALUE! | AA38: =IF(K38=0,"",IF(AND(K38>0,K38>M38),K38-M38,"")) | AB38: =IF(J38=0,"",IF(AND(J38>0,J38>L38),J38-L38,"")) | AE38: CUSTOS COM PRODUTOS
D39: 46026 | E39: Desinfetante | F39: 1 | G39: und | H39: Assaí | I39: Limpeza | K39: R$ 6,89 | M39: R$ 6,89 | N39: CAIXA ECONOMICA | P39: =IF(J39="","",J39-L39) | Q39: =IF(K39="","",K39-M39) -> #VALUE! | AA39: =IF(K39=0,"",IF(AND(K39>0,K39>M39),K39-M39,"")) | AB39: =IF(J39=0,"",IF(AND(J39>0,J39>L39),J39-L39,"")) | AE39: INSUMOS
D40: 46026 | E40: Desinfetante | F40: 2 | G40: und | H40: Assaí | I40: Limpeza | K40: R$ 11,38 | M40: R$ 11,38 | N40: CAIXA ECONOMICA | P40: =IF(J40="","",J40-L40) | Q40: =IF(K40="","",K40-M40) -> #VALUE! | AA40: =IF(K40=0,"",IF(AND(K40>0,K40>M40),K40-M40,"")) | AB40: =IF(J40=0,"",IF(AND(J40>0,J40>L40),J40-L40,"")) | AE40: Macarrão
D41: 46026 | E41: Bucha de Prato | F41: 1 | G41: und | H41: Assaí | I41: Limpeza | K41: R$ 4,60 | M41: R$ 4,60 | N41: CAIXA ECONOMICA | P41: =IF(J41="","",J41-L41) | Q41: =IF(K41="","",K41-M41) -> #VALUE! | AA41: =IF(K41=0,"",IF(AND(K41>0,K41>M41),K41-M41,"")) | AB41: =IF(J41=0,"",IF(AND(J41>0,J41>L41),J41-L41,"")) | AE41: Arroz
D42: 46026 | E42: Sabão em Pó | F42: 1 | G42: und | H42: Assaí | I42: Limpeza | K42: 7.29 | M42: 7.29 | N42: CAIXA ECONOMICA | P42: =IF(J42="","",J42-L42) | Q42: =IF(K42="","",K42-M42) -> 0 | AA42: =IF(K42=0,"",IF(AND(K42>0,K42>M42),K42-M42,"")) | AB42: =IF(J42=0,"",IF(AND(J42>0,J42>L42),J42-L42,"")) | AE42: Feijão mulato
D43: 46026 | E43: Pastilha Banheiro | F43: 1 | G43: und | H43: Assaí | I43: Limpeza | K43: 7.29 | M43: 7.29 | N43: CAIXA ECONOMICA | P43: =IF(J43="","",J43-L43) -> #VALUE! | Q43: =IF(K43="","",K43-M43) -> 0 | AA43: =IF(K43=0,"",IF(AND(K43>0,K43>M43),K43-M43,"")) | AB43: =IF(J43=0,"",IF(AND(J43>0,J43>L43),J43-L43,"")) -> #VALUE! | AE43: Feijão Preto
D44: 46026 | E44: Papel Higienico | F44: 1 | G44: pct | H44: Assaí | I44: Limpeza | K44: 12.8 | M44: 12.8 | N44: CAIXA ECONOMICA | P44: =IF(J44="","",J44-L44) | Q44: =IF(K44="","",K44-M44) -> 0 | AA44: =IF(K44=0,"",IF(AND(K44>0,K44>M44),K44-M44,"")) | AB44: =IF(J44=0,"",IF(AND(J44>0,J44>L44),J44-L44,"")) | AE44: Feijão macassar
D45: 46026 | E45: Sabão em Pó | F45: 9 | G45: und | H45: Assaí | I45: Limpeza | K45: 15.99 | M45: 15.99 | N45: CAIXA ECONOMICA | P45: =IF(J45="","",J45-L45) -> #VALUE! | Q45: =IF(K45="","",K45-M45) -> 0 | AA45: =IF(K45=0,"",IF(AND(K45>0,K45>M45),K45-M45,"")) | AB45: =IF(J45=0,"",IF(AND(J45>0,J45>L45),J45-L45,"")) -> #VALUE! | AE45: Sal
D46: 46026 | E46: Molho de Tomate (Pronto) | F46: 2 | G46: und | H46: Assaí | I46: Insumos | K46: 20.98 | M46: 20.98 | N46: CAIXA ECONOMICA | P46: =IF(J46="","",J46-L46) | Q46: =IF(K46="","",K46-M46) -> 0 | AA46: =IF(K46=0,"",IF(AND(K46>0,K46>M46),K46-M46,"")) | AB46: =IF(J46=0,"",IF(AND(J46>0,J46>L46),J46-L46,"")) | AE46: Açúcar
D47: 46026 | E47: Café | F47: 4 | G47: pct | H47: Assaí | I47: Insumos | K47: 55.16 | M47: 55.16 | N47: CAIXA ECONOMICA | P47: =IF(J47="","",J47-L47) | Q47: =IF(K47="","",K47-M47) -> 0 | AA47: =IF(K47=0,"",IF(AND(K47>0,K47>M47),K47-M47,"")) | AB47: =IF(J47=0,"",IF(AND(J47>0,J47>L47),J47-L47,"")) | AE47: Farinha
D48: 46026 | E48: Leite Condensado | F48: 4 | G48: und | H48: Assaí | I48: Insumos | K48: 15.8 | M48: 15.8 | N48: CAIXA ECONOMICA | P48: =IF(J48="","",J48-L48) | Q48: =IF(K48="","",K48-M48) -> 0 | AA48: =IF(K48=0,"",IF(AND(K48>0,K48>M48),K48-M48,"")) | AB48: =IF(J48=0,"",IF(AND(J48>0,J48>L48),J48-L48,"")) | AE48: Leite em pó
D49: 46026 | E49: Molho Alho | F49: 3 | G49: und | H49: Assaí | I49: Insumos | K49: 8.85 | M49: 8.85 | N49: CAIXA ECONOMICA | P49: =IF(J49="","",J49-L49) | Q49: =IF(K49="","",K49-M49) -> 0 | AA49: =IF(K49=0,"",IF(AND(K49>0,K49>M49),K49-M49,"")) | AB49: =IF(J49=0,"",IF(AND(J49>0,J49>L49),J49-L49,"")) | AE49: Trigo Normal
D50: 46026 | E50: Margarina | F50: 3,000 | G50: kg | H50: Assaí | I50: Insumos | K50: 23.9 | M50: 23.9 | N50: CAIXA ECONOMICA | P50: =IF(J50="","",J50-L50) | Q50: =IF(K50="","",K50-M50) -> 0 | AA50: =IF(K50=0,"",IF(AND(K50>0,K50>M50),K50-M50,"")) | AB50: =IF(J50=0,"",IF(AND(J50>0,J50>L50),J50-L50,"")) | AE50: Farinha de Rosca
D51: 46026 | E51: Molho Ingles | F51: 3 | G51: und | H51: Assaí | I51: Insumos | K51: 8.85 | M51: 8.85 | N51: CAIXA ECONOMICA | P51: =IF(J51="","",J51-L51) | Q51: =IF(K51="","",K51-M51) -> 0 | AA51: =IF(K51=0,"",IF(AND(K51>0,K51>M51),K51-M51,"")) | AB51: =IF(J51=0,"",IF(AND(J51>0,J51>L51),J51-L51,"")) | AE51: Macarrão Lasanha
D52: 46026 | E52: Azeite | F52: 2 | G52: und | H52: Assaí | I52: Insumos | K52: 43.8 | M52: 43.8 | N52: CAIXA ECONOMICA | P52: =IF(J52="","",J52-L52) | Q52: =IF(K52="","",K52-M52) -> 0 | AA52: =IF(K52=0,"",IF(AND(K52>0,K52>M52),K52-M52,"")) | AB52: =IF(J52=0,"",IF(AND(J52>0,J52>L52),J52-L52,"")) | AE52: Molho Ingles
D53: 46026 | E53: Oleo | F53: 1 | G53: und | H53: Assaí | I53: Insumos | K53: 15.49 | M53: 15.49 | N53: CAIXA ECONOMICA | P53: =IF(J53="","",J53-L53) | Q53: =IF(K53="","",K53-M53) -> 0 | AA53: =IF(K53=0,"",IF(AND(K53>0,K53>M53),K53-M53,"")) | AB53: =IF(J53=0,"",IF(AND(J53>0,J53>L53),J53-L53,"")) | AE53: Sprite Lata
... D78: 46026 | E78: H2o | F78: 12 | G78: und | H78: Assaí | I78: Insumos | K78: 59.4 | M78: 59.4 | N78: CAIXA ECONOMICA | P78: =IF(J78="","",J78-L78) | Q78: =IF(K78="","",K78-M78) -> 0 | AA78: =IF(K78=0,"",IF(AND(K78>0,K78>M78),K78-M78,"")) | AB78: =IF(J78=0,"",IF(AND(J78>0,J78>L78),J78-L78,"")) | AE78: Inhame
D79: . | F79: . | G79: . | H79: . | I79: . | J79: . | K79: . | L79: . | M79: . | P79: =IF(J79="","",J79-L79) -> #VALUE! | Q79: =IF(K79="","",K79-M79) -> #VALUE! | AA79: =IF(K79=0,"",IF(AND(K79>0,K79>M79),K79-M79,"")) | AB79: =IF(J79=0,"",IF(AND(J79>0,J79>L79),J79-L79,"")) | AE79: Abacaxi
D80: 46027 | E80: Queijo Ralado | F80: 1,000 | G80: kg | H80: RC Frios | I80: Laticinios | K80: 38.99 | M80: 38.99 | N80: IFOOD | P80: =IF(J80="","",J80-L80) | Q80: =IF(K80="","",K80-M80) -> 0 | AA80: =IF(K80=0,"",IF(AND(K80>0,K80>M80),K80-M80,"")) | AB80: =IF(J80=0,"",IF(AND(J80>0,J80>L80),J80-L80,"")) | AE80: Macaxeira
D81: 46027 | E81: Costela de Charque | F81: 5,000 | G81: kg | H81: RC Frios | I81: Proteina | K81: 67.99 | M81: 67.99 | N81: IFOOD | P81: =IF(J81="","",J81-L81) | Q81: =IF(K81="","",K81-M81) -> 0 | AA81: =IF(K81=0,"",IF(AND(K81>0,K81>M81),K81-M81,"")) | AB81: =IF(J81=0,"",IF(AND(J81>0,J81>L81),J81-L81,"")) | AE81: Coco Ralado
D82: 46027 | E82: Calabresa | F82: 2,500 | G82: kg | H82: RC Frios | I82: Proteina | K82: 46.49 | M82: 46.49 | N82: IFOOD | P82: =IF(J82="","",J82-L82) | Q82: =IF(K82="","",K82-M82) -> 0 | AA82: =IF(K82=0,"",IF(AND(K82>0,K82>M82),K82-M82,"")) | AB82: =IF(J82=0,"",IF(AND(J82>0,J82>L82),J82-L82,"")) | AE82: Limão
D83: 46027 | E83: Galinha (Coxa/sobrecoxa) | F83: 12,000 | G83: kg | H83: RC Frios | I83: Proteina | K83: 154.85 | M83: 154.85 | N83: IFOOD | P83: =IF(J83="","",J83-L83) | Q83: =IF(K83="","",K83-M83) -> 0 | AA83: =IF(K83=0,"",IF(AND(K83>0,K83>M83),K83-M83,"")) | AB83: =IF(J83=0,"",IF(AND(J83>0,J83>L83),J83-L83,"")) | AE83: Laranja
D84: 46027 | E84: Sobrecoxa Temperada | F84: 5,000 | G84: kg | H84: RC Frios | I84: Proteina | K84: 61.99 | M84: 61.99 | N84: IFOOD | P84: =IF(J84="","",J84-L84) | Q84: =IF(K84="","",K84-M84) -> 0 | AA84: =IF(K84=0,"",IF(AND(K84>0,K84>M84),K84-M84,"")) | AB84: =IF(J84=0,"",IF(AND(J84>0,J84>L84),J84-L84,"")) | AE84: Pimenta Cheiro
D85: 46027 | E85: Galinha (Peito) | F85: 5,000 | G85: kg | H85: RC Frios | I85: Proteina | K85: 70.7 | M85: 70.7 | N85: IFOOD | P85: =IF(J85="","",J85-L85) | Q85: =IF(K85="","",K85-M85) -> 0 | AA85: =IF(K85=0,"",IF(AND(K85>0,K85>M85),K85-M85,"")) | AB85: =IF(J85=0,"",IF(AND(J85>0,J85>L85),J85-L85,"")) | AE85: Queijo Mussarela
D86: 46027 | E86: Alho Triturado | F86: 12,000 | G86: kg | H86: RC Frios | I86: Tempero | K86: 90.36 | M86: 90.36 | N86: IFOOD | P86: =IF(J86="","",J86-L86) | Q86: =IF(K86="","",K86-M86) -> 0 | AA86: =IF(K86=0,"",IF(AND(K86>0,K86>M86),K86-M86,"")) | AB86: =IF(J86=0,"",IF(AND(J86>0,J86>L86),J86-L86,"")) | AE86: Queijo Coalho
D87: 46027 | E87: Queijo Mussarela | F87: 2,176 | G87: kg | H87: Villa Frios | I87: Laticinios | K87: 73.96 | M87: 73.96 | N87: IFOOD | P87: =IF(J87="","",J87-L87) | Q87: =IF(K87="","",K87-M87) -> 0 | AA87: =IF(K87=0,"",IF(AND(K87>0,K87>M87),K87-M87,"")) | AB87: =IF(J87=0,"",IF(AND(J87>0,J87>L87),J87-L87,"")) | AE87: Milho
D88: 46027 | E88: Coxão Mole (Sol) | F88: 4,496 | G88: kg | H88: Novilho Cevado | I88: Proteina | K88: 202.28 | M88: 202.28 | N88: IFOOD | P88: =IF(J88="","",J88-L88) | Q88: =IF(K88="","",K88-M88) -> 0 | AA88: =IF(K88=0,"",IF(AND(K88>0,K88>M88),K88-M88,"")) | AB88: =IF(J88=0,"",IF(AND(J88>0,J88>L88),J88-L88,"")) | AE88: Repolho
D89: 46027 | E89: Charque | F89: 5,000 | G89: kg | H89: Novilho Cevado | I89: Proteina | K89: 185 | M89: 185 | N89: IFOOD | P89: =IF(J89="","",J89-L89) | Q89: =IF(K89="","",K89-M89) -> 0 | AA89: =IF(K89=0,"",IF(AND(K89>0,K89>M89),K89-M89,"")) | AB89: =IF(J89=0,"",IF(AND(J89>0,J89>L89),J89-L89,"")) | AE89: Gelo
D90: 46027 | E90: Batata Palito | F90: 10,000 | G90: kg | H90: Mazid | I90: Insumos | K90: 99.6 | M90: 99.6 | N90: DINHEIRO | P90: =IF(J90="","",J90-L90) | Q90: =IF(K90="","",K90-M90) -> 0 | AA90: =IF(K90=0,"",IF(AND(K90>0,K90>M90),K90-M90,"")) | AB90: =IF(J90=0,"",IF(AND(J90>0,J90>L90),J90-L90,"")) | AE90: Agua Mineral
D91: 46027 | E91: Sacolas Plastica branca (PP-P-M) | F91: 3,000 | G91: kg | H91: Varejão das Embalagens | I91: Descartaveis | K91: 37 | M91: 37 | N91: DINHEIRO | P91: =IF(J91="","",J91-L91) | Q91: =IF(K91="","",K91-M91) -> 0 | AA91: =IF(K91=0,"",IF(AND(K91>0,K91>M91),K91-M91,"")) | AB91: =IF(J91=0,"",IF(AND(J91>0,J91>L91),J91-L91,"")) | AE91: Agua Cozinha
... D118: 46027 | E118: Queijo Coalho | F118: 3,435 | G118: kg | H118: Central das Cestas | I118: Laticinios | K118: 96.18 | M118: 96.18 | N118: IFOOD | P118: =IF(J118="","",J118-L118) | Q118: =IF(K118="","",K118-M118) -> 0 | AA118: =IF(K118=0,"",IF(AND(K118>0,K118>M118),K118-M118,"")) | AB118: =IF(J118=0,"",IF(AND(J118>0,J118>L118),J118-L118,"")) | AE118: Colorau
D119: 46028 | E119: 3.1.1 Receita com Cash - Diaria | F119: . | G119: . | H119: Vendas Diarias | I119: Deposito Dinheiro | J119: 520 | L119: 2363.7 | N119: DINHEIRO | P119: =IF(J119="","",J119-L119) -> -1843.7 | Q119: =IF(K119="","",K119-M119) | AA119: =IF(K119=0,"",IF(AND(K119>0,K119>M119),K119-M119,"")) | AB119: =IF(J119=0,"",IF(AND(J119>0,J119>L119),J119-L119,"")) | AE119: Base Carne
D120: 46028 | E120: 3.1.2 Receita com Cartão (Caixa) | F120: . | G120: . | H120: Vendas Cartão | I120: Recebiveis Cartão | N120: CAIXA ECONOMICA | P120: =IF(J120="","",J120-L120) | Q120: =IF(K120="","",K120-M120) | AA120: =IF(K120=0,"",IF(AND(K120>0,K120>M120),K120-M120,"")) | AB120: =IF(J120=0,"",IF(AND(J120>0,J120>L120),J120-L120,"")) | AE120: Base Galinha
D121: 46028 | E121: 3.1.3 Receita Ifood | F121: . | G121: . | H121: Vendas Ifood | I121: Recebimento Ifood | N121: IFOOD | P121: =IF(J121="","",J121-L121) | Q121: =IF(K121="","",K121-M121) | AA121: =IF(K121=0,"",IF(AND(K121>0,K121>M121),K121-M121,"")) | AB121: =IF(J121=0,"",IF(AND(J121>0,J121>L121),J121-L121,"")) | AE121: Alho Triturado
D122: 46028 | E122: 3.1.4 Receita com Cartão - (Infinity Emp) | F122: . | G122: . | H122: Vendas na Infinity | I122: Recebiveis Cartão/Pix | N122: INFINITY EMPORIO | P122: =IF(J122="","",J122-L122) | Q122: =IF(K122="","",K122-M122) | AA122: =IF(K122=0,"",IF(AND(K122>0,K122>M122),K122-M122,"")) | AB122: =IF(J122=0,"",IF(AND(J122>0,J122>L122),J122-L122,"")) | AE122: Oregano
D123: 46028 | E123: 3.1.5 Receita com Cartão - (Infinity Sil) | F123: . | G123: . | H123: Vendas na Infinity | I123: Recebiveis Cartão/Pix | N123: INFINITY SILVIO | P123: =IF(J123="","",J123-L123) | Q123: =IF(K123="","",K123-M123) | AA123: =IF(K123=0,"",IF(AND(K123>0,K123>M123),K123-M123,"")) | AB123: =IF(J123=0,"",IF(AND(J123>0,J123>L123),J123-L123,"")) | AE123: Sazon camarão
D124: 46028 | E124: Pão ou Torrada | F124: 30 | G124: und | H124: Padaria | I124: Insumos | K124: 14.85 | M124: 14.85 | N124: INFINITY EMPORIO | P124: =IF(J124="","",J124-L124) | Q124: =IF(K124="","",K124-M124) -> 0 | AA124: =IF(K124=0,"",IF(AND(K124>0,K124>M124),K124-M124,"")) | AB124: =IF(J124=0,"",IF(AND(J124>0,J124>L124),J124-L124,"")) | AE124: Sal Parrilha
D125: 46028 | E125: Coxão Mole (Bife) | F125: 2,051 | G125: kg | H125: Só Frios | I125: Proteina | K125: 77.78 | M125: 77.78 | N125: CAIXA ECONOMICA | P125: =IF(J125="","",J125-L125) | Q125: =IF(K125="","",K125-M125) -> 0 | AA125: =IF(K125=0,"",IF(AND(K125>0,K125>M125),K125-M125,"")) | AB125: =IF(J125=0,"",IF(AND(J125>0,J125>L125),J125-L125,"")) | AE125: Docinhos
D126: 46028 | E126: Carne para Guisada (picadão) | F126: 2,568 | G126: kg | H126: Só Frios | I126: Proteina | K126: 74.45 | M126: 74.45 | N126: CAIXA ECONOMICA
D127: 46028 | E127: Carne para Guisada (picadão) | F127: 0,584 | G127: kg | H127: Só Frios | I127: Proteina | K127: 16.93 | M127: 16.93 | N127: CAIXA ECONOMICA
D128: 46028 | E128: Camarão sem Casca | F128: 1,610 | G128: kg | H128: Só Frios | I128: Proteina | K128: 50 | M128: 50 | N128: CAIXA ECONOMICA
D129: 46029 | E129: 3.1.1 Receita com Cash - Diaria | F129: . | G129: . | H129: Vendas Diarias | I129: Deposito Dinheiro | J129: 267 | L129: 1944 | N129: DINHEIRO
D130: 46029 | E130: 3.1.2 Receita com Cartão (Caixa) | F130: . | G130: . | H130: Vendas Cartão | I130: Recebiveis Cartão | N130: CAIXA ECONOMICA
D131: 46029 | E131: 3.1.3 Receita Ifood | F131: . | G131: . | H131: Vendas Ifood | I131: Recebimento Ifood | N131: IFOOD | AE131: BEBIDAS
D132: 46029 | E132: 3.1.4 Receita com Cartão - (Infinity Emp) | F132: . | G132: . | H132: Vendas na Infinity | I132: Recebiveis Cartão/Pix | N132: INFINITY EMPORIO | P132: =IF(J132="","",J132-L132) | Q132: =IF(K132="","",K132-M132) | AA132: =IF(K132=0,"",IF(AND(K132>0,K132>M132),K132-M132,"")) | AB132: =IF(J132=0,"",IF(AND(J132>0,J132>L132),J132-L132,"")) | AE132: Limoneto
D133: 46029 | E133: 3.1.5 Receita com Cartão - (Infinity Sil) | F133: . | G133: . | H133: Vendas na Infinity | I133: Recebiveis Cartão/Pix | N133: INFINITY SILVIO | P133: =IF(J133="","",J133-L133) | Q133: =IF(K133="","",K133-M133) | AA133: =IF(K133=0,"",IF(AND(K133>0,K133>M133),K133-M133,"")) | AB133: =IF(J133=0,"",IF(AND(J133>0,J133>L133),J133-L133,"")) | AE133: H2o
D134: 46029 | E134: Pão ou Torrada | F134: 30 | G134: und | H134: Padaria | I134: Insumos | K134: 15 | M134: 15 | N134: INFINITY SILVIO | P134: =IF(J134="","",J134-L134) | Q134: =IF(K134="","",K134-M134) -> 0 | AA134: =IF(K134=0,"",IF(AND(K134>0,K134>M134),K134-M134,"")) | AB134: =IF(J134=0,"",IF(AND(J134>0,J134>L134),J134-L134,"")) | AE134: h2o Limao
D135: 46029 | E135: Brownie | F135: 18 | G135: und | H135: Brownie | I135: Insumos | K135: 81 | M135: 81 | N135: CAIXA ECONOMICA | P135: =IF(J135="","",J135-L135) | Q135: =IF(K135="","",K135-M135) -> 0 | AA135: =IF(K135=0,"",IF(AND(K135>0,K135>M135),K135-M135,"")) | AB135: =IF(J135=0,"",IF(AND(J135>0,J135>L135),J135-L135,"")) | AE135: Antartica 1 Litro
D136: 46029 | E136: Carne para Guisada (picadão) | F136: 2,576 | G136: kg | H136: Só Frios | I136: Proteina | K136: 74.68 | M136: 74.68 | N136: CAIXA ECONOMICA | P136: =IF(J136="","",J136-L136) | Q136: =IF(K136="","",K136-M136) -> 0 | AA136: =IF(K136=0,"",IF(AND(K136>0,K136>M136),K136-M136,"")) | AB136: =IF(J136=0,"",IF(AND(J136>0,J136>L136),J136-L136,"")) | AE136: Antartica lata
D137: 46029 | E137: Carne para Guisada (picadão) | F137: 0,622 | G137: kg | H137: Só Frios | I137: Proteina | K137: 18.03 | M137: 18.03 | N137: CAIXA ECONOMICA | P137: =IF(J137="","",J137-L137) | Q137: =IF(K137="","",K137-M137) -> 0 | AA137: =IF(K137=0,"",IF(AND(K137>0,K137>M137),K137-M137,"")) | AB137: =IF(J137=0,"",IF(AND(J137>0,J137>L137),J137-L137,"")) | AE137: Schweppes
D138: 46029 | E138: Toscana Frango | F138: 5,044 | G138: kg | H138: Só Frios | I138: Proteina | K138: 115.96 | M138: 115.96 | N138: CAIXA ECONOMICA | P138: =IF(J138="","",J138-L138) | Q138: =IF(K138="","",K138-M138) -> 0 | AA138: =IF(K138=0,"",IF(AND(K138>0,K138>M138),K138-M138,"")) | AB138: =IF(J138=0,"",IF(AND(J138>0,J138>L138),J138-L138,"")) | AE138: Fanta Lata
D139: 46029 | E139: Galinha (Peito) | F139: 6,495 | G139: kg | H139: Só Frios | I139: Proteina | K139: 103.86 | M139: 103.86 | N139: CAIXA ECONOMICA | AE139: Agua com Gás
D140: . | F140: . | G140: . | H140: . | I140: . | J140: . | K140: . | L140: . | M140: .
D141: 46030 | E141: 3.1.1 Receita com Cash - Diaria | F141: . | G141: . | H141: Vendas Diarias | I141: Deposito Dinheiro | J141: 350 | L141: 350 | N141: DINHEIRO
D142: 46030 | E142: 3.1.2 Receita com Cartão (Caixa) | F142: . | G142: . | H142: Vendas Cartão | I142: Recebiveis Cartão | P142: =IF(J142="","",J142-L142) | Q142: =IF(K142="","",K142-M142) | AA142: =IF(K142=0,"",IF(AND(K142>0,K142>M142),K142-M142,"")) | AB142: =IF(J142=0,"",IF(AND(J142>0,J142>L142),J142-L142,"")) | AE142: POLPAS DE FRUTAS
D143: 46030 | E143: 3.1.3 Receita Ifood | F143: . | G143: . | H143: Vendas Ifood | I143: Recebimento Ifood | P143: =IF(J143="","",J143-L143) | Q143: =IF(K143="","",K143-M143) | AA143: =IF(K143=0,"",IF(AND(K143>0,K143>M143),K143-M143,"")) | AB143: =IF(J143=0,"",IF(AND(J143>0,J143>L143),J143-L143,"")) | AE143: Polpas de Frutas
D144: 46030 | E144: 3.1.4 Receita com Cartão - (Infinity Emp) | F144: . | G144: . | H144: Vendas na Infinity | I144: Recebiveis Cartão/Pix | P144: =IF(J144="","",J144-L144) | Q144: =IF(K144="","",K144-M144) | AA144: =IF(K144=0,"",IF(AND(K144>0,K144>M144),K144-M144,"")) | AB144: =IF(J144=0,"",IF(AND(J144>0,J144>L144),J144-L144,"")) | AE144: Polpa acerola
D145: 46030 | E145: 3.1.5 Receita com Cartão - (Infinity Sil) | F145: . | G145: . | H145: Vendas na Infinity | I145: Recebiveis Cartão/Pix | P145: =IF(J145="","",J145-L145) | Q145: =IF(K145="","",K145-M145) | AA145: =IF(K145=0,"",IF(AND(K145>0,K145>M145),K145-M145,"")) | AB145: =IF(J145=0,"",IF(AND(J145>0,J145>L145),J145-L145,"")) | AE145: Polpa cajá
D146: 46030 | E146: Pão ou Torrada | F146: 30 | G146: und | H146: Padaria | I146: Insumos | K146: 15.9 | M146: 15.9 | N146: INFINITY EMPORIO | P146: =IF(J146="","",J146-L146) | Q146: =IF(K146="","",K146-M146) -> 0 | AA146: =IF(K146=0,"",IF(AND(K146>0,K146>M146),K146-M146,"")) | AB146: =IF(J146=0,"",IF(AND(J146>0,J146>L146),J146-L146,"")) | AE146: Polpa Mangaba
D147: 46030 | E147: Carne para Guisada (picadão) | F147: 2,500 | G147: kg | H147: Só Frios | I147: Proteina | K147: 60.06 | M147: 60.06 | N147: CAIXA ECONOMICA | P147: =IF(J147="","",J147-L147) | Q147: =IF(K147="","",K147-M147) -> 0 | AA147: =IF(K147=0,"",IF(AND(K147>0,K147>M147),K147-M147,"")) | AB147: =IF(J147=0,"",IF(AND(J147>0,J147>L147),J147-L147,"")) | AE147: Polpa Abacaxi Hortela
D148: 46030 | E148: Limão | F148: 20 | G148: und | H148: Só Frios | I148: Frutas | K148: 11.6 | M148: 11.6 | N148: CAIXA ECONOMICA | P148: =IF(J148="","",J148-L148) | Q148: =IF(K148="","",K148-M148) -> 0 | AA148: =IF(K148=0,"",IF(AND(K148>0,K148>M148),K148-M148,"")) | AB148: =IF(J148=0,"",IF(AND(J148>0,J148>L148),J148-L148,"")) | AE148: Polpa Caju
D149: 46030 | E149: Molho de Tomate (Pronto) | F149: 2 | G149: Litro | H149: Só Frios | I149: Insumos | K149: 9.99 | M149: 9.99 | N149: CAIXA ECONOMICA | P149: =IF(J149="","",J149-L149) | Q149: =IF(K149="","",K149-M149) -> 0 | AA149: =IF(K149=0,"",IF(AND(K149>0,K149>M149),K149-M149,"")) | AB149: =IF(J149=0,"",IF(AND(J149>0,J149>L149),J149-L149,"")) | AE149: Polpa Abacaxi
D150: 46030 | E150: Leite em pó | F150: 1 | G150: pct | H150: Menor Preço | I150: Insumos | K150: 6.99 | M150: 6.99 | N150: CAIXA ECONOMICA | P150: =IF(J150="","",J150-L150) | Q150: =IF(K150="","",K150-M150) -> 0 | AA150: =IF(K150=0,"",IF(AND(K150>0,K150>M150),K150-M150,"")) | AB150: =IF(J150=0,"",IF(AND(J150>0,J150>L150),J150-L150,"")) | AE150: Polpa Graviola
D151: 46030 | E151: Compras Diversos | F151: 1 | G151: und | H151: Menor Preço | I151: cereal | K151: 10.39 | M151: 10.39 | N151: CAIXA ECONOMICA | P151: =IF(J151="","",J151-L151) | Q151: =IF(K151="","",K151-M151) -> 0 | AA151: =IF(K151=0,"",IF(AND(K151>0,K151>M151),K151-M151,"")) | AB151: =IF(J151=0,"",IF(AND(J151>0,J151>L151),J151-L151,"")) | AE151: Polpa maracujá
D152: 46030 | E152: Compras Diversos | F152: 3 | G152: und | H152: Menor Preço | I152: barra cereal | K152: 8.37 | M152: 8.37 | N152: CAIXA ECONOMICA | P152: =IF(J152="","",J152-L152) | Q152: =IF(K152="","",K152-M152) -> 0 | AA152: =IF(K152=0,"",IF(AND(K152>0,K152>M152),K152-M152,"")) | AB152: =IF(J152=0,"",IF(AND(J152>0,J152>L152),J152-L152,"")) | AE152: Polpa Pitanga
D153: 46030 | E153: Inhame | F153: 6,485 | G153: kg | H153: Menor Preço | I153: Raiz | K153: 45.33 | M153: 45.33 | N153: CAIXA ECONOMICA | P153: =IF(J153="","",J153-L153) | Q153: =IF(K153="","",K153-M153) -> 0 | AA153: =IF(K153=0,"",IF(AND(K153>0,K153>M153),K153-M153,"")) | AB153: =IF(J153=0,"",IF(AND(J153>0,J153>L153),J153-L153,"")) | AE153: Polpa Uva
D154: 46030 | E154: Batata Palito | F154: 6,000 | G154: kg | H154: Menor Preço | I154: Insumos | K154: 47.98 | M154: 47.98 | N154: CAIXA ECONOMICA | P154: =IF(J154="","",J154-L154) | Q154: =IF(K154="","",K154-M154) -> 0 | AA154: =IF(K154=0,"",IF(AND(K154>0,K154>M154),K154-M154,"")) | AB154: =IF(J154=0,"",IF(AND(J154>0,J154>L154),J154-L154,"")) | AE154: Polpa Morango
D155: 46030 | E155: Compras Diversos | F155: 1 | G155: . | H155: Menor Preço | I155: outros | K155: 2.29 | M155: 2.29 | N155: CAIXA ECONOMICA | P155: =IF(J155="","",J155-L155) | Q155: =IF(K155="","",K155-M155) -> 0 | AA155: =IF(K155=0,"",IF(AND(K155>0,K155>M155),K155-M155,"")) | AB155: =IF(J155=0,"",IF(AND(J155>0,J155>L155),J155-L155,""))
...

Sheet Fluxo de Caixa
C2: Meta de Lucro % = 15% | D2: Faturamento | E2: =E11 -> 7753.7 | F2: =IF(E$2=0,"",E2/E$2) -> 1 | I2: Faturamento | J2: =J11 -> 0 | K2: =IF(J$2=0,"",J2/J$2) | N2: Faturamento | O2: =O11 -> 0 | P2: =IF(O$2=0,"",O2/O$2) | S2: Faturamento | T2: =T11 -> 0 | U2: =IF(T$2=0,"",T2/T$2) | X2: Faturamento | Y2: =Y11 -> 0 | Z2: =IF(Y$2=0,"",Y2/Y$2) | AC2: Faturamento | AD2: =AD11 -> 0 | AE2: =IF(AD$2=0,"",AD2/AD$2) | AG2: Faturamento | AH2: =AH11 -> 0 | AI2: =IF(AH$2=0,"",AH2/AH$2) | AK2: Faturamento | AL2: =AL11 -> 0 | AM2: =IF(AL$2=0,"",AL2/AL$2) | AO2: Faturamento | AP2: =AP11 -> 0 | AQ2: =IF(AP$2=0,"",AP2/AP$2) | AS2: Faturamento | AT2: =AT11 -> 0 | AU2: =IF(AT$2=0,"",AT2/AT$2) | AW2: Faturamento | AX2: =AX11 -> 0 | AY2: =IF(AX$2=0,"",AX2/AX$2) | BA2: Faturamento | BB2: =BB11 -> 0 | BC2: =IF(BB$2=0,"",BB2/BB$2)
C3: Meta de Faturamento dia = R$2.000,00 | D3: Dispesas | E3: =E10 -> 10921.25 | F3: =IF(E$2=0,"",E3/E$2) -> 1.4085211 | I3: Dispesas | J3: =J10 -> 0 | K3: =IF(J$2=0,"",J3/J$2) | N3: Dispesas | O3: =O10 -> 0 | P3: =IF(O$2=0,"",O3/O$2) | S3: Dispesas | T3: =T10 -> 0 | U3: =IF(T$2=0,"",T3/T$2) | X3: Dispesas | Y3: =Y10 -> 0 | Z3: =IF(Y$2=0,"",Y3/Y$2) | AC3: Dispesas | AD3: =AD10 -> 0 | AE3: =IF(AD$2=0,"",AD3/AD$2) | AG3: Dispesas | AH3: =AH10 -> 0 | AI3: =IF(AH$2=0,"",AH3/AH$2) | AK3: Dispesas | AL3: =AL10 -> 0 | AM3: =IF(AL$2=0,"",AL3/AL$2) | AO3: Dispesas | AP3: =AP10 -> 0 | AQ3: =IF(AP$2=0,"",AP3/AP$2) | AS3: Dispesas | AT3: =AT10 -> 0 | AU3: =IF(AT$2=0,"",AT3/AT$2) | AW3: Dispesas | AX3: =AX10 -> 0 | AY3: =IF(AX$2=0,"",AX3/AX$2) | BA3: Dispesas | BB3: =BB10 -> 0 | BC3: =IF(BB$2=0,"",BB3/BB$2)
C4: Meta de Despesas dia = R$1.700,00 | D4: Lucro | E4: =SUM(E2-E3) -> -3167.55 | F4: =IF(E$2=0,"",E4/E$2) -> -0.40852109 | I4: Lucro | J4: =SUM(J2-J3) -> 0 | K4: =IF(J$2=0,"",J4/J$2) | N4: Lucro | O4: =SUM(O2-O3) -> 0 | P4: =IF(O$2=0,"",O4/O$2) | S4: Lucro | T4: =SUM(T2-T3) -> 0 | U4: =IF(T$2=0,"",T4/T$2) | X4: Lucro | Y4: =SUM(Y2-Y3) -> 0 | Z4: =IF(Y$2=0,"",Y4/Y$2) | AC4: Lucro | AD4: =SUM(AD2-AD3) -> 0 | AE4: =IF(AD$2=0,"",AD4/AD$2) | AG4: Lucro | AH4: =SUM(AH2-AH3) -> 0 | AI4: =IF(AH$2=0,"",AH4/AH$2) | AK4: Lucro | AL4: =SUM(AL2-AL3) -> 0 | AM4: =IF(AL$2=0,"",AL4/AL$2) | AO4: Lucro | AP4: =SUM(AP2-AP3) -> 0 | AQ4: =IF(AP$2=0,"",AP4/AP$2) | AS4: Lucro | AT4: =SUM(AT2-AT3) -> 0 | AU4: =IF(AT$2=0,"",AT4/AT$2) | AW4: Lucro | AX4: =SUM(AX2-AX3) -> 0 | AY4: =IF(AX$2=0,"",AX4/AX$2) | BA4: Lucro | BB4: =SUM(BB2-BB3) -> 0 | BC4: =IF(BB$2=0,"",BB4/BB$2)
C5: FLUXO DE CAIXA | D5: REAL | E5: 0 | F5: =IF(E$2=0,"",E5/E$2) -> 0 | I5: REAL | J5: 0 | K5: =IF(J$2=0,"",J5/J$2) | N5: REAL | O5: 0 | P5: =IF(O$2=0,"",O5/O$2) | S5: REAL | T5: 0 | U5: =IF(T$2=0,"",T5/T$2) | X5: REAL | Y5: 0 | Z5: =IF(Y$2=0,"",Y5/Y$2) | AC5: REAL | AD5: 0 | AE5: =IF(AD$2=0,"",AD5/AD$2) | AG5: REAL | AH5: 0 | AI5: =IF(AH$2=0,"",AH5/AH$2) | AK5: REAL | AL5: 0 | AM5: =IF(AL$2=0,"",AL5/AL$2) | AO5: REAL | AP5: 0 | AQ5: =IF(AP$2=0,"",AP5/AP$2) | AS5: REAL | AT5: 0 | AU5: =IF(AT$2=0,"",AT5/AT$2) | AW5: REAL | AX5: 0 | AY5: =IF(AX$2=0,"",AX5/AX$2) | BA5: REAL | BB5: 0 | BC5: =IF(BB$2=0,"",BB5/BB$2)
C6: 2026 | D6: Diferença | E6: =SUM(E4-E5) -> -3167.55 | I6: Diferença | J6: =SUM(J4-J5) -> 0 | N6: Diferença | O6: =SUM(O4-O5) -> 0 | S6: Diferença | T6: =SUM(T4-T5) -> 0 | X6: Diferença | Y6: =SUM(Y4-Y5) -> 0 | AC6: Diferença | AD6: =SUM(AD4-AD5) -> 0 | AG6: Diferença | AH6: =SUM(AH4-AH5) -> 0 | AK6: Diferença | AL6: =SUM(AL4-AL5) -> 0 | AO6: Diferença | AP6: =SUM(AP4-AP5) -> 0 | AS6: Diferença | AT6: =SUM(AT4-AT5) -> 0 | AW6: Diferença | AX6: =SUM(AX4-AX5) -> 0 | BA6: Diferença | BB6: =SUM(BB4-BB5) -> 0 | BE6: MEDIA | BF6: =SUM(BF11/12) -> 646.14167
C8: =YEAR((TODAY())) -> 2026 | D8: JANEIRO | I8: FEVEREIRO | N8: MARÇO | S8: ABRIL | X8: MAIO | AC8: JUNHO | AG8: JULHO | AK8: AGOSTO | AO8: SETEMBRO | AS8: OUTUBRO | AW8: NOVEMBRO | BA8: DEZEMBRO | BE8: Total Ano | BI8: POR PERÍODO | BK8: 45292
D9: PREVISÃO | E9: REALIZADO | F9: A. V. | G9: A.H. | I9: PREVISÃO | J9: REALIZADO | K9: A. V. | L9: A.H. | N9: PREVISÃO | O9: REALIZADO | P9: A. V. | Q9: A.H. | S9: PREVISÃO | T9: REALIZADO | U9: A. V. | V9: A.H. | X9: PREVISÃO | Y9: REALIZADO | Z9: A. V. | AA9: A.H. | AC9: PREVISÃO | AD9: REALIZADO | AE9: A. V. | AF9: A.H. | AG9: PREVISÃO | AH9: REALIZADO | AI9: A. V. | AJ9: A.H. | AK9: PREVISÃO | AL9: REALIZADO | AM9: A. V. | AN9: A.H. | AO9: PREVISÃO | AP9: REALIZADO | AQ9: A. V. | AR9: A.H. | AS9: PREVISÃO | AT9: REALIZADO | AU9: A. V. | AV9: A.H. | AW9: PREVISÃO | AX9: REALIZADO | AY9: A. V. | AZ9: A.H. | BA9: PREVISÃO | BB9: REALIZADO | BC9: A. V. | BD9: A.H. | BE9: PREVISÃO | BF9: REALIZADO | BG9: A. V. Total | BI9: REALIZADO | BJ9: A. V. | BK9: 45657
C10: RECEITA / FATURAMENTO | D10: DESPESAS | E10: =E321 -> 10921.25 | F10: =F321 -> 1.4085211 | I10: DESPESAS | J10: =J321 -> 0 | K10: =K321 | N10: DESPESAS | O10: =O321 -> 0 | P10: =P321 | S10: DESPESAS | T10: =T321 -> 0 | U10: =U321 | X10: DESPESAS | Y10: =Y321 -> 0 | Z10: =Z321 | AC10: DESPESAS | AD10: =AD321 -> 0 | AE10: =AE321 | AG10: DESPESAS | AH10: =AH321 -> 0 | AI10: =AI321 | AK10: DESPESAS | AL10: =AL321 -> 0 | AM10: =AM321 | AO10: DESPESAS | AP10: =AP321 -> 0 | AQ10: =AQ321 | AS10: DESPESAS | AT10: =AT321 -> 0 | AU10: =AU321 | AW10: DESPESAS | AX10: =AX321 -> 0 | AY10: =AY321 | BA10: DESPESAS | BB10: =BB321 -> 0 | BC10: =BC321 | BK10: =ROUND((BK9-BK8)/30,0.1) -> 12
D11: =D12 -> 3276 | E11: =E12 -> 7753.7 | F11: =IF(E$11=0,"",E11/E$11) -> 1 | G11: =IF(A11=0,"",E11/A11-1) | I11: =I12 -> 0 | J11: =J12 -> 0 | K11: =IF(J$11=0,"",J11/J$11) | L11: =IF(E11=0,"",J11/E11-1) -> -1 | N11: =N12 -> 0 | O11: =O12 -> 0 | P11: =IF(O$11=0,"",O11/O$11) | Q11: =IF(J11=0,"",O11/J11-1) | S11: =S12 -> 0 | T11: =T12 -> 0 | U11: =IF(T$11=0,"",T11/T$11) | V11: =IF(O11=0,"",T11/O11-1) | X11: =X12 -> 0 | Y11: =Y12 -> 0 | Z11: =IF(Y$11=0,"",Y11/Y$11) | AA11: =IF(T11=0,"",Y11/T11-1) | AC11: =AC12 -> 0 | AD11: =AD12 -> 0 | AE11: =IF(AD$11=0,"",AD11/AD$11) | AF11: =IF(Y11=0,"",AD11/Y11-1) | AG11: =AG12 -> 0 | AH11: =AH12 -> 0 | AI11: =IF(AH$11=0,"",AH11/AH$11) | AJ11: =IF(AD11=0,"",AH11/AD11-1) | AK11: =AK12 -> 0 | AL11: =AL12 -> 0 | AM11: =IF(AL$11=0,"",AL11/AL$11) | AN11: =IF(AH11=0,"",AL11/AH11-1) | AO11: =AO12 -> 0 | AP11: =AP12 -> 0 | AQ11: =IF(AP$11=0,"",AP11/AP$11) | AR11: =IF(AL11=0,"",AP11/AL11-1) | AS11: =AS12 -> 0 | AT11: =AT12 -> 0 | AU11: =IF(AT$11=0,"",AT11/AT$11) | AV11: =IF(AP11=0,"",AT11/AP11-1) | AW11: =AW12 -> 0 | AX11: =AX12 -> 0 | AY11: =IF(AX$11=0,"",AX11/AX$11) | AZ11: =IF(AT11=0,"",AX11/AT11-1) | BA11: =BA12 -> 0 | BB11: =BB12 -> 0 | BC11: =IF(BB$11=0,"",BB11/BB$11) | BD11: =IF(AX11=0,"",BB11/AX11-1) | BE11: =SUM(D11,I11,N11,S11,X11,AC11,AG11,AK11,AO11,AS11,AW11,BA11) -> 3276 | BF11: =SUM(E11,J11,O11,T11,Y11,AD11,AH11,AL11,AP11,AT11,AX11,BB11) -> 7753.7 | BG11: =IF(BF$11=0,"",BF11/BF$11) -> 1 | BI11: =BI12 -> 0 | BJ11: =IF(BI$11=0,"",BI11/BI$11) | BK11: meses
C12: 3.1 Receita de Vendas | D12: =SUMIFS('Livro Diario - FC'!$J$11:$J1028,'Livro Diario - FC'!$E$11:$E1028,$C$12,'Livro Diario - FC'!$D$11:$D1028,">=01/01"&$C$7,'Livro Diario - FC'!$D$11:$D1028,"<=31/01"&$C$7)+SUM(D13:D22) -> 3276 | E12: =SUMIFS('Livro Diario - FC'!$L$11:$L1028,'Livro Diario - FC'!$E$11:$E1028,$C$12,'Livro Diario - FC'!$D$11:$D1028,">=01/01"&$C$7,'Livro Diario - FC'!$D$11:$D1028,"<=31/01"&$C$7)+SUM(E13:E22) -> 7753.7 | F12: =IF(E$11=0,"",E12/E$11) -> 1 | G12: =IF(A12=0,"",E12/A12-1) | I12: =SUMIFS('Livro Diario - FC'!$J$11:$J1028,'Livro Diario - FC'!$E$11:$E1028,$C$12,'Livro Diario - FC'!$D$11:$D1028,">=01/02"&$C$7,'Livro Diario - FC'!$D$11:$D1028,"<=29/02"&$C$7)+SUM(I13:I22) -> 0 | J12: =SUMIFS('Livro Diario - FC'!$L$11:$L1028,'Livro Diario - FC'!$E$11:$E1028,$C$12,'Livro Diario - FC'!$D$11:$D1028,">=01/02"&$C$7,'Livro Diario - FC'!$D$11:$D1028,"<=29/02"&$C$7)+SUM(J13:J22) -> 0 | K12: =IF(J$11=0,"",J12/J$11) | L12: =IF(E12=0,"",J12/E12-1) -> -1 | N12: =SUMIFS('Livro Diario - FC'!$J$11:$J1028,'Livro Diario - FC'!$E$11:$E1028,$C$12,'Livro Diario - FC'!$D$11:$D1028,">=01/03"&$C$7,'Livro Diario - FC'!$D$11:$D1028,"<=31/03"&$C$7)+SUM(N13:N22) -> 0 | O12: =SUMIFS('Livro Diario - FC'!$L$11:$L1028,'Livro Diario - FC'!$E$11:$E1028,$C$12,'Livro Diario - FC'!$D$11:$D1028,">=01/03"&$C$7,'Livro Diario - FC'!$D$11:$D1028,"<=31/03"&$C$7)+SUM(O13:O22) -> 0 | P12: =IF(O$11=0,"",O12/O$11) | Q12: =IF(J12=0,"",O12/J12-1) | S12: =SUMIFS('Livro Diario - FC'!$J$11:$J1028,'Livro Diario - FC'!$E$11:$E1028,$C$12,'Livro Diario - FC'!$D$11:$D1028,">=01/04"&$C$7,'Livro Diario - FC'!$D$11:$D1028,"<=30/04"&$C$7)+SUM(S13:S22) -> 0 | T12: =SUMIFS('Livro Diario - FC'!$L$11:$L1028,'Livro Diario - FC'!$E$11:$E1028,$C$12,'Livro Diario - FC'!$D$11:$D1028,">=01/04"&$C$7,'Livro Diario - FC'!$D$11:$D1028,"<=30/04"&$C$7)+SUM(T13:T22) -> 0 | U12: =IF(T$11=0,"",T12/T$11) | V12: =IF(O12=0,"",T12/O12-1) | X12: =SUMIFS('Livro Diario - FC'!$J$11:$J1028,'Livro Diario - FC'!$E$11:$E1028,$C$12,'Livro Diario - FC'!$D$11:$D1028,">=01/05"&$C$7,'Livro Diario - FC'!$D$11:$D1028,"<=31/05"&$C$7)+SUM(X13:X22) -> 0 | Y12: =SUMIFS('Livro Diario - FC'!$L$11:$L1028,'Livro Diario - FC'!$E$11:$E1028,$C$12,'Livro Diario - FC'!$D$11:$D1028,">=01/05"&$C$7,'Livro Diario - FC'!$D$11:$D1028,"<=31/05"&$C$7)+SUM(Y13:Y22) -> 0 | Z12: =IF(Y$11=0,"",Y12/Y$11) | AA12: =IF(T12=0,"",Y12/T12-1) | AC12: =SUMIFS('Livro Diario - FC'!$J$11:$J1028,'Livro Diario - FC'!$E$11:$E1028,$C$12,'Livro Diario - FC'!$D$11:$D1028,">=01/06"&$C$7,'Livro Diario - FC'!$D$11:$D1028,"<=30/06"&$C$7)+SUM(AC13:AC22) -> 0 | AD12: =SUMIFS('Livro Diario - FC'!$L$11:$L1028,'Livro Diario - FC'!$E$11:$E1028,$C$12,'Livro Diario - FC'!$D$11:$D1028,">=01/06"&$C$7,'Livro Diario - FC'!$D$11:$D1028,"<=30/06"&$C$7)+SUM(AD13:AD22) -> 0 | AE12: =IF(AD$11=0,"",AD12/AD$11) | AF12: =IF(Y12=0,"",AD12/Y12-1) | AG12: =SUMIFS('Livro Diario - FC'!$J$11:$J1028,'Livro Diario - FC'!$E$11:$E1028,$C$12,'Livro Diario - FC'!$D$11:$D1028,">=01/07"&$C$7,'Livro Diario - FC'!$D$11:$D1028,"<=31/07"&$C$7)+SUM(AG13:AG22) -> 0 | AH12: =SUMIFS('Livro Diario - FC'!$L$11:$L1028,'Livro Diario - FC'!$E$11:$E1028,$C$12,'Livro Diario - FC'!$D$11:$D1028,">=01/07"&$C$7,'Livro Diario - FC'!$D$11:$D1028,"<=31/07"&$C$7)+SUM(AH13:AH22) -> 0 | AI12: =IF(AH$11=0,"",AH12/AH$11) | AJ12: =IF(AD12=0,"",AH12/AD12-1) | AK12: =SUMIFS('Livro Diario - FC'!$J$11:$J1028,'Livro Diario - FC'!$E$11:$E1028,$C$12,'Livro Diario - FC'!$D$11:$D1028,">=01/08"&$C$7,'Livro Diario - FC'!$D$11:$D1028,"<=31/08"&$C$7)+SUM(AK13:AK22) -> 0 | AL12: =SUMIFS('Livro Diario - FC'!$L$11:$L1028,'Livro Diario - FC'!$E$11:$E1028,$C$12,'Livro Diario - FC'!$D$11:$D1028,">=01/08"&$C$7,'Livro Diario - FC'!$D$11:$D1028,"<=31/08"&$C$7)+SUM(AL13:AL22) -> 0 | AM12: =IF(AL$11=0,"",AL12/AL$11) | AN12: =IF(AH12=0,"",AL12/AH12-1) | AO12: =SUMIFS('Livro Diario - FC'!$J$11:$J1028,'Livro Diario - FC'!$E$11:$E1028,$C$12,'Livro Diario - FC'!$D$11:$D1028,">=01/09"&$C$7,'Livro Diario - FC'!$D$11:$D1028,"<=30/09"&$C$7)+SUM(AO13:AO22) -> 0 | AP12: =SUMIFS('Livro Diario - FC'!$L$11:$L1028,'Livro Diario - FC'!$E$11:$E1028,$C$12,'Livro Diario - FC'!$D$11:$D1028,">=01/09"&$C$7,'Livro Diario - FC'!$D$11:$D1028,"<=30/09"&$C$7)+SUM(AP13:AP22) -> 0 | AQ12: =IF(AP$11=0,"",AP12/AP$11) | AR12: =IF(AL12=0,"",AP12/AL12-1) | AS12: =SUMIFS('Livro Diario - FC'!$J$11:$J1028,'Livro Diario - FC'!$E$11:$E1028,$C$12,'Livro Diario - FC'!$D$11:$D1028,">=01/10"&$C$7,'Livro Diario - FC'!$D$11:$D1028,"<=31/10"&$C$7)+SUM(AS13:AS22) -> 0 | AT12: =SUMIFS('Livro Diario - FC'!$L$11:$L1028,'Livro Diario - FC'!$E$11:$E1028,$C$12,'Livro Diario - FC'!$D$11:$D1028,">=01/10"&$C$7,'Livro Diario - FC'!$D$11:$D1028,"<=31/10"&$C$7)+SUM(AT13:AT22) -> 0 | AU12: =IF(AT$11=0,"",AT12/AT$11) | AV12: =IF(AP12=0,"",AT12/AP12-1) | AW12: =SUMIFS('Livro Diario - FC'!$J$11:$J1028,'Livro Diario - FC'!$E$11:$E1028,$C$12,'Livro Diario - FC'!$D$11:$D1028,">=01/11"&$C$7,'Livro Diario - FC'!$D$11:$D1028,"<=30/11"&$C$7)+SUM(AW13:AW22) -> 0 | AX12: =SUMIFS('Livro Diario - FC'!$L$11:$L1028,'Livro Diario - FC'!$E$11:$E1028,$C$12,'Livro Diario - FC'!$D$11:$D1028,">=01/11"&$C$7,'Livro Diario - FC'!$D$11:$D1028,"<=30/11"&$C$7)+SUM(AX13:AX22) -> 0 | AY12: =IF(AX$11=0,"",AX12/AX$11) | AZ12: =IF(AT12=0,"",AX12/AT12-1) | BA12: =SUMIFS('Livro Diario - FC'!$J$11:$J1028,'Livro Diario - FC'!$E$11:$E1028,$C$12,'Livro Diario - FC'!$D$11:$D1028,">=01/12"&$C$7,'Livro Diario - FC'!$D$11:$D1028,"<=31/12"&$C$7)+SUM(BA13:BA22) -> 0 | BB12: =SUMIFS('Livro Diario - FC'!$L$11:$L1028,'Livro Diario - FC'!$E$11:$E1028,$C$12,'Livro Diario - FC'!$D$11:$D1028,">=01/12"&$C$7,'Livro Diario - FC'!$D$11:$D1028,"<=31/12"&$C$7)+SUM(BB13:BB22) -> 0 | BC12: =IF(BB$11=0,"",BB12/BB$11) | BD12: =IF(AX12=0,"",BB12/AX12-1) | BE12: =SUM(D12,I12,N12,S12,X12,AC12,AG12,AK12,AO12,AS12,AW12,BA12) -> 3276 | BF12: =SUM(E12,J12,O12,T12,Y12,AD12,AH12,AL12,AP12,AT12,AX12,BB12) -> 7753.7 | BG12: =IF(BF$11=0,"",BF12/BF$11) -> 1 | BI12: =SUMIFS('Livro Diario - FC'!$L$11:$L1028,'Livro Diario - FC'!$E$11:$E1028,C13,'Livro Diario - FC'!$D$11:$D1028,">="&$BK$8,'Livro Diario - FC'!$D$11:$D1028,"<="&$BK$9)+SUM(BI13:BI22) -> 0 | BJ12: =IF(BI$11=0,"",BI12/BI$11)
C13: ='Livro Diario - FC'!AE12 -> 3.1.1 Receita com Cash - Diaria | D13: =SUMIFS('Livro Diario - FC'!$J$11:$J1028,'Livro Diario - FC'!$E$11:$E1028,$C$13,'Livro Diario - FC'!$D$11:$D1028,">=01/01"&$C$7,'Livro Diario - FC'!$D$11:$D1028,"<=31/01"&$C$7) -> 3276 | E13: =SUMIFS('Livro Diario - FC'!$L$11:$L1028,'Livro Diario - FC'!$E$11:$E1028,$C$13,'Livro Diario - FC'!$D$11:$D1028,">=01/01"&$C$7,'Livro Diario - FC'!$D$11:$D1028,"<=31/01"&$C$7) -> 7753.7 | F13: =IF(E$11=0,"",E13/E$11) -> 1 | G13: =IF(A13=0,"",E13/A13-1) | I13: =SUMIFS('Livro Diario - FC'!$J$11:$J1028,'Livro Diario - FC'!$E$11:$E1028,$C$13,'Livro Diario - FC'!$D$11:$D1028,">=01/02"&$C$7,'Livro Diario - FC'!$D$11:$D1028,"<=29/02"&$C$7) -> 0 | J13: =SUMIFS('Livro Diario - FC'!$L$11:$L1028,'Livro Diario - FC'!$E$11:$E1028,$C$13,'Livro Diario - FC'!$D$11:$D1028,">=01/02"&$C$7,'Livro Diario - FC'!$D$11:$D1028,"<=29/02"&$C$7) -> 0 | K13: =IF(J$11=0,"",J13/J$11) | L13: =IF(E13=0,"",J13/E13-1) -> -1 | N13: =SUMIFS('Livro Diario - FC'!$J$11:$J1028,'Livro Diario - FC'!$E$11:$E1028,$C$13,'Livro Diario - FC'!$D$11:$D1028,">=01/03"&$C$7,'Livro Diario - FC'!$D$11:$D1028,"<=31/03"&$C$7) -> 0 | O13: =SUMIFS('Livro Diario - FC'!$L$11:$L1028,'Livro Diario - FC'!$E$11:$E1028,$C$13,'Livro Diario - FC'!$D$11:$D1028,">=01/03"&$C$7,'Livro Diario - FC'!$D$11:$D1028,"<=31/03"&$C$7) -> 0 | P13: =IF(O$11=0,"",O13/O$11) | Q13: =IF(J13=0,"",O13/J13-1) | S13: =SUMIFS('Livro Diario - FC'!$J$11:$J1028,'Livro Diario - FC'!$E$11:$E1028,$C$13,'Livro Diario - FC'!$D$11:$D1028,">=01/04"&$C$7,'Livro Diario - FC'!$D$11:$D1028,"<=30/04"&$C$7) -> 0 | T13: =SUMIFS('Livro Diario - FC'!$L$11:$L1028,'Livro Diario - FC'!$E$11:$E1028,$C$13,'Livro Diario - FC'!$D$11:$D1028,">=01/04"&$C$7,'Livro Diario - FC'!$D$11:$D1028,"<=30/04"&$C$7) -> 0 | U13: =IF(T$11=0,"",T13/T$11) | V13: =IF(O13=0,"",T13/O13-1) | X13: =SUMIFS('Livro Diario - FC'!$J$11:$J1028,'Livro Diario - FC'!$E$11:$E1028,$C$13,'Livro Diario - FC'!$D$11:$D1028,">=01/05"&$C$7,'Livro Diario - FC'!$D$11:$D1028,"<=31/05"&$C$7) -> 0 | Y13: =SUMIFS('Livro Diario - FC'!$L$11:$L1028,'Livro Diario - FC'!$E$11:$E1028,$C$13,'Livro Diario - FC'!$D$11:$D1028,">=01/05"&$C$7,'Livro Diario - FC'!$D$11:$D1028,"<=31/05"&$C$7) -> 0 | Z13: =IF(Y$11=0,"",Y13/Y$11) | AA13: =IF(T13=0,"",Y13/T13-1) | AC13: =SUMIFS('Livro Diario - FC'!$J$11:$J1028,'Livro Diario - FC'!$E$11:$E1028,$C$13,'Livro Diario - FC'!$D$11:$D1028,">=01/06"&$C$7,'Livro Diario - FC'!$D$11:$D1028,"<=30/06"&$C$7) -> 0 | AD13: =SUMIFS('Livro Diario - FC'!$L$11:$L1028,'Livro Diario - FC'!$E$11:$E1028,$C$13,'Livro Diario - FC'!$D$11:$D1028,">=01/06"&$C$7,'Livro Diario - FC'!$D$11:$D1028,"<=30/06"&$C$7) -> 0 | AE13: =IF(AD$11=0,"",AD13/AD$11) | AF13: =IF(Y13=0,"",AD13/Y13-1) | AG13: =SUMIFS('Livro Diario - FC'!$J$11:$J1028,'Livro Diario - FC'!$E$11:$E1028,$C$13,'Livro Diario - FC'!$D$11:$D1028,">=01/07"&$C$7,'Livro Diario - FC'!$D$11:$D1028,"<=31/07"&$C$7) -> 0 | AH13: =SUMIFS('Livro Diario - FC'!$L$11:$L1028,'Livro Diario - FC'!$E$11:$E1028,$C$13,'Livro Diario - FC'!$D$11:$D1028,">=01/07"&$C$7,'Livro Diario - FC'!$D$11:$D1028,"<=31/07"&$C$7) -> 0 | AI13: =IF(AH$11=0,"",AH13/AH$11) | AJ13: =IF(AD13=0,"",AH13/AD13-1) | AK13: =SUMIFS('Livro Diario - FC'!$J$11:$J1028,'Livro Diario - FC'!$E$11:$E1028,$C$13,'Livro Diario - FC'!$D$11:$D1028,">=01/08"&$C$7,'Livro Diario - FC'!$D$11:$D1028,"<=31/08"&$C$7) -> 0 | AL13: =SUMIFS('Livro Diario - FC'!$L$11:$L1028,'Livro Diario - FC'!$E$11:$E1028,$C$13,'Livro Diario - FC'!$D$11:$D1028,">=01/08"&$C$7,'Livro Diario - FC'!$D$11:$D1028,"<=31/08"&$C$7) -> 0 | AM13: =IF(AL$11=0,"",AL13/AL$11) | AN13: =IF(AH13=0,"",AL13/AH13-1) | AO13: =SUMIFS('Livro Diario - FC'!$J$11:$J1028,'Livro Diario - FC'!$E$11:$E1028,$C$13,'Livro Diario - FC'!$D$11:$D1028,">=01/09"&$C$7,'Livro Diario - FC'!$D$11:$D1028,"<=30/09"&$C$7) -> 0 | AP13: =SUMIFS('Livro Diario - FC'!$L$11:$L1028,'Livro Diario - FC'!$E$11:$E1028,$C$13,'Livro Diario - FC'!$D$11:$D1028,">=01/09"&$C$7,'Livro Diario - FC'!$D$11:$D1028,"<=30/09"&$C$7) -> 0 | AQ13: =IF(AP$11=0,"",AP13/AP$11) | AR13: =IF(AL13=0,"",AP13/AL13-1) | AS13: =SUMIFS('Livro Diario - FC'!$J$11:$J1028,'Livro Diario - FC'!$E$11:$E1028,$C$13,'Livro Diario - FC'!$D$11:$D1028,">=01/10"&$C$7,'Livro Diario - FC'!$D$11:$D1028,"<=31/10"&$C$7) -> 0 | AT13: =SUMIFS('Livro Diario - FC'!$L$11:$L1028,'Livro Diario - FC'!$E$11:$E1028,$C$13,'Livro Diario - FC'!$D$11:$D1028,">=01/10"&$C$7,'Livro Diario - FC'!$D$11:$D1028,"<=31/10"&$C$7) -> 0 | AU13: =IF(AT$11=0,"",AT13/AT$11) | AV13: =IF(AP13=0,"",AT13/AP13-1) | AW13: =SUMIFS('Livro Diario - FC'!$J$11:$J1028,'Livro Diario - FC'!$E$11:$E1028,$C$13,'Livro Diario - FC'!$D$11:$D1028,">=01/11"&$C$7,'Livro Diario - FC'!$D$11:$D1028,"<=30/11"&$C$7) -> 0 | AX13: =SUMIFS('Livro Diario - FC'!$L$11:$L1028,'Livro Diario - FC'!$E$11:$E1028,$C$13,'Livro Diario - FC'!$D$11:$D1028,">=01/11"&$C$7,'Livro Diario - FC'!$D$11:$D1028,"<=30/11"&$C$7) -> 0 | AY13: =IF(AX$11=0,"",AX13/AX$11) | AZ13: =IF(AT13=0,"",AX13/AT13-1) | BA13: =SUMIFS('Livro Diario - FC'!$J$11:$J1028,'Livro Diario - FC'!$E$11:$E1028,$C$13,'Livro Diario - FC'!$D$11:$D1028,">=01/12"&$C$7,'Livro Diario - FC'!$D$11:$D1028,"<=31/12"&$C$7) -> 0 | BB13: =SUMIFS('Livro Diario - FC'!$L$11:$L1028,'Livro Diario - FC'!$E$11:$E1028,$C$13,'Livro Diario - FC'!$D$11:$D1028,">=01/12"&$C$7,'Livro Diario - FC'!$D$11:$D1028,"<=31/12"&$C$7) -> 0 | BC13: =IF(BB$11=0,"",BB13/BB$11) | BD13: =IF(AX13=0,"",BB13/AX13-1) | BE13: =SUM(D13,I13,N13,S13,X13,AC13,AG13,AK13,AO13,AS13,AW13,BA13) -> 3276 | BF13: =SUM(E13,J13,O13,T13,Y13,AD13,AH13,AL13,AP13,AT13,AX13,BB13) -> 7753.7 | BI13: =SUMIFS('Livro Diario - FC'!$L$11:$L1028,'Livro Diario - FC'!$E$11:$E1028,C13,'Livro Diario - FC'!$D$11:$D1028,">="&$BK$8,'Livro Diario - FC'!$D$11:$D1028,"<="&$BK$9) -> 0
C14: ='Livro Diario - FC'!AE13 -> 3.1.2 Receita com Cartão (Caixa) | D14: =SUMIFS('Livro Diario - FC'!$J$11:$J1028,'Livro Diario - FC'!$E$11:$E1028,$C$14,'Livro Diario - FC'!$D$11:$D1028,">=01/01"&$C$7,'Livro Diario - FC'!$D$11:$D1028,"<=31/01"&$C$7) -> 0 | E14: =SUMIFS('Livro Diario - FC'!$L$11:$L1028,'Livro Diario - FC'!$E$11:$E1028,$C$14,'Livro Diario - FC'!$D$11:$D1028,">=01/01"&$C$7,'Livro Diario - FC'!$D$11:$D1028,"<=31/01"&$C$7) -> 0 | F14: =IF(E$11=0,"",E14/E$11) -> 0 | G14: =IF(A14=0,"",E14/A14-1) | I14: =SUMIFS('Livro Diario - FC'!$J$11:$J1028,'Livro Diario - FC'!$E$11:$E1028,$C$14,'Livro Diario - FC'!$D$11:$D1028,">=01/02"&$C$7,'Livro Diario - FC'!$D$11:$D1028,"<=29/02"&$C$7) -> 0 | J14: =SUMIFS('Livro Diario - FC'!$L$11:$L1028,'Livro Diario - FC'!$E$11:$E1028,$C$14,'Livro Diario - FC'!$D$11:$D1028,">=01/02"&$C$7,'Livro Diario - FC'!$D$11:$D1028,"<=29/02"&$C$7) -> 0 | K14: =IF(J$11=0,"",J14/J$11) | L14: =IF(E14=0,"",J14/E14-1) | N14: =SUMIFS('Livro Diario - FC'!$J$11:$J1028,'Livro Diario - FC'!$E$11:$E1028,$C$14,'Livro Diario - FC'!$D$11:$D1028,">=01/03"&$C$7,'Livro Diario - FC'!$D$11:$D1028,"<=31/03"&$C$7) -> 0 | O14: =SUMIFS('Livro Diario - FC'!$L$11:$L1028,'Livro Diario - FC'!$E$11:$E1028,$C$14,'Livro Diario - FC'!$D$11:$D1028,">=01/03"&$C$7,'Livro Diario - FC'!$D$11:$D1028,"<=31/03"&$C$7) -> 0 | P14: =IF(O$11=0,"",O14/O$11) | Q14: =IF(J14=0,"",O14/J14-1) | S14: =SUMIFS('Livro Diario - FC'!$J$11:$J1028,'Livro Diario - FC'!$E$11:$E1028,$C$14,'Livro Diario - FC'!$D$11:$D1028,">=01/04"&$C$7,'Livro Diario - FC'!$D$11:$D1028,"<=30/04"&$C$7) -> 0 | T14: =SUMIFS('Livro Diario - FC'!$L$11:$L1028,'Livro Diario - FC'!$E$11:$E1028,$C$14,'Livro Diario - FC'!$D$11:$D1028,">=01/04"&$C$7,'Livro Diario - FC'!$D$11:$D1028,"<=30/04"&$C$7) -> 0 | U14: =IF(T$11=0,"",T14/T$11) | V14: =IF(O14=0,"",T14/O14-1) | X14: =SUMIFS('Livro Diario - FC'!$J$11:$J1028,'Livro Diario - FC'!$E$11:$E1028,$C$14,'Livro Diario - FC'!$D$11:$D1028,">=01/05"&$C$7,'Livro Diario - FC'!$D$11:$D1028,"<=31/05"&$C$7) -> 0 | Y14: =SUMIFS('Livro Diario - FC'!$L$11:$L1028,'Livro Diario - FC'!$E$11:$E1028,$C$14,'Livro Diario - FC'!$D$11:$D1028,">=01/05"&$C$7,'Livro Diario - FC'!$D$11:$D1028,"<=31/05"&$C$7) -> 0 | Z14: =IF(Y$11=0,"",Y14/Y$11) | AA14: =IF(T14=0,"",Y14/T14-1) | AC14: =SUMIFS('Livro Diario - FC'!$J$11:$J1028,'Livro Diario - FC'!$E$11:$E1028,$C$14,'Livro Diario - FC'!$D$11:$D1028,">=01/06"&$C$7,'Livro Diario - FC'!$D$11:$D1028,"<=30/06"&$C$7) -> 0 | AD14: =SUMIFS('Livro Diario - FC'!$L$11:$L1028,'Livro Diario - FC'!$E$11:$E1028,$C$14,'Livro Diario - FC'!$D$11:$D1028,">=01/06"&$C$7,'Livro Diario - FC'!$D$11:$D1028,"<=30/06"&$C$7) -> 0 | AE14: =IF(AD$11=0,"",AD14/AD$11) | AF14: =IF(Y14=0,"",AD14/Y14-1) | AG14: =SUMIFS('Livro Diario - FC'!$J$11:$J1028,'Livro Diario - FC'!$E$11:$E1028,$C$14,'Livro Diario - FC'!$D$11:$D1028,">=01/07"&$C$7,'Livro Diario - FC'!$D$11:$D1028,"<=31/07"&$C$7) -> 0 | AH14: =SUMIFS('Livro Diario - FC'!$L$11:$L1028,'Livro Diario - FC'!$E$11:$E1028,$C$14,'Livro Diario - FC'!$D$11:$D1028,">=01/07"&$C$7,'Livro Diario - FC'!$D$11:$D1028,"<=31/07"&$C$7) -> 0 | AI14: =IF(AH$11=0,"",AH14/AH$11) | AJ14: =IF(AD14=0,"",AH14/AD14-1) | AK14: =SUMIFS('Livro Diario - FC'!$J$11:$J1028,'Livro Diario - FC'!$E$11:$E1028,$C$14,'Livro Diario - FC'!$D$11:$D1028,">=01/08"&$C$7,'Livro Diario - FC'!$D$11:$D1028,"<=31/08"&$C$7) -> 0 | AL14: =SUMIFS('Livro Diario - FC'!$L$11:$L1028,'Livro Diario - FC'!$E$11:$E1028,$C$14,'Livro Diario - FC'!$D$11:$D1028,">=01/08"&$C$7,'Livro Diario - FC'!$D$11:$D1028,"<=31/08"&$C$7) -> 0 | AM14: =IF(AL$11=0,"",AL14/AL$11) | AN14: =IF(AH14=0,"",AL14/AH14-1) | AO14: =SUMIFS('Livro Diario - FC'!$J$11:$J1028,'Livro Diario - FC'!$E$11:$E1028,$C$14,'Livro Diario - FC'!$D$11:$D1028,">=01/09"&$C$7,'Livro Diario - FC'!$D$11:$D1028,"<=30/09"&$C$7) -> 0 | AP14: =SUMIFS('Livro Diario - FC'!$L$11:$L1028,'Livro Diario - FC'!$E$11:$E1028,$C$14,'Livro Diario - FC'!$D$11:$D1028,">=01/09"&$C$7,'Livro Diario - FC'!$D$11:$D1028,"<=30/09"&$C$7) -> 0 | AQ14: =IF(AP$11=0,"",AP14/AP$11) | AR14: =IF(AL14=0,"",AP14/AL14-1) | AS14: =SUMIFS('Livro Diario - FC'!$J$11:$J1028,'Livro Diario - FC'!$E$11:$E1028,$C$14,'Livro Diario - FC'!$D$11:$D1028,">=01/10"&$C$7,'Livro Diario - FC'!$D$11:$D1028,"<=31/10"&$C$7) -> 0 | AT14: =SUMIFS('Livro Diario - FC'!$L$11:$L1028,'Livro Diario - FC'!$E$11:$E1028,$C$14,'Livro Diario - FC'!$D$11:$D1028,">=01/10"&$C$7,'Livro Diario - FC'!$D$11:$D1028,"<=31/10"&$C$7) -> 0 | AU14: =IF(AT$11=0,"",AT14/AT$11) | AV14: =IF(AP14=0,"",AT14/AP14-1) | AW14: =SUMIFS('Livro Diario - FC'!$J$11:$J1028,'Livro Diario - FC'!$E$11:$E1028,$C$14,'Livro Diario - FC'!$D$11:$D1028,">=01/11"&$C$7,'Livro Diario - FC'!$D$11:$D1028,"<=30/11"&$C$7) -> 0 | AX14: =SUMIFS('Livro Diario - FC'!$L$11:$L1028,'Livro Diario - FC'!$E$11:$E1028,$C$14,'Livro Diario - FC'!$D$11:$D1028,">=01/11"&$C$7,'Livro Diario - FC'!$D$11:$D1028,"<=30/11"&$C$7) -> 0 | AY14: =IF(AX$11=0,"",AX14/AX$11) | AZ14: =IF(AT14=0,"",AX14/AT14-1) | BA14: =SUMIFS('Livro Diario - FC'!$J$11:$J1028,'Livro Diario - FC'!$E$11:$E1028,$C$14,'Livro Diario - FC'!$D$11:$D1028,">=01/12"&$C$7,'Livro Diario - FC'!$D$11:$D1028,"<=31/12"&$C$7) -> 0 | BB14: =SUMIFS('Livro Diario - FC'!$L$11:$L1028,'Livro Diario - FC'!$E$11:$E1028,$C$14,'Livro Diario - FC'!$D$11:$D1028,">=01/12"&$C$7,'Livro Diario - FC'!$D$11:$D1028,"<=31/12"&$C$7) -> 0 | BC14: =IF(BB$11=0,"",BB14/BB$11) | BD14: =IF(AX14=0,"",BB14/AX14-1) | BE14: =SUM(D14,I14,N14,S14,X14,AC14,AG14,AK14,AO14,AS14,AW14,BA14) -> 0 | BF14: =SUM(E14,J14,O14,T14,Y14,AD14,AH14,AL14,AP14,AT14,AX14,BB14) -> 0 | BI14: =SUMIFS('Livro Diario - FC'!$L$11:$L1028,'Livro Diario - FC'!$E$11:$E1028,C14,'Livro Diario - FC'!$D$11:$D1028,">="&$BK$8,'Livro Diario - FC'!$D$11:$D1028,"<="&$BK$9) -> 0
C15: ='Livro Diario - FC'!AE14 -> 3.1.3 Receita Ifood | D15: =SUMIFS('Livro Diario - FC'!$J$11:$J1028,'Livro Diario - FC'!$E$11:$E1028,$C$15,'Livro Diario - FC'!$D$11:$D1028,">=01/01"&$C$7,'Livro Diario - FC'!$D$11:$D1028,"<=31/01"&$C$7) -> 0 | E15: =SUMIFS('Livro Diario - FC'!$L$11:$L1028,'Livro Diario - FC'!$E$11:$E1028,$C$15,'Livro Diario - FC'!$D$11:$D1028,">=01/01"&$C$7,'Livro Diario - FC'!$D$11:$D1028,"<=31/01"&$C$7) -> 0 | F15: =IF(E$11=0,"",E15/E$11) -> 0 | G15: =IF(A15=0,"",E15/A15-1) | I15: =SUMIFS('Livro Diario - FC'!$J$11:$J1028,'Livro Diario - FC'!$E$11:$E1028,$C$15,'Livro Diario - FC'!$D$11:$D1028,">=01/02"&$C$7,'Livro Diario - FC'!$D$11:$D1028,"<=29/02"&$C$7) -> 0 | J15: =SUMIFS('Livro Diario - FC'!$L$11:$L1028,'Livro Diario - FC'!$E$11:$E1028,$C$15,'Livro Diario - FC'!$D$11:$D1028,">=01/02"&$C$7,'Livro Diario - FC'!$D$11:$D1028,"<=29/02"&$C$7) -> 0 | K15: =IF(J$11=0,"",J15/J$11) | L15: =IF(E15=0,"",J15/E15-1) | N15: =SUMIFS('Livro Diario - FC'!$J$11:$J1028,'Livro Diario - FC'!$E$11:$E1028,$C$15,'Livro Diario - FC'!$D$11:$D1028,">=01/03"&$C$7,'Livro Diario - FC'!$D$11:$D1028,"<=31/03"&$C$7) -> 0 | O15: =SUMIFS('Livro Diario - FC'!$L$11:$L1028,'Livro Diario - FC'!$E$11:$E1028,$C$15,'Livro Diario - FC'!$D$11:$D1028,">=01/03"&$C$7,'Livro Diario - FC'!$D$11:$D1028,"<=31/03"&$C$7) -> 0 | P15: =IF(O$11=0,"",O15/O$11) | Q15: =IF(J15=0,"",O15/J15-1) | S15: =SUMIFS('Livro Diario - FC'!$J$11:$J1028,'Livro Diario - FC'!$E$11:$E1028,$C$15,'Livro Diario - FC'!$D$11:$D1028,">=01/04"&$C$7,'Livro Diario - FC'!$D$11:$D1028,"<=30/04"&$C$7) -> 0 | T15: =SUMIFS('Livro Diario - FC'!$L$11:$L1028,'Livro Diario - FC'!$E$11:$E1028,$C$15,'Livro Diario - FC'!$D$11:$D1028,">=01/04"&$C$7,'Livro Diario - FC'!$D$11:$D1028,"<=30/04"&$C$7) -> 0 | U15: =IF(T$11=0,"",T15/T$11) | V15: =IF(O15=0,"",T15/O15-1) | X15: =SUMIFS('Livro Diario - FC'!$J$11:$J1028,'Livro Diario - FC'!$E$11:$E1028,$C$15,'Livro Diario - FC'!$D$11:$D1028,">=01/05"&$C$7,'Livro Diario - FC'!$D$11:$D1028,"<=31/05"&$C$7) -> 0 | Y15: =SUMIFS('Livro Diario - FC'!$L$11:$L1028,'Livro Diario - FC'!$E$11:$E1028,$C$15,'Livro Diario - FC'!$D$11:$D1028,">=01/05"&$C$7,'Livro Diario - FC'!$D$11:$D1028,"<=31/05"&$C$7) -> 0 | Z15: =IF(Y$11=0,"",Y15/Y$11) | AA15: =IF(T15=0,"",Y15/T15-1) | AC15: =SUMIFS('Livro Diario - FC'!$J$11:$J1028,'Livro Diario - FC'!$E$11:$E1028,$C$15,'Livro Diario - FC'!$D$11:$D1028,">=01/06"&$C$7,'Livro Diario - FC'!$D$11:$D1028,"<=30/06"&$C$7) -> 0 | AD15: =SUMIFS('Livro Diario - FC'!$L$11:$L1028,'Livro Diario - FC'!$E$11:$E1028,$C$15,'Livro Diario - FC'!$D$11:$D1028,">=01/06"&$C$7,'Livro Diario - FC'!$D$11:$D1028,"<=30/06"&$C$7) -> 0 | AE15: =IF(AD$11=0,"",AD15/AD$11) | AF15: =IF(Y15=0,"",AD15/Y15-1) | AG15: =SUMIFS('Livro Diario - FC'!$J$11:$J1028,'Livro Diario - FC'!$E$11:$E1028,$C$15,'Livro Diario - FC'!$D$11:$D1028,">=01/07"&$C$7,'Livro Diario - FC'!$D$11:$D1028,"<=31/07"&$C$7) -> 0 | AH15: =SUMIFS('Livro Diario - FC'!$L$11:$L1028,'Livro Diario - FC'!$E$11:$E1028,$C$15,'Livro Diario - FC'!$D$11:$D1028,">=01/07"&$C$7,'Livro Diario - FC'!$D$11:$D1028,"<=31/07"&$C$7) -> 0 | AI15: =IF(AH$11=0,"",AH15/AH$11) | AJ15: =IF(AD15=0,"",AH15/AD15-1) | AK15: =SUMIFS('Livro Diario - FC'!$J$11:$J1028,'Livro Diario - FC'!$E$11:$E1028,$C$15,'Livro Diario - FC'!$D$11:$D1028,">=01/08"&$C$7,'Livro Diario - FC'!$D$11:$D1028,"<=31/08"&$C$7) -> 0 | AL15: =SUMIFS('Livro Diario - FC'!$L$11:$L1028,'Livro Diario - FC'!$E$11:$E1028,$C$15,'Livro Diario - FC'!$D$11:$D1028,">=01/08"&$C$7,'Livro Diario - FC'!$D$11:$D1028,"<=31/08"&$C$7) -> 0 | AM15: =IF(AL$11=0,"",AL15/AL$11) | AN15: =IF(AH15=0,"",AL15/AH15-1) | AO15: =SUMIFS('Livro Diario - FC'!$J$11:$J1028,'Livro Diario - FC'!$E$11:$E1028,$C$15,'Livro Diario - FC'!$D$11:$D1028,">=01/09"&$C$7,'Livro Diario - FC'!$D$11:$D1028,"<=30/09"&$C$7) -> 0 | AP15: =SUMIFS('Livro Diario - FC'!$L$11:$L1028,'Livro Diario - FC'!$E$11:$E1028,$C$15,'Livro Diario - FC'!$D$11:$D1028,">=01/09"&$C$7,'Livro Diario - FC'!$D$11:$D1028,"<=30/09"&$C$7) -> 0 | AQ15: =IF(AP$11=0,"",AP15/AP$11) | AR15: =IF(AL15=0,"",AP15/AL15-1) | AS15: =SUMIFS('Livro Diario - FC'!$J$11:$J1028,'Livro Diario - FC'!$E$11:$E1028,$C$15,'Livro Diario - FC'!$D$11:$D1028,">=01/10"&$C$7,'Livro Diario - FC'!$D$11:$D1028,"<=31/10"&$C$7) -> 0 | AT15: =SUMIFS('Livro Diario - FC'!$L$11:$L1028,'Livro Diario - FC'!$E$11:$E1028,$C$15,'Livro Diario - FC'!$D$11:$D1028,">=01/10"&$C$7,'Livro Diario - FC'!$D$11:$D1028,"<=31/10"&$C$7) -> 0 | AU15: =IF(AT$11=0,"",AT15/AT$11) | AV15: =IF(AP15=0,"",AT15/AP15-1) | AW15: =SUMIFS('Livro Diario - FC'!$J$11:$J1028,'Livro Diario - FC'!$E$11:$E1028,$C$15,'Livro Diario - FC'!$D$11:$D1028,">=01/11"&$C$7,'Livro Diario - FC'!$D$11:$D1028,"<=30/11"&$C$7) -> 0 | AX15: =SUMIFS('Livro Diario - FC'!$L$11:$L1028,'Livro Diario - FC'!$E$11:$E1028,$C$15,'Livro Diario - FC'!$D$11:$D1028,">=01/11"&$C$7,'Livro Diario - FC'!$D$11:$D1028,"<=30/11"&$C$7) -> 0 | AY15: =IF(AX$11=0,"",AX15/AX$11) | AZ15: =IF(AT15=0,"",AX15/AT15-1) | BA15: =SUMIFS('Livro Diario - FC'!$J$11:$J1028,'Livro Diario - FC'!$E$11:$E1028,$C$15,'Livro Diario - FC'!$D$11:$D1028,">=01/12"&$C$7,'Livro Diario - FC'!$D$11:$D1028,"<=31/12"&$C$7) -> 0 | BB15: =SUMIFS('Livro Diario - FC'!$L$11:$L1028,'Livro Diario - FC'!$E$11:$E1028,$C$15,'Livro Diario - FC'!$D$11:$D1028,">=01/12"&$C$7,'Livro Diario - FC'!$D$11:$D1028,"<=31/12"&$C$7) -> 0 | BC15: =IF(BB$11=0,"",BB15/BB$11) | BD15: =IF(AX15=0,"",BB15/AX15-1) | BE15: =SUM(D15,I15,N15,S15,X15,AC15,AG15,AK15,AO15,AS15,AW15,BA15) -> 0 | BF15: =SUM(E15,J15,O15,T15,Y15,AD15,AH15,AL15,AP15,AT15,AX15,BB15) -> 0 | BI15: =SUMIFS('Livro Diario - FC'!$L$11:$L1028,'Livro Diario - FC'!$E$11:$E1028,C15,'Livro Diario - FC'!$D$11:$D1028,">="&$BK$8,'Livro Diario - FC'!$D$11:$D1028,"<="&$BK$9) -> 0
C16: ='Livro Diario - FC'!AE15 -> 3.1.4 Receita com Cartão - (Infinity Emp) | D16: =SUMIFS('Livro Diario - FC'!$J$11:$J1028,'Livro Diario - FC'!$E$11:$E1028,$C$16,'Livro Diario - FC'!$D$11:$D1028,">=01/01"&$C$7,'Livro Diario - FC'!$D$11:$D1028,"<=31/01"&$C$7) -> 0 | E16: =SUMIFS('Livro Diario - FC'!$L$11:$L1028,'Livro Diario - FC'!$E$11:$E1028,$C$16,'Livro Diario - FC'!$D$11:$D1028,">=01/01"&$C$7,'Livro Diario - FC'!$D$11:$D1028,"<=31/01"&$C$7) -> 0 | F16: =IF(E$11=0,"",E16/E$11) -> 0 | G16: =IF(A16=0,"",E16/A16-1) | I16: =SUMIFS('Livro Diario - FC'!$J$11:$J1028,'Livro Diario - FC'!$E$11:$E1028,$C$16,'Livro Diario - FC'!$D$11:$D1028,">=01/02"&$C$7,'Livro Diario - FC'!$D$11:$D1028,"<=29/02"&$C$7) -> 0 | J16: =SUMIFS('Livro Diario - FC'!$L$11:$L1028,'Livro Diario - FC'!$E$11:$E1028,$C$16,'Livro Diario - FC'!$D$11:$D1028,">=01/02"&$C$7,'Livro Diario - FC'!$D$11:$D1028,"<=29/02"&$C$7) -> 0 | K16: =IF(J$11=0,"",J16/J$11) | L16: =IF(E16=0,"",J16/E16-1) | N16: =SUMIFS('Livro Diario - FC'!$J$11:$J1028,'Livro Diario - FC'!$E$11:$E1028,$C$16,'Livro Diario - FC'!$D$11:$D1028,">=01/03"&$C$7,'Livro Diario - FC'!$D$11:$D1028,"<=31/03"&$C$7) -> 0 | O16: =SUMIFS('Livro Diario - FC'!$L$11:$L1028,'Livro Diario - FC'!$E$11:$E1028,$C$16,'Livro Diario - FC'!$D$11:$D1028,">=01/03"&$C$7,'Livro Diario - FC'!$D$11:$D1028,"<=31/03"&$C$7) -> 0 | P16: =IF(O$11=0,"",O16/O$11) | Q16: =IF(J16=0,"",O16/J16-1) | S16: =SUMIFS('Livro Diario - FC'!$J$11:$J1028,'Livro Diario - FC'!$E$11:$E1028,$C$16,'Livro Diario - FC'!$D$11:$D1028,">=01/04"&$C$7,'Livro Diario - FC'!$D$11:$D1028,"<=30/04"&$C$7) -> 0 | T16: =SUMIFS('Livro Diario - FC'!$L$11:$L1028,'Livro Diario - FC'!$E$11:$E1028,$C$16,'Livro Diario - FC'!$D$11:$D1028,">=01/04"&$C$7,'Livro Diario - FC'!$D$11:$D1028,"<=30/04"&$C$7) -> 0 | U16: =IF(T$11=0,"",T16/T$11) | V16: =IF(O16=0,"",T16/O16-1) | X16: =SUMIFS('Livro Diario - FC'!$J$11:$J1028,'Livro Diario - FC'!$E$11:$E1028,$C$16,'Livro Diario - FC'!$D$11:$D1028,">=01/05"&$C$7,'Livro Diario - FC'!$D$11:$D1028,"<=31/05"&$C$7) -> 0 | Y16: =SUMIFS('Livro Diario - FC'!$L$11:$L1028,'Livro Diario - FC'!$E$11:$E1028,$C$16,'Livro Diario - FC'!$D$11:$D1028,">=01/05"&$C$7,'Livro Diario - FC'!$D$11:$D1028,"<=31/05"&$C$7) -> 0 | Z16: =IF(Y$11=0,"",Y16/Y$11) | AA16: =IF(T16=0,"",Y16/T16-1) | AC16: =SUMIFS('Livro Diario - FC'!$J$11:$J1028,'Livro Diario - FC'!$E$11:$E1028,$C$16,'Livro Diario - FC'!$D$11:$D1028,">=01/06"&$C$7,'Livro Diario - FC'!$D$11:$D1028,"<=30/06"&$C$7) -> 0 | AD16: =SUMIFS('Livro Diario - FC'!$L$11:$L1028,'Livro Diario - FC'!$E$11:$E1028,$C$16,'Livro Diario - FC'!$D$11:$D1028,">=01/06"&$C$7,'Livro Diario - FC'!$D$11:$D1028,"<=30/06"&$C$7) -> 0 | AE16: =IF(AD$11=0,"",AD16/AD$11) | AF16: =IF(Y16=0,"",AD16/Y16-1) | AG16: =SUMIFS('Livro Diario - FC'!$J$11:$J1028,'Livro Diario - FC'!$E$11:$E1028,$C$16,'Livro Diario - FC'!$D$11:$D1028,">=01/07"&$C$7,'Livro Diario - FC'!$D$11:$D1028,"<=31/07"&$C$7) -> 0 | AH16: =SUMIFS('Livro Diario - FC'!$L$11:$L1028,'Livro Diario - FC'!$E$11:$E1028,$C$16,'Livro Diario - FC'!$D$11:$D1028,">=01/07"&$C$7,'Livro Diario - FC'!$D$11:$D1028,"<=31/07"&$C$7) -> 0 | AI16: =IF(AH$11=0,"",AH16/AH$11) | AJ16: =IF(AD16=0,"",AH16/AD16-1) | AK16: =SUMIFS('Livro Diario - FC'!$J$11:$J1028,'Livro Diario - FC'!$E$11:$E1028,$C$16,'Livro Diario - FC'!$D$11:$D1028,">=01/08"&$C$7,'Livro Diario - FC'!$D$11:$D1028,"<=31/08"&$C$7) -> 0 | AL16: =SUMIFS('Livro Diario - FC'!$L$11:$L1028,'Livro Diario - FC'!$E$11:$E1028,$C$16,'Livro Diario - FC'!$D$11:$D1028,">=01/08"&$C$7,'Livro Diario - FC'!$D$11:$D1028,"<=31/08"&$C$7) -> 0 | AM16: =IF(AL$11=0,"",AL16/AL$11) | AN16: =IF(AH16=0,"",AL16/AH16-1) | AO16: =SUMIFS('Livro Diario - FC'!$J$11:$J1028,'Livro Diario - FC'!$E$11:$E1028,$C$16,'Livro Diario - FC'!$D$11:$D1028,">=01/09"&$C$7,'Livro Diario - FC'!$D$11:$D1028,"<=30/09"&$C$7) -> 0 | AP16: =SUMIFS('Livro Diario - FC'!$L$11:$L1028,'Livro Diario - FC'!$E$11:$E1028,$C$16,'Livro Diario - FC'!$D$11:$D1028,">=01/09"&$C$7,'Livro Diario - FC'!$D$11:$D1028,"<=30/09"&$C$7) -> 0 | AQ16: =IF(AP$11=0,"",AP16/AP$11) | AR16: =IF(AL16=0,"",AP16/AL16-1) | AS16: =SUMIFS('Livro Diario - FC'!$J$11:$J1028,'Livro Diario - FC'!$E$11:$E1028,$C$16,'Livro Diario - FC'!$D$11:$D1028,">=01/10"&$C$7,'Livro Diario - FC'!$D$11:$D1028,"<=31/10"&$C$7) -> 0 | AT16: =SUMIFS('Livro Diario - FC'!$L$11:$L1028,'Livro Diario - FC'!$E$11:$E1028,$C$16,'Livro Diario - FC'!$D$11:$D1028,">=01/10"&$C$7,'Livro Diario - FC'!$D$11:$D1028,"<=31/10"&$C$7) -> 0 | AU16: =IF(AT$11=0,"",AT16/AT$11) | AV16: =IF(AP16=0,"",AT16/AP16-1) | AW16: =SUMIFS('Livro Diario - FC'!$J$11:$J1028,'Livro Diario - FC'!$E$11:$E1028,$C$16,'Livro Diario - FC'!$D$11:$D1028,">=01/11"&$C$7,'Livro Diario - FC'!$D$11:$D1028,"<=30/11"&$C$7) -> 0 | AX16: =SUMIFS('Livro Diario - FC'!$L$11:$L1028,'Livro Diario - FC'!$E$11:$E1028,$C$16,'Livro Diario - FC'!$D$11:$D1028,">=01/11"&$C$7,'Livro Diario - FC'!$D$11:$D1028,"<=30/11"&$C$7) -> 0 | AY16: =IF(AX$11=0,"",AX16/AX$11) | AZ16: =IF(AT16=0,"",AX16/AT16-1) | BA16: =SUMIFS('Livro Diario - FC'!$J$11:$J1028,'Livro Diario - FC'!$E$11:$E1028,$C$16,'Livro Diario - FC'!$D$11:$D1028,">=01/12"&$C$7,'Livro Diario - FC'!$D$11:$D1028,"<=31/12"&$C$7) -> 0 | BB16: =SUMIFS('Livro Diario - FC'!$L$11:$L1028,'Livro Diario - FC'!$E$11:$E1028,$C$16,'Livro Diario - FC'!$D$11:$D1028,">=01/12"&$C$7,'Livro Diario - FC'!$D$11:$D1028,"<=31/12"&$C$7) -> 0 | BC16: =IF(BB$11=0,"",BB16/BB$11) | BD16: =IF(AX16=0,"",BB16/AX16-1) | BE16: =SUM(D16,I16,N16,S16,X16,AC16,AG16,AK16,AO16,AS16,AW16,BA16) -> 0 | BF16: =SUM(E16,J16,O16,T16,Y16,AD16,AH16,AL16,AP16,AT16,AX16,BB16) -> 0 | BI16: =SUMIFS('Livro Diario - FC'!$L$11:$L1028,'Livro Diario - FC'!$E$11:$E1028,C16,'Livro Diario - FC'!$D$11:$D1028,">="&$BK$8,'Livro Diario - FC'!$D$11:$D1028,"<="&$BK$9) -> 0
C17: ='Livro Diario - FC'!AE16 -> 3.1.5 Receita com Cartão - (Infinity Sil) | D17: =SUMIFS('Livro Diario - FC'!$J$11:$J1028,'Livro Diario - FC'!$E$11:$E1028,$C$17,'Livro Diario - FC'!$D$11:$D1028,">=01/01"&$C$7,'Livro Diario - FC'!$D$11:$D1028,"<=31/01"&$C$7) -> 0 | E17: =SUMIFS('Livro Diario - FC'!$L$11:$L1028,'Livro Diario - FC'!$E$11:$E1028,$C$17,'Livro Diario - FC'!$D$11:$D1028,">=01/01"&$C$7,'Livro Diario - FC'!$D$11:$D1028,"<=31/01"&$C$7) -> 0 | F17: =IF(E$11=0,"",E17/E$11) -> 0 | I17: =SUMIFS('Livro Diario - FC'!$J$11:$J1028,'Livro Diario - FC'!$E$11:$E1028,$C$17,'Livro Diario - FC'!$D$11:$D1028,">=01/02"&$C$7,'Livro Diario - FC'!$D$11:$D1028,"<=29/02"&$C$7) -> 0 | J17: =SUMIFS('Livro Diario - FC'!$L$11:$L1028,'Livro Diario - FC'!$E$11:$E1028,$C$17,'Livro Diario - FC'!$D$11:$D1028,">=01/02"&$C$7,'Livro Diario - FC'!$D$11:$D1028,"<=29/02"&$C$7) -> 0 | K17: =IF(J$11=0,"",J17/J$11) | N17: =SUMIFS('Livro Diario - FC'!$J$11:$J1028,'Livro Diario - FC'!$E$11:$E1028,$C$17,'Livro Diario - FC'!$D$11:$D1028,">=01/03"&$C$7,'Livro Diario - FC'!$D$11:$D1028,"<=31/03"&$C$7) -> 0 | O17: =SUMIFS('Livro Diario - FC'!$L$11:$L1028,'Livro Diario - FC'!$E$11:$E1028,$C$17,'Livro Diario - FC'!$D$11:$D1028,">=01/03"&$C$7,'Livro Diario - FC'!$D$11:$D1028,"<=31/03"&$C$7) -> 0 | P17: =IF(O$11=0,"",O17/O$11) | S17: =SUMIFS('Livro Diario - FC'!$J$11:$J1028,'Livro Diario - FC'!$E$11:$E1028,$C$17,'Livro Diario - FC'!$D$11:$D1028,">=01/04"&$C$7,'Livro Diario - FC'!$D$11:$D1028,"<=30/04"&$C$7) -> 0 | T17: =SUMIFS('Livro Diario - FC'!$L$11:$L1028,'Livro Diario - FC'!$E$11:$E1028,$C$17,'Livro Diario - FC'!$D$11:$D1028,">=01/04"&$C$7,'Livro Diario - FC'!$D$11:$D1028,"<=30/04"&$C$7) -> 0 | U17: =IF(T$11=0,"",T17/T$11) | X17: =SUMIFS('Livro Diario - FC'!$J$11:$J1028,'Livro Diario - FC'!$E$11:$E1028,$C$17,'Livro Diario - FC'!$D$11:$D1028,">=01/05"&$C$7,'Livro Diario - FC'!$D$11:$D1028,"<=31/05"&$C$7) -> 0 | Y17: =SUMIFS('Livro Diario - FC'!$L$11:$L1028,'Livro Diario - FC'!$E$11:$E1028,$C$17,'Livro Diario - FC'!$D$11:$D1028,">=01/05"&$C$7,'Livro Diario - FC'!$D$11:$D1028,"<=31/05"&$C$7) -> 0 | Z17: =IF(Y$11=0,"",Y17/Y$11) | AC17: =SUMIFS('Livro Diario - FC'!$J$11:$J1028,'Livro Diario - FC'!$E$11:$E1028,$C$17,'Livro Diario - FC'!$D$11:$D1028,">=01/06"&$C$7,'Livro Diario - FC'!$D$11:$D1028,"<=30/06"&$C$7) -> 0 | AD17: =SUMIFS('Livro Diario - FC'!$L$11:$L1028,'Livro Diario - FC'!$E$11:$E1028,$C$17,'Livro Diario - FC'!$D$11:$D1028,">=01/06"&$C$7,'Livro Diario - FC'!$D$11:$D1028,"<=30/06"&$C$7) -> 0 | AE17: =IF(AD$11=0,"",AD17/AD$11) | AG17: =SUMIFS('Livro Diario - FC'!$J$11:$J1028,'Livro Diario - FC'!$E$11:$E1028,$C$17,'Livro Diario - FC'!$D$11:$D1028,">=01/07"&$C$7,'Livro Diario - FC'!$D$11:$D1028,"<=31/07"&$C$7) -> 0 | AH17: =SUMIFS('Livro Diario - FC'!$L$11:$L1028,'Livro Diario - FC'!$E$11:$E1028,$C$17,'Livro Diario - FC'!$D$11:$D1028,">=01/07"&$C$7,'Livro Diario - FC'!$D$11:$D1028,"<=31/07"&$C$7) -> 0 | AI17: =IF(AH$11=0,"",AH17/AH$11) | AK17: =SUMIFS('Livro Diario - FC'!$J$11:$J1028,'Livro Diario - FC'!$E$11:$E1028,$C$17,'Livro Diario - FC'!$D$11:$D1028,">=01/08"&$C$7,'Livro Diario - FC'!$D$11:$D1028,"<=31/08"&$C$7) -> 0 | AL17: =SUMIFS('Livro Diario - FC'!$L$11:$L1028,'Livro Diario - FC'!$E$11:$E1028,$C$17,'Livro Diario - FC'!$D$11:$D1028,">=01/08"&$C$7,'Livro Diario - FC'!$D$11:$D1028,"<=31/08"&$C$7) -> 0 | AM17: =IF(AL$11=0,"",AL17/AL$11) | AO17: =SUMIFS('Livro Diario - FC'!$J$11:$J1028,'Livro Diario - FC'!$E$11:$E1028,$C$17,'Livro Diario - FC'!$D$11:$D1028,">=01/09"&$C$7,'Livro Diario - FC'!$D$11:$D1028,"<=30/09"&$C$7) -> 0 | AP17: =SUMIFS('Livro Diario - FC'!$L$11:$L1028,'Livro Diario - FC'!$E$11:$E1028,$C$17,'Livro Diario - FC'!$D$11:$D1028,">=01/09"&$C$7,'Livro Diario - FC'!$D$11:$D1028,"<=30/09"&$C$7) -> 0 | AQ17: =IF(AP$11=0,"",AP17/AP$11) | AS17: =SUMIFS('Livro Diario - FC'!$J$11:$J1028,'Livro Diario - FC'!$E$11:$E1028,$C$17,'Livro Diario - FC'!$D$11:$D1028,">=01/10"&$C$7,'Livro Diario - FC'!$D$11:$D1028,"<=31/10"&$C$7) -> 0 | AT17: =SUMIFS('Livro Diario - FC'!$L$11:$L1028,'Livro Diario - FC'!$E$11:$E1028,$C$17,'Livro Diario - FC'!$D$11:$D1028,">=01/10"&$C$7,'Livro Diario - FC'!$D$11:$D1028,"<=31/10"&$C$7) -> 0 | AU17: =IF(AT$11=0,"",AT17/AT$11) | AW17: =SUMIFS('Livro Diario - FC'!$J$11:$J1028,'Livro Diario - FC'!$E$11:$E1028,$C$17,'Livro Diario - FC'!$D$11:$D1028,">=01/11"&$C$7,'Livro Diario - FC'!$D$11:$D1028,"<=30/11"&$C$7) -> 0 | AX17: =SUMIFS('Livro Diario - FC'!$L$11:$L1028,'Livro Diario - FC'!$E$11:$E1028,$C$17,'Livro Diario - FC'!$D$11:$D1028,">=01/11"&$C$7,'Livro Diario - FC'!$D$11:$D1028,"<=30/11"&$C$7) -> 0 | AY17: =IF(AX$11=0,"",AX17/AX$11) | BA17: =SUMIFS('Livro Diario - FC'!$J$11:$J1028,'Livro Diario - FC'!$E$11:$E1028,$C$17,'Livro Diario - FC'!$D$11:$D1028,">=01/12"&$C$7,'Livro Diario - FC'!$D$11:$D1028,"<=31/12"&$C$7) -> 0 | BB17: =SUMIFS('Livro Diario - FC'!$L$11:$L1028,'Livro Diario - FC'!$E$11:$E1028,$C$17,'Livro Diario - FC'!$D$11:$D1028,">=01/12"&$C$7,'Livro Diario - FC'!$D$11:$D1028,"<=31/12"&$C$7) -> 0 | BC17: =IF(BB$11=0,"",BB17/BB$11) | BE17: =SUM(D17,I17,N17,S17,X17,AC17,AG17,AK17,AO17,AS17,AW17,BA17) -> 0 | BF17: =SUM(E17,J17,O17,T17,Y17,AD17,AH17,AL17,AP17,AT17,AX17,BB17) -> 0 | BI17: =SUMIFS('Livro Diario - FC'!$L$11:$L1028,'Livro Diario - FC'!$E$11:$E1028,C17,'Livro Diario - FC'!$D$11:$D1028,">="&$BK$8,'Livro Diario - FC'!$D$11:$D1028,"<="&$BK$9) -> 0
C18: ='Livro Diario - FC'!AE17 -> 3.1.6 - | D18: =SUMIFS('Livro Diario - FC'!$J$11:$J1028,'Livro Diario - FC'!$E$11:$E1028,$C$18,'Livro Diario - FC'!$D$11:$D1028,">=01/01"&$C$7,'Livro Diario - FC'!$D$11:$D1028,"<=31/01"&$C$7) -> 0 | E18: =SUMIFS('Livro Diario - FC'!$L$11:$L1028,'Livro Diario - FC'!$E$11:$E1028,$C$18,'Livro Diario - FC'!$D$11:$D1028,">=01/01"&$C$7,'Livro Diario - FC'!$D$11:$D1028,"<=31/01"&$C$7) -> 0 | F18: =IF(E$11=0,"",E18/E$11) -> 0 | I18: =SUMIFS('Livro Diario - FC'!$J$11:$J1028,'Livro Diario - FC'!$E$11:$E1028,$C$18,'Livro Diario - FC'!$D$11:$D1028,">=01/02"&$C$7,'Livro Diario - FC'!$D$11:$D1028,"<=29/02"&$C$7) -> 0 | J18: =SUMIFS('Livro Diario - FC'!$L$11:$L1028,'Livro Diario - FC'!$E$11:$E1028,$C$18,'Livro Diario - FC'!$D$11:$D1028,">=01/02"&$C$7,'Livro Diario - FC'!$D$11:$D1028,"<=29/02"&$C$7) -> 0 | K18: =IF(J$11=0,"",J18/J$11) | N18: =SUMIFS('Livro Diario - FC'!$J$11:$J1028,'Livro Diario - FC'!$E$11:$E1028,$C$18,'Livro Diario - FC'!$D$11:$D1028,">=01/03"&$C$7,'Livro Diario - FC'!$D$11:$D1028,"<=31/03"&$C$7) -> 0 | O18: =SUMIFS('Livro Diario - FC'!$L$11:$L1028,'Livro Diario - FC'!$E$11:$E1028,$C$18,'Livro Diario - FC'!$D$11:$D1028,">=01/03"&$C$7,'Livro Diario - FC'!$D$11:$D1028,"<=31/03"&$C$7) -> 0 | P18: =IF(O$11=0,"",O18/O$11) | S18: =SUMIFS('Livro Diario - FC'!$J$11:$J1028,'Livro Diario - FC'!$E$11:$E1028,$C$18,'Livro Diario - FC'!$D$11:$D1028,">=01/04"&$C$7,'Livro Diario - FC'!$D$11:$D1028,"<=30/04"&$C$7) -> 0 | T18: =SUMIFS('Livro Diario - FC'!$L$11:$L1028,'Livro Diario - FC'!$E$11:$E1028,$C$18,'Livro Diario - FC'!$D$11:$D1028,">=01/04"&$C$7,'Livro Diario - FC'!$D$11:$D1028,"<=30/04"&$C$7) -> 0 | U18: =IF(T$11=0,"",T18/T$11) | X18: =SUMIFS('Livro Diario - FC'!$J$11:$J1028,'Livro Diario - FC'!$E$11:$E1028,$C$18,'Livro Diario - FC'!$D$11:$D1028,">=01/05"&$C$7,'Livro Diario - FC'!$D$11:$D1028,"<=31/05"&$C$7) -> 0 | Y18: =SUMIFS('Livro Diario - FC'!$L$11:$L1028,'Livro Diario - FC'!$E$11:$E1028,$C$18,'Livro Diario - FC'!$D$11:$D1028,">=01/05"&$C$7,'Livro Diario - FC'!$D$11:$D1028,"<=31/05"&$C$7) -> 0 | Z18: =IF(Y$11=0,"",Y18/Y$11) | AC18: =SUMIFS('Livro Diario - FC'!$J$11:$J1028,'Livro Diario - FC'!$E$11:$E1028,$C$18,'Livro Diario - FC'!$D$11:$D1028,">=01/06"&$C$7,'Livro Diario - FC'!$D$11:$D1028,"<=30/06"&$C$7) -> 0 | AD18: =SUMIFS('Livro Diario - FC'!$L$11:$L1028,'Livro Diario - FC'!$E$11:$E1028,$C$18,'Livro Diario - FC'!$D$11:$D1028,">=01/06"&$C$7,'Livro Diario - FC'!$D$11:$D1028,"<=30/06"&$C$7) -> 0 | AE18: =IF(AD$11=0,"",AD18/AD$11) | AG18: =SUMIFS('Livro Diario - FC'!$J$11:$J1028,'Livro Diario - FC'!$E$11:$E1028,$C$18,'Livro Diario - FC'!$D$11:$D1028,">=01/07"&$C$7,'Livro Diario - FC'!$D$11:$D1028,"<=31/07"&$C$7) -> 0 | AH18: =SUMIFS('Livro Diario - FC'!$L$11:$L1028,'Livro Diario - FC'!$E$11:$E1028,$C$18,'Livro Diario - FC'!$D$11:$D1028,">=01/07"&$C$7,'Livro Diario - FC'!$D$11:$D1028,"<=31/07"&$C$7) -> 0 | AI18: =IF(AH$11=0,"",AH18/AH$11) | AK18: =SUMIFS('Livro Diario - FC'!$J$11:$J1028,'Livro Diario - FC'!$E$11:$E1028,$C$18,'Livro Diario - FC'!$D$11:$D1028,">=01/08"&$C$7,'Livro Diario - FC'!$D$11:$D1028,"<=31/08"&$C$7) -> 0 | AL18: =SUMIFS('Livro Diario - FC'!$L$11:$L1028,'Livro Diario - FC'!$E$11:$E1028,$C$18,'Livro Diario - FC'!$D$11:$D1028,">=01/08"&$C$7,'Livro Diario - FC'!$D$11:$D1028,"<=31/08"&$C$7) -> 0 | AM18: =IF(AL$11=0,"",AL18/AL$11) | AO18: =SUMIFS('Livro Diario - FC'!$J$11:$J1028,'Livro Diario - FC'!$E$11:$E1028,$C$18,'Livro Diario - FC'!$D$11:$D1028,">=01/09"&$C$7,'Livro Diario - FC'!$D$11:$D1028,"<=30/09"&$C$7) -> 0 | AP18: =SUMIFS('Livro Diario - FC'!$L$11:$L1028,'Livro Diario - FC'!$E$11:$E1028,$C$18,'Livro Diario - FC'!$D$11:$D1028,">=01/09"&$C$7,'Livro Diario - FC'!$D$11:$D1028,"<=30/09"&$C$7) -> 0 | AQ18: =IF(AP$11=0,"",AP18/AP$11) | AS18: =SUMIFS('Livro Diario - FC'!$J$11:$J1028,'Livro Diario - FC'!$E$11:$E1028,$C$18,'Livro Diario - FC'!$D$11:$D1028,">=01/10"&$C$7,'Livro Diario - FC'!$D$11:$D1028,"<=31/10"&$C$7) -> 0 | AT18: =SUMIFS('Livro Diario - FC'!$L$11:$L1028,'Livro Diario - FC'!$E$11:$E1028,$C$18,'Livro Diario - FC'!$D$11:$D1028,">=01/10"&$C$7,'Livro Diario - FC'!$D$11:$D1028,"<=31/10"&$C$7) -> 0 | AU18: =IF(AT$11=0,"",AT18/AT$11) | AW18: =SUMIFS('Livro Diario - FC'!$J$11:$J1028,'Livro Diario - FC'!$E$11:$E1028,$C$18,'Livro Diario - FC'!$D$11:$D1028,">=01/11"&$C$7,'Livro Diario - FC'!$D$11:$D1028,"<=30/11"&$C$7) -> 0 | AX18: =SUMIFS('Livro Diario - FC'!$L$11:$L1028,'Livro Diario - FC'!$E$11:$E1028,$C$18,'Livro Diario - FC'!$D$11:$D1028,">=01/11"&$C$7,'Livro Diario - FC'!$D$11:$D1028,"<=30/11"&$C$7) -> 0 | AY18: =IF(AX$11=0,"",AX18/AX$11) | BA18: =SUMIFS('Livro Diario - FC'!$J$11:$J1028,'Livro Diario - FC'!$E$11:$E1028,$C$18,'Livro Diario - FC'!$D$11:$D1028,">=01/12"&$C$7,'Livro Diario - FC'!$D$11:$D1028,"<=31/12"&$C$7) -> 0 | BB18: =SUMIFS('Livro Diario - FC'!$L$11:$L1028,'Livro Diario - FC'!$E$11:$E1028,$C$18,'Livro Diario - FC'!$D$11:$D1028,">=01/12"&$C$7,'Livro Diario - FC'!$D$11:$D1028,"<=31/12"&$C$7) -> 0 | BC18: =IF(BB$11=0,"",BB18/BB$11) | BE18: =SUM(D18,I18,N18,S18,X18,AC18,AG18,AK18,AO18,AS18,AW18,BA18) -> 0 | BF18: =SUM(E18,J18,O18,T18,Y18,AD18,AH18,AL18,AP18,AT18,AX18,BB18) -> 0 | BI18: =SUMIFS('Livro Diario - FC'!$L$11:$L1028,'Livro Diario - FC'!$E$11:$E1028,C18,'Livro Diario - FC'!$D$11:$D1028,">="&$BK$8,'Livro Diario - FC'!$D$11:$D1028,"<="&$BK$9) -> 0
C19: ='Livro Diario - FC'!AE18 -> 3.1.7 - | D19: =SUMIFS('Livro Diario - FC'!$J$11:$J1028,'Livro Diario - FC'!$E$11:$E1028,$C$19,'Livro Diario - FC'!$D$11:$D1028,">=01/01"&$C$7,'Livro Diario - FC'!$D$11:$D1028,"<=31/01"&$C$7) -> 0 | E19: =SUMIFS('Livro Diario - FC'!$L$11:$L1028,'Livro Diario - FC'!$E$11:$E1028,$C$19,'Livro Diario - FC'!$D$11:$D1028,">=01/01"&$C$7,'Livro Diario - FC'!$D$11:$D1028,"<=31/01"&$C$7) -> 0 | F19: =IF(E$11=0,"",E19/E$11) -> 0 | I19: =SUMIFS('Livro Diario - FC'!$J$11:$J1028,'Livro Diario - FC'!$E$11:$E1028,$C$19,'Livro Diario - FC'!$D$11:$D1028,">=01/02"&$C$7,'Livro Diario - FC'!$D$11:$D1028,"<=29/02"&$C$7) -> 0 | J19: =SUMIFS('Livro Diario - FC'!$L$11:$L1028,'Livro Diario - FC'!$E$11:$E1028,$C$19,'Livro Diario - FC'!$D$11:$D1028,">=01/02"&$C$7,'Livro Diario - FC'!$D$11:$D1028,"<=29/02"&$C$7) -> 0 | K19: =IF(J$11=0,"",J19/J$11) | N19: =SUMIFS('Livro Diario - FC'!$J$11:$J1028,'Livro Diario - FC'!$E$11:$E1028,$C$19,'Livro Diario - FC'!$D$11:$D1028,">=01/03"&$C$7,'Livro Diario - FC'!$D$11:$D1028,"<=31/03"&$C$7) -> 0 | O19: =SUMIFS('Livro Diario - FC'!$L$11:$L1028,'Livro Diario - FC'!$E$11:$E1028,$C$19,'Livro Diario - FC'!$D$11:$D1028,">=01/03"&$C$7,'Livro Diario - FC'!$D$11:$D1028,"<=31/03"&$C$7) -> 0 | P19: =IF(O$11=0,"",O19/O$11) | S19: =SUMIFS('Livro Diario - FC'!$J$11:$J1028,'Livro Diario - FC'!$E$11:$E1028,$C$19,'Livro Diario - FC'!$D$11:$D1028,">=01/04"&$C$7,'Livro Diario - FC'!$D$11:$D1028,"<=30/04"&$C$7) -> 0 | T19: =SUMIFS('Livro Diario - FC'!$L$11:$L1028,'Livro Diario - FC'!$E$11:$E1028,$C$19,'Livro Diario - FC'!$D$11:$D1028,">=01/04"&$C$7,'Livro Diario - FC'!$D$11:$D1028,"<=30/04"&$C$7) -> 0 | U19: =IF(T$11=0,"",T19/T$11) | X19: =SUMIFS('Livro Diario - FC'!$J$11:$J1028,'Livro Diario - FC'!$E$11:$E1028,$C$19,'Livro Diario - FC'!$D$11:$D1028,">=01/05"&$C$7,'Livro Diario - FC'!$D$11:$D1028,"<=31/05"&$C$7) -> 0 | Y19: =SUMIFS('Livro Diario - FC'!$L$11:$L1028,'Livro Diario - FC'!$E$11:$E1028,$C$19,'Livro Diario - FC'!$D$11:$D1028,">=01/05"&$C$7,'Livro Diario - FC'!$D$11:$D1028,"<=31/05"&$C$7) -> 0 | Z19: =IF(Y$11=0,"",Y19/Y$11) | AC19: =SUMIFS('Livro Diario - FC'!$J$11:$J1028,'Livro Diario - FC'!$E$11:$E1028,$C$19,'Livro Diario - FC'!$D$11:$D1028,">=01/06"&$C$7,'Livro Diario - FC'!$D$11:$D1028,"<=30/06"&$C$7) -> 0 | AD19: =SUMIFS('Livro Diario - FC'!$L$11:$L1028,'Livro Diario - FC'!$E$11:$E1028,$C$19,'Livro Diario - FC'!$D$11:$D1028,">=01/06"&$C$7,'Livro Diario - FC'!$D$11:$D1028,"<=30/06"&$C$7) -> 0 | AE19: =IF(AD$11=0,"",AD19/AD$11) | AG19: =SUMIFS('Livro Diario - FC'!$J$11:$J1028,'Livro Diario - FC'!$E$11:$E1028,$C$19,'Livro Diario - FC'!$D$11:$D1028,">=01/07"&$C$7,'Livro Diario - FC'!$D$11:$D1028,"<=31/07"&$C$7) -> 0 | AH19: =SUMIFS('Livro Diario - FC'!$L$11:$L1028,'Livro Diario - FC'!$E$11:$E1028,$C$19,'Livro Diario - FC'!$D$11:$D1028,">=01/07"&$C$7,'Livro Diario - FC'!$D$11:$D1028,"<=31/07"&$C$7) -> 0 | AI19: =IF(AH$11=0,"",AH19/AH$11) | AK19: =SUMIFS('Livro Diario - FC'!$J$11:$J1028,'Livro Diario - FC'!$E$11:$E1028,$C$19,'Livro Diario - FC'!$D$11:$D1028,">=01/08"&$C$7,'Livro Diario - FC'!$D$11:$D1028,"<=31/08"&$C$7) -> 0 | AL19: =SUMIFS('Livro Diario - FC'!$L$11:$L1028,'Livro Diario - FC'!$E$11:$E1028,$C$19,'Livro Diario - FC'!$D$11:$D1028,">=01/08"&$C$7,'Livro Diario - FC'!$D$11:$D1028,"<=31/08"&$C$7) -> 0 | AM19: =IF(AL$11=0,"",AL19/AL$11) | AO19: =SUMIFS('Livro Diario - FC'!$J$11:$J1028,'Livro Diario - FC'!$E$11:$E1028,$C$19,'Livro Diario - FC'!$D$11:$D1028,">=01/09"&$C$7,'Livro Diario - FC'!$D$11:$D1028,"<=30/09"&$C$7) -> 0 | AP19: =SUMIFS('Livro Diario - FC'!$L$11:$L1028,'Livro Diario - FC'!$E$11:$E1028,$C$19,'Livro Diario - FC'!$D$11:$D1028,">=01/09"&$C$7,'Livro Diario - FC'!$D$11:$D1028,"<=30/09"&$C$7) -> 0 | AQ19: =IF(AP$11=0,"",AP19/AP$11) | AS19: =SUMIFS('Livro Diario - FC'!$J$11:$J1028,'Livro Diario - FC'!$E$11:$E1028,$C$19,'Livro Diario - FC'!$D$11:$D1028,">=01/10"&$C$7,'Livro Diario - FC'!$D$11:$D1028,"<=31/10"&$C$7) -> 0 | AT19: =SUMIFS('Livro Diario - FC'!$L$11:$L1028,'Livro Diario - FC'!$E$11:$E1028,$C$19,'Livro Diario - FC'!$D$11:$D1028,">=01/10"&$C$7,'Livro Diario - FC'!$D$11:$D1028,"<=31/10"&$C$7) -> 0 | AU19: =IF(AT$11=0,"",AT19/AT$11) | AW19: =SUMIFS('Livro Diario - FC'!$J$11:$J1028,'Livro Diario - FC'!$E$11:$E1028,$C$19,'Livro Diario - FC'!$D$11:$D1028,">=01/11"&$C$7,'Livro Diario - FC'!$D$11:$D1028,"<=30/11"&$C$7) -> 0 | AX19: =SUMIFS('Livro Diario - FC'!$L$11:$L1028,'Livro Diario - FC'!$E$11:$E1028,$C$19,'Livro Diario - FC'!$D$11:$D1028,">=01/11"&$C$7,'Livro Diario - FC'!$D$11:$D1028,"<=30/11"&$C$7) -> 0 | AY19: =IF(AX$11=0,"",AX19/AX$11) | BA19: =SUMIFS('Livro Diario - FC'!$J$11:$J1028,'Livro Diario - FC'!$E$11:$E1028,$C$19,'Livro Diario - FC'!$D$11:$D1028,">=01/12"&$C$7,'Livro Diario - FC'!$D$11:$D1028,"<=31/12"&$C$7) -> 0 | BB19: =SUMIFS('Livro Diario - FC'!$L$11:$L1028,'Livro Diario - FC'!$E$11:$E1028,$C$19,'Livro Diario - FC'!$D$11:$D1028,">=01/12"&$C$7,'Livro Diario - FC'!$D$11:$D1028,"<=31/12"&$C$7) -> 0 | BC19: =IF(BB$11=0,"",BB19/BB$11) | BE19: =SUM(D19,I19,N19,S19,X19,AC19,AG19,AK19,AO19,AS19,AW19,BA19) -> 0 | BF19: =SUM(E19,J19,O19,T19,Y19,AD19,AH19,AL19,AP19,AT19,AX19,BB19) -> 0 | BI19: =SUMIFS('Livro Diario - FC'!$L$11:$L1028,'Livro Diario - FC'!$E$11:$E1028,C19,'Livro Diario - FC'!$D$11:$D1028,">="&$BK$8,'Livro Diario - FC'!$D$11:$D1028,"<="&$BK$9) -> 0
C20: ='Livro Diario - FC'!AE19 -> 3.1.8 - | D20: =SUMIFS('Livro Diario - FC'!$J$11:$J1028,'Livro Diario - FC'!$E$11:$E1028,$C$20,'Livro Diario - FC'!$D$11:$D1028,">=01/01"&$C$7,'Livro Diario - FC'!$D$11:$D1028,"<=31/01"&$C$7) -> 0 | E20: =SUMIFS('Livro Diario - FC'!$L$11:$L1028,'Livro Diario - FC'!$E$11:$E1028,$C$20,'Livro Diario - FC'!$D$11:$D1028,">=01/01"&$C$7,'Livro Diario - FC'!$D$11:$D1028,"<=31/01"&$C$7) -> 0 | F20: =IF(E$11=0,"",E20/E$11) -> 0 | I20: =SUMIFS('Livro Diario - FC'!$J$11:$J1028,'Livro Diario - FC'!$E$11:$E1028,$C$20,'Livro Diario - FC'!$D$11:$D1028,">=01/02"&$C$7,'Livro Diario - FC'!$D$11:$D1028,"<=29/02"&$C$7) -> 0 | J20: =SUMIFS('Livro Diario - FC'!$L$11:$L1028,'Livro Diario - FC'!$E$11:$E1028,$C$20,'Livro Diario - FC'!$D$11:$D1028,">=01/02"&$C$7,'Livro Diario - FC'!$D$11:$D1028,"<=29/02"&$C$7) -> 0 | N20: =SUMIFS('Livro Diario - FC'!$J$11:$J1028,'Livro Diario - FC'!$E$11:$E1028,$C$20,'Livro Diario - FC'!$D$11:$D1028,">=01/03"&$C$7,'Livro Diario - FC'!$D$11:$D1028,"<=31/03"&$C$7) -> 0 | O20: =SUMIFS('Livro Diario - FC'!$L$11:$L1028,'Livro Diario - FC'!$E$11:$E1028,$C$20,'Livro Diario - FC'!$D$11:$D1028,">=01/03"&$C$7,'Livro Diario - FC'!$D$11:$D1028,"<=31/03"&$C$7) -> 0 | S20: =SUMIFS('Livro Diario - FC'!$J$11:$J1028,'Livro Diario - FC'!$E$11:$E1028,$C$20,'Livro Diario - FC'!$D$11:$D1028,">=01/04"&$C$7,'Livro Diario - FC'!$D$11:$D1028,"<=30/04"&$C$7) -> 0 | T20: =SUMIFS('Livro Diario - FC'!$L$11:$L1028,'Livro Diario - FC'!$E$11:$E1028,$C$20,'Livro Diario - FC'!$D$11:$D1028,">=01/04"&$C$7,'Livro Diario - FC'!$D$11:$D1028,"<=30/04"&$C$7) -> 0 | X20: =SUMIFS('Livro Diario - FC'!$J$11:$J1028,'Livro Diario - FC'!$E$11:$E1028,$C$20,'Livro Diario - FC'!$D$11:$D1028,">=01/05"&$C$7,'Livro Diario - FC'!$D$11:$D1028,"<=31/05"&$C$7) -> 0 | Y20: =SUMIFS('Livro Diario - FC'!$L$11:$L1028,'Livro Diario - FC'!$E$11:$E1028,$C$20,'Livro Diario - FC'!$D$11:$D1028,">=01/05"&$C$7,'Livro Diario - FC'!$D$11:$D1028,"<=31/05"&$C$7) -> 0 | AC20: =SUMIFS('Livro Diario - FC'!$J$11:$J1028,'Livro Diario - FC'!$E$11:$E1028,$C$20,'Livro Diario - FC'!$D$11:$D1028,">=01/06"&$C$7,'Livro Diario - FC'!$D$11:$D1028,"<=30/06"&$C$7) -> 0 | AD20: =SUMIFS('Livro Diario - FC'!$L$11:$L1028,'Livro Diario - FC'!$E$11:$E1028,$C$20,'Livro Diario - FC'!$D$11:$D1028,">=01/06"&$C$7,'Livro Diario - FC'!$D$11:$D1028,"<=30/06"&$C$7) -> 0 | AG20: =SUMIFS('Livro Diario - FC'!$J$11:$J1028,'Livro Diario - FC'!$E$11:$E1028,$C$20,'Livro Diario - FC'!$D$11:$D1028,">=01/07"&$C$7,'Livro Diario - FC'!$D$11:$D1028,"<=31/07"&$C$7) -> 0 | AH20: =SUMIFS('Livro Diario - FC'!$L$11:$L1028,'Livro Diario - FC'!$E$11:$E1028,$C$20,'Livro Diario - FC'!$D$11:$D1028,">=01/07"&$C$7,'Livro Diario - FC'!$D$11:$D1028,"<=31/07"&$C$7) -> 0 | AK20: =SUMIFS('Livro Diario - FC'!$J$11:$J1028,'Livro Diario - FC'!$E$11:$E1028,$C$20,'Livro Diario - FC'!$D$11:$D1028,">=01/08"&$C$7,'Livro Diario - FC'!$D$11:$D1028,"<=31/08"&$C$7) -> 0 | AL20: =SUMIFS('Livro Diario - FC'!$L$11:$L1028,'Livro Diario - FC'!$E$11:$E1028,$C$20,'Livro Diario - FC'!$D$11:$D1028,">=01/08"&$C$7,'Livro Diario - FC'!$D$11:$D1028,"<=31/08"&$C$7) -> 0 | AO20: =SUMIFS('Livro Diario - FC'!$J$11:$J1028,'Livro Diario - FC'!$E$11:$E1028,$C$20,'Livro Diario - FC'!$D$11:$D1028,">=01/09"&$C$7,'Livro Diario - FC'!$D$11:$D1028,"<=30/09"&$C$7) -> 0 | AP20: =SUMIFS('Livro Diario - FC'!$L$11:$L1028,'Livro Diario - FC'!$E$11:$E1028,$C$20,'Livro Diario - FC'!$D$11:$D1028,">=01/09"&$C$7,'Livro Diario - FC'!$D$11:$D1028,"<=30/09"&$C$7) -> 0 | AS20: =SUMIFS('Livro Diario - FC'!$J$11:$J1028,'Livro Diario - FC'!$E$11:$E1028,$C$20,'Livro Diario - FC'!$D$11:$D1028,">=01/10"&$C$7,'Livro Diario - FC'!$D$11:$D1028,"<=31/10"&$C$7) -> 0 | AT20: =SUMIFS('Livro Diario - FC'!$L$11:$L1028,'Livro Diario - FC'!$E$11:$E1028,$C$20,'Livro Diario - FC'!$D$11:$D1028,">=01/10"&$C$7,'Livro Diario - FC'!$D$11:$D1028,"<=31/10"&$C$7) -> 0 | AW20: =SUMIFS('Livro Diario - FC'!$J$11:$J1028,'Livro Diario - FC'!$E$11:$E1028,$C$20,'Livro Diario - FC'!$D$11:$D1028,">=01/11"&$C$7,'Livro Diario - FC'!$D$11:$D1028,"<=30/11"&$C$7) -> 0 | AX20: =SUMIFS('Livro Diario - FC'!$L$11:$L1028,'Livro Diario - FC'!$E$11:$E1028,$C$20,'Livro Diario - FC'!$D$11:$D1028,">=01/11"&$C$7,'Livro Diario - FC'!$D$11:$D1028,"<=30/11"&$C$7) -> 0 | BA20: =SUMIFS('Livro Diario - FC'!$J$11:$J1028,'Livro Diario - FC'!$E$11:$E1028,$C$20,'Livro Diario - FC'!$D$11:$D1028,">=01/12"&$C$7,'Livro Diario - FC'!$D$11:$D1028,"<=31/12"&$C$7) -> 0 | BB20: =SUMIFS('Livro Diario - FC'!$L$11:$L1028,'Livro Diario - FC'!$E$11:$E1028,$C$20,'Livro Diario - FC'!$D$11:$D1028,">=01/12"&$C$7,'Livro Diario - FC'!$D$11:$D1028,"<=31/12"&$C$7) -> 0 | BE20: =SUM(D20,I20,N20,S20,X20,AC20,AG20,AK20,AO20,AS20,AW20,BA20) -> 0 | BF20: =SUM(E20,J20,O20,T20,Y20,AD20,AH20,AL20,AP20,AT20,AX20,BB20) -> 0 | BI20: =SUMIFS('Livro Diario - FC'!$L$11:$L1028,'Livro Diario - FC'!$E$11:$E1028,C20,'Livro Diario - FC'!$D$11:$D1028,">="&$BK$8,'Livro Diario - FC'!$D$11:$D1028,"<="&$BK$9) -> 0
C21: ='Livro Diario - FC'!AE20 -> 3.1.9 . | D21: =SUMIFS('Livro Diario - FC'!$J$11:$J1028,'Livro Diario - FC'!$E$11:$E1028,$C$21,'Livro Diario - FC'!$D$11:$D1028,">=01/01"&$C$7,'Livro Diario - FC'!$D$11:$D1028,"<=31/01"&$C$7) -> 0 | E21: =SUMIFS('Livro Diario - FC'!$L$11:$L1028,'Livro Diario - FC'!$E$11:$E1028,$C$21,'Livro Diario - FC'!$D$11:$D1028,">=01/01"&$C$7,'Livro Diario - FC'!$D$11:$D1028,"<=31/01"&$C$7) -> 0 | F21: =IF(E$11=0,"",E21/E$11) -> 0 | I21: =SUMIFS('Livro Diario - FC'!$J$11:$J1028,'Livro Diario - FC'!$E$11:$E1028,$C$21,'Livro Diario - FC'!$D$11:$D1028,">=01/02"&$C$7,'Livro Diario - FC'!$D$11:$D1028,"<=29/02"&$C$7) -> 0 | J21: =SUMIFS('Livro Diario - FC'!$L$11:$L1028,'Livro Diario - FC'!$E$11:$E1028,$C$21,'Livro Diario - FC'!$D$11:$D1028,">=01/02"&$C$7,'Livro Diario - FC'!$D$11:$D1028,"<=29/02"&$C$7) -> 0 | N21: =SUMIFS('Livro Diario - FC'!$J$11:$J1028,'Livro Diario - FC'!$E$11:$E1028,$C$21,'Livro Diario - FC'!$D$11:$D1028,">=01/03"&$C$7,'Livro Diario - FC'!$D$11:$D1028,"<=31/03"&$C$7) -> 0 | O21: =SUMIFS('Livro Diario - FC'!$L$11:$L1028,'Livro Diario - FC'!$E$11:$E1028,$C$21,'Livro Diario - FC'!$D$11:$D1028,">=01/03"&$C$7,'Livro Diario - FC'!$D$11:$D1028,"<=31/03"&$C$7) -> 0 | S21: =SUMIFS('Livro Diario - FC'!$J$11:$J1028,'Livro Diario - FC'!$E$11:$E1028,$C$21,'Livro Diario - FC'!$D$11:$D1028,">=01/04"&$C$7,'Livro Diario - FC'!$D$11:$D1028,"<=30/04"&$C$7) -> 0 | T21: =SUMIFS('Livro Diario - FC'!$L$11:$L1028,'Livro Diario - FC'!$E$11:$E1028,$C$21,'Livro Diario - FC'!$D$11:$D1028,">=01/04"&$C$7,'Livro Diario - FC'!$D$11:$D1028,"<=30/04"&$C$7) -> 0 | X21: =SUMIFS('Livro Diario - FC'!$J$11:$J1028,'Livro Diario - FC'!$E$11:$E1028,$C$21,'Livro Diario - FC'!$D$11:$D1028,">=01/05"&$C$7,'Livro Diario - FC'!$D$11:$D1028,"<=31/05"&$C$7) -> 0 | Y21: =SUMIFS('Livro Diario - FC'!$L$11:$L1028,'Livro Diario - FC'!$E$11:$E1028,$C$21,'Livro Diario - FC'!$D$11:$D1028,">=01/05"&$C$7,'Livro Diario - FC'!$D$11:$D1028,"<=31/05"&$C$7) -> 0 | AC21: =SUMIFS('Livro Diario - FC'!$J$11:$J1028,'Livro Diario - FC'!$E$11:$E1028,$C$21,'Livro Diario - FC'!$D$11:$D1028,">=01/06"&$C$7,'Livro Diario - FC'!$D$11:$D1028,"<=30/06"&$C$7) -> 0 | AD21: =SUMIFS('Livro Diario - FC'!$L$11:$L1028,'Livro Diario - FC'!$E$11:$E1028,$C$21,'Livro Diario - FC'!$D$11:$D1028,">=01/06"&$C$7,'Livro Diario - FC'!$D$11:$D1028,"<=30/06"&$C$7) -> 0 | AG21: =SUMIFS('Livro Diario - FC'!$J$11:$J1028,'Livro Diario - FC'!$E$11:$E1028,$C$21,'Livro Diario - FC'!$D$11:$D1028,">=01/07"&$C$7,'Livro Diario - FC'!$D$11:$D1028,"<=31/07"&$C$7) -> 0 | AH21: =SUMIFS('Livro Diario - FC'!$L$11:$L1028,'Livro Diario - FC'!$E$11:$E1028,$C$21,'Livro Diario - FC'!$D$11:$D1028,">=01/07"&$C$7,'Livro Diario - FC'!$D$11:$D1028,"<=31/07"&$C$7) -> 0 | AK21: =SUMIFS('Livro Diario - FC'!$J$11:$J1028,'Livro Diario - FC'!$E$11:$E1028,$C$21,'Livro Diario - FC'!$D$11:$D1028,">=01/08"&$C$7,'Livro Diario - FC'!$D$11:$D1028,"<=31/08"&$C$7) -> 0 | AL21: =SUMIFS('Livro Diario - FC'!$L$11:$L1028,'Livro Diario - FC'!$E$11:$E1028,$C$21,'Livro Diario - FC'!$D$11:$D1028,">=01/08"&$C$7,'Livro Diario - FC'!$D$11:$D1028,"<=31/08"&$C$7) -> 0 | AO21: =SUMIFS('Livro Diario - FC'!$J$11:$J1028,'Livro Diario - FC'!$E$11:$E1028,$C$21,'Livro Diario - FC'!$D$11:$D1028,">=01/09"&$C$7,'Livro Diario - FC'!$D$11:$D1028,"<=30/09"&$C$7) -> 0 | AP21: =SUMIFS('Livro Diario - FC'!$L$11:$L1028,'Livro Diario - FC'!$E$11:$E1028,$C$21,'Livro Diario - FC'!$D$11:$D1028,">=01/09"&$C$7,'Livro Diario - FC'!$D$11:$D1028,"<=30/09"&$C$7) -> 0 | AS21: =SUMIFS('Livro Diario - FC'!$J$11:$J1028,'Livro Diario - FC'!$E$11:$E1028,$C$21,'Livro Diario - FC'!$D$11:$D1028,">=01/10"&$C$7,'Livro Diario - FC'!$D$11:$D1028,"<=31/10"&$C$7) -> 0 | AT21: =SUMIFS('Livro Diario - FC'!$L$11:$L1028,'Livro Diario - FC'!$E$11:$E1028,$C$21,'Livro Diario - FC'!$D$11:$D1028,">=01/10"&$C$7,'Livro Diario - FC'!$D$11:$D1028,"<=31/10"&$C$7) -> 0 | AW21: =SUMIFS('Livro Diario - FC'!$J$11:$J1028,'Livro Diario - FC'!$E$11:$E1028,$C$21,'Livro Diario - FC'!$D$11:$D1028,">=01/11"&$C$7,'Livro Diario - FC'!$D$11:$D1028,"<=30/11"&$C$7) -> 0 | AX21: =SUMIFS('Livro Diario - FC'!$L$11:$L1028,'Livro Diario - FC'!$E$11:$E1028,$C$21,'Livro Diario - FC'!$D$11:$D1028,">=01/11"&$C$7,'Livro Diario - FC'!$D$11:$D1028,"<=30/11"&$C$7) -> 0 | BA21: =SUMIFS('Livro Diario - FC'!$J$11:$J1028,'Livro Diario - FC'!$E$11:$E1028,$C$21,'Livro Diario - FC'!$D$11:$D1028,">=01/12"&$C$7,'Livro Diario - FC'!$D$11:$D1028,"<=31/12"&$C$7) -> 0 | BB21: =SUMIFS('Livro Diario - FC'!$L$11:$L1028,'Livro Diario - FC'!$E$11:$E1028,$C$21,'Livro Diario - FC'!$D$11:$D1028,">=01/12"&$C$7,'Livro Diario - FC'!$D$11:$D1028,"<=31/12"&$C$7) -> 0 | BE21: =SUM(D21,I21,N21,S21,X21,AC21,AG21,AK21,AO21,AS21,AW21,BA21) -> 0 | BF21: =SUM(E21,J21,O21,T21,Y21,AD21,AH21,AL21,AP21,AT21,AX21,BB21) -> 0 | BI21: =SUMIFS('Livro Diario - FC'!$L$11:$L1028,'Livro Diario - FC'!$E$11:$E1028,C21,'Livro Diario - FC'!$D$11:$D1028,">="&$BK$8,'Livro Diario - FC'!$D$11:$D1028,"<="&$BK$9) -> 0
C22: ='Livro Diario - FC'!AE21 -> 3.1.10 Acerto | D22: =SUMIFS('Livro Diario - FC'!$J$11:$J1028,'Livro Diario - FC'!$E$11:$E1028,$C$22,'Livro Diario - FC'!$D$11:$D1028,">=01/01"&$C$7,'Livro Diario - FC'!$D$11:$D1028,"<=31/01"&$C$7) -> 0 | E22: =SUMIFS('Livro Diario - FC'!$L$11:$L1028,'Livro Diario - FC'!$E$11:$E1028,$C$22,'Livro Diario - FC'!$D$11:$D1028,">=01/01"&$C$7,'Livro Diario - FC'!$D$11:$D1028,"<=31/01"&$C$7) -> 0 | F22: =IF(E$11=0,"",E22/E$11) -> 0 | I22: =SUMIFS('Livro Diario - FC'!$J$11:$J1028,'Livro Diario - FC'!$E$11:$E1028,$C$22,'Livro Diario - FC'!$D$11:$D1028,">=01/02"&$C$7,'Livro Diario - FC'!$D$11:$D1028,"<=29/02"&$C$7) -> 0 | J22: =SUMIFS('Livro Diario - FC'!$L$11:$L1028,'Livro Diario - FC'!$E$11:$E1028,$C$22,'Livro Diario - FC'!$D$11:$D1028,">=01/02"&$C$7,'Livro Diario - FC'!$D$11:$D1028,"<=29/02"&$C$7) -> 0 | N22: =SUMIFS('Livro Diario - FC'!$J$11:$J1028,'Livro Diario - FC'!$E$11:$E1028,$C$22,'Livro Diario - FC'!$D$11:$D1028,">=01/03"&$C$7,'Livro Diario - FC'!$D$11:$D1028,"<=31/03"&$C$7) -> 0 | O22: =SUMIFS('Livro Diario - FC'!$L$11:$L1028,'Livro Diario - FC'!$E$11:$E1028,$C$22,'Livro Diario - FC'!$D$11:$D1028,">=01/03"&$C$7,'Livro Diario - FC'!$D$11:$D1028,"<=31/03"&$C$7) -> 0 | S22: =SUMIFS('Livro Diario - FC'!$J$11:$J1028,'Livro Diario - FC'!$E$11:$E1028,$C$22,'Livro Diario - FC'!$D$11:$D1028,">=01/04"&$C$7,'Livro Diario - FC'!$D$11:$D1028,"<=30/04"&$C$7) -> 0 | T22: =SUMIFS('Livro Diario - FC'!$L$11:$L1028,'Livro Diario - FC'!$E$11:$E1028,$C$22,'Livro Diario - FC'!$D$11:$D1028,">=01/04"&$C$7,'Livro Diario - FC'!$D$11:$D1028,"<=30/04"&$C$7) -> 0 | X22: =SUMIFS('Livro Diario - FC'!$J$11:$J1028,'Livro Diario - FC'!$E$11:$E1028,$C$22,'Livro Diario - FC'!$D$11:$D1028,">=01/05"&$C$7,'Livro Diario - FC'!$D$11:$D1028,"<=31/05"&$C$7) -> 0 | Y22: =SUMIFS('Livro Diario - FC'!$L$11:$L1028,'Livro Diario - FC'!$E$11:$E1028,$C$22,'Livro Diario - FC'!$D$11:$D1028,">=01/05"&$C$7,'Livro Diario - FC'!$D$11:$D1028,"<=31/05"&$C$7) -> 0 | AC22: =SUMIFS('Livro Diario - FC'!$J$11:$J1028,'Livro Diario - FC'!$E$11:$E1028,$C$22,'Livro Diario - FC'!$D$11:$D1028,">=01/06"&$C$7,'Livro Diario - FC'!$D$11:$D1028,"<=30/06"&$C$7) -> 0 | AD22: =SUMIFS('Livro Diario - FC'!$L$11:$L1028,'Livro Diario - FC'!$E$11:$E1028,$C$22,'Livro Diario - FC'!$D$11:$D1028,">=01/06"&$C$7,'Livro Diario - FC'!$D$11:$D1028,"<=30/06"&$C$7) -> 0 | AG22: =SUMIFS('Livro Diario - FC'!$J$11:$J1028,'Livro Diario - FC'!$E$11:$E1028,$C$22,'Livro Diario - FC'!$D$11:$D1028,">=01/07"&$C$7,'Livro Diario - FC'!$D$11:$D1028,"<=31/07"&$C$7) -> 0 | AH22: =SUMIFS('Livro Diario - FC'!$L$11:$L1028,'Livro Diario - FC'!$E$11:$E1028,$C$22,'Livro Diario - FC'!$D$11:$D1028,">=01/07"&$C$7,'Livro Diario - FC'!$D$11:$D1028,"<=31/07"&$C$7) -> 0 | AK22: =SUMIFS('Livro Diario - FC'!$J$11:$J1028,'Livro Diario - FC'!$E$11:$E1028,$C$22,'Livro Diario - FC'!$D$11:$D1028,">=01/08"&$C$7,'Livro Diario - FC'!$D$11:$D1028,"<=31/08"&$C$7) -> 0 | AL22: =SUMIFS('Livro Diario - FC'!$L$11:$L1028,'Livro Diario - FC'!$E$11:$E1028,$C$22,'Livro Diario - FC'!$D$11:$D1028,">=01/08"&$C$7,'Livro Diario - FC'!$D$11:$D1028,"<=31/08"&$C$7) -> 0 | AO22: =SUMIFS('Livro Diario - FC'!$J$11:$J1028,'Livro Diario - FC'!$E$11:$E1028,$C$22,'Livro Diario - FC'!$D$11:$D1028,">=01/09"&$C$7,'Livro Diario - FC'!$D$11:$D1028,"<=30/09"&$C$7) -> 0 | AP22: =SUMIFS('Livro Diario - FC'!$L$11:$L1028,'Livro Diario - FC'!$E$11:$E1028,$C$22,'Livro Diario - FC'!$D$11:$D1028,">=01/09"&$C$7,'Livro Diario - FC'!$D$11:$D1028,"<=30/09"&$C$7) -> 0 | AS22: =SUMIFS('Livro Diario - FC'!$J$11:$J1028,'Livro Diario - FC'!$E$11:$E1028,$C$22,'Livro Diario - FC'!$D$11:$D1028,">=01/10"&$C$7,'Livro Diario - FC'!$D$11:$D1028,"<=31/10"&$C$7) -> 0 | AT22: =SUMIFS('Livro Diario - FC'!$L$11:$L1028,'Livro Diario - FC'!$E$11:$E1028,$C$22,'Livro Diario - FC'!$D$11:$D1028,">=01/10"&$C$7,'Livro Diario - FC'!$D$11:$D1028,"<=31/10"&$C$7) -> 0 | AW22: =SUMIFS('Livro Diario - FC'!$J$11:$J1028,'Livro Diario - FC'!$E$11:$E1028,$C$22,'Livro Diario - FC'!$D$11:$D1028,">=01/11"&$C$7,'Livro Diario - FC'!$D$11:$D1028,"<=30/11"&$C$7) -> 0 | AX22: =SUMIFS('Livro Diario - FC'!$L$11:$L1028,'Livro Diario - FC'!$E$11:$E1028,$C$22,'Livro Diario - FC'!$D$11:$D1028,">=01/11"&$C$7,'Livro Diario - FC'!$D$11:$D1028,"<=30/11"&$C$7) -> 0 | BA22: =SUMIFS('Livro Diario - FC'!$J$11:$J1028,'Livro Diario - FC'!$E$11:$E1028,$C$22,'Livro Diario - FC'!$D$11:$D1028,">=01/12"&$C$7,'Livro Diario - FC'!$D$11:$D1028,"<=31/12"&$C$7) -> 0 | BB22: =SUMIFS('Livro Diario - FC'!$L$11:$L1028,'Livro Diario - FC'!$E$11:$E1028,$C$22,'Livro Diario - FC'!$D$11:$D1028,">=01/12"&$C$7,'Livro Diario - FC'!$D$11:$D1028,"<=31/12"&$C$7) -> 0 | BE22: =SUM(D22,I22,N22,S22,X22,AC22,AG22,AK22,AO22,AS22,AW22,BA22) -> 0 | BF22: =SUM(E22,J22,O22,T22,Y22,AD22,AH22,AL22,AP22,AT22,AX22,BB22) -> 0 | BI22: =SUMIFS('Livro Diario - FC'!$L$11:$L1028,'Livro Diario - FC'!$E$11:$E1028,C22,'Livro Diario - FC'!$D$11:$D1028,">="&$BK$8,'Livro Diario - FC'!$D$11:$D1028,"<="&$BK$9) -> 0
C23: ='Livro Diario - FC'!AE22 -> 3.1.11 - | D23: =SUMIFS('Livro Diario - FC'!$J$11:$J1028,'Livro Diario - FC'!$E$11:$E1028,$C$23,'Livro Diario - FC'!$D$11:$D1028,">=01/01"&$C$7,'Livro Diario - FC'!$D$11:$D1028,"<=31/01"&$C$7) -> 0 | E23: =SUMIFS('Livro Diario - FC'!$L$11:$L1028,'Livro Diario - FC'!$E$11:$E1028,$C$23,'Livro Diario - FC'!$D$11:$D1028,">=01/01"&$C$7,'Livro Diario - FC'!$D$11:$D1028,"<=31/01"&$C$7) -> 0 | F23: =IF(E$11=0,"",E23/E$11) -> 0 | I23: =SUMIFS('Livro Diario - FC'!$J$11:$J1028,'Livro Diario - FC'!$E$11:$E1028,$C$22,'Livro Diario - FC'!$D$11:$D1028,">=01/02"&$C$7,'Livro Diario - FC'!$D$11:$D1028,"<=29/02"&$C$7) -> 0 | J23: =SUMIFS('Livro Diario - FC'!$L$11:$L1028,'Livro Diario - FC'!$E$11:$E1028,$C$22,'Livro Diario - FC'!$D$11:$D1028,">=01/02"&$C$7,'Livro Diario - FC'!$D$11:$D1028,"<=29/02"&$C$7) -> 0 | N23: =SUMIFS('Livro Diario - FC'!$J$11:$J1028,'Livro Diario - FC'!$E$11:$E1028,$C$22,'Livro Diario - FC'!$D$11:$D1028,">=01/03"&$C$7,'Livro Diario - FC'!$D$11:$D1028,"<=31/03"&$C$7) -> 0 | O23: =SUMIFS('Livro Diario - FC'!$L$11:$L1028,'Livro Diario - FC'!$E$11:$E1028,$C$22,'Livro Diario - FC'!$D$11:$D1028,">=01/03"&$C$7,'Livro Diario - FC'!$D$11:$D1028,"<=31/03"&$C$7) -> 0 | S23: =SUMIFS('Livro Diario - FC'!$J$11:$J1028,'Livro Diario - FC'!$E$11:$E1028,$C$22,'Livro Diario - FC'!$D$11:$D1028,">=01/04"&$C$7,'Livro Diario - FC'!$D$11:$D1028,"<=30/04"&$C$7) -> 0 | T23: =SUMIFS('Livro Diario - FC'!$L$11:$L1028,'Livro Diario - FC'!$E$11:$E1028,$C$22,'Livro Diario - FC'!$D$11:$D1028,">=01/04"&$C$7,'Livro Diario - FC'!$D$11:$D1028,"<=30/04"&$C$7) -> 0 | X23: =SUMIFS('Livro Diario - FC'!$J$11:$J1028,'Livro Diario - FC'!$E$11:$E1028,$C$22,'Livro Diario - FC'!$D$11:$D1028,">=01/05"&$C$7,'Livro Diario - FC'!$D$11:$D1028,"<=31/05"&$C$7) -> 0 | Y23: =SUMIFS('Livro Diario - FC'!$L$11:$L1028,'Livro Diario - FC'!$E$11:$E1028,$C$22,'Livro Diario - FC'!$D$11:$D1028,">=01/05"&$C$7,'Livro Diario - FC'!$D$11:$D1028,"<=31/05"&$C$7) -> 0 | AC23: =SUMIFS('Livro Diario - FC'!$J$11:$J1028,'Livro Diario - FC'!$E$11:$E1028,$C$22,'Livro Diario - FC'!$D$11:$D1028,">=01/06"&$C$7,'Livro Diario - FC'!$D$11:$D1028,"<=30/06"&$C$7) -> 0 | AD23: =SUMIFS('Livro Diario - FC'!$L$11:$L1028,'Livro Diario - FC'!$E$11:$E1028,$C$22,'Livro Diario - FC'!$D$11:$D1028,">=01/06"&$C$7,'Livro Diario - FC'!$D$11:$D1028,"<=30/06"&$C$7) -> 0 | AG23: =SUMIFS('Livro Diario - FC'!$J$11:$J1028,'Livro Diario - FC'!$E$11:$E1028,$C$22,'Livro Diario - FC'!$D$11:$D1028,">=01/07"&$C$7,'Livro Diario - FC'!$D$11:$D1028,"<=31/07"&$C$7) -> 0 | AH23: =SUMIFS('Livro Diario - FC'!$L$11:$L1028,'Livro Diario - FC'!$E$11:$E1028,$C$22,'Livro Diario - FC'!$D$11:$D1028,">=01/07"&$C$7,'Livro Diario - FC'!$D$11:$D1028,"<=31/07"&$C$7) -> 0 | AK23: =SUMIFS('Livro Diario - FC'!$J$11:$J1028,'Livro Diario - FC'!$E$11:$E1028,$C$22,'Livro Diario - FC'!$D$11:$D1028,">=01/08"&$C$7,'Livro Diario - FC'!$D$11:$D1028,"<=31/08"&$C$7) -> 0 | AL23: =SUMIFS('Livro Diario - FC'!$L$11:$L1028,'Livro Diario - FC'!$E$11:$E1028,$C$22,'Livro Diario - FC'!$D$11:$D1028,">=01/08"&$C$7,'Livro Diario - FC'!$D$11:$D1028,"<=31/08"&$C$7) -> 0 | AO23: =SUMIFS('Livro Diario - FC'!$J$11:$J1028,'Livro Diario - FC'!$E$11:$E1028,$C$22,'Livro Diario - FC'!$D$11:$D1028,">=01/09"&$C$7,'Livro Diario - FC'!$D$11:$D1028,"<=30/09"&$C$7) -> 0 | AP23: =SUMIFS('Livro Diario - FC'!$L$11:$L1028,'Livro Diario - FC'!$E$11:$E1028,$C$22,'Livro Diario - FC'!$D$11:$D1028,">=01/09"&$C$7,'Livro Diario - FC'!$D$11:$D1028,"<=30/09"&$C$7) -> 0 | AS23: =SUMIFS('Livro Diario - FC'!$J$11:$J1028,'Livro Diario - FC'!$E$11:$E1028,$C$22,'Livro Diario - FC'!$D$11:$D1028,">=01/10"&$C$7,'Livro Diario - FC'!$D$11:$D1028,"<=31/10"&$C$7) -> 0 | AT23: =SUMIFS('Livro Diario - FC'!$L$11:$L1028,'Livro Diario - FC'!$E$11:$E1028,$C$22,'Livro Diario - FC'!$D$11:$D1028,">=01/10"&$C$7,'Livro Diario - FC'!$D$11:$D1028,"<=31/10"&$C$7) -> 0 | AW23: =SUMIFS('Livro Diario - FC'!$J$11:$J1028,'Livro Diario - FC'!$E$11:$E1028,$C$22,'Livro Diario - FC'!$D$11:$D1028,">=01/11"&$C$7,'Livro Diario - FC'!$D$11:$D1028,"<=30/11"&$C$7) -> 0 | AX23: =SUMIFS('Livro Diario - FC'!$L$11:$L1028,'Livro Diario - FC'!$E$11:$E1028,$C$22,'Livro Diario - FC'!$D$11:$D1028,">=01/11"&$C$7,'Livro Diario - FC'!$D$11:$D1028,"<=30/11"&$C$7) -> 0 | BA23: =SUMIFS('Livro Diario - FC'!$J$11:$J1028,'Livro Diario - FC'!$E$11:$E1028,$C$22,'Livro Diario - FC'!$D$11:$D1028,">=01/12"&$C$7,'Livro Diario - FC'!$D$11:$D1028,"<=31/12"&$C$7) -> 0 | BB23: =SUMIFS('Livro Diario - FC'!$L$11:$L1028,'Livro Diario - FC'!$E$11:$E1028,$C$22,'Livro Diario - FC'!$D$11:$D1028,">=01/12"&$C$7,'Livro Diario - FC'!$D$11:$D1028,"<=31/12"&$C$7) -> 0 | BE23: =SUM(D23,I23,N23,S23,X23,AC23,AG23,AK23,AO23,AS23,AW23,BA23) -> 0 | BF23: =SUM(E23,J23,O23,T23,Y23,AD23,AH23,AL23,AP23,AT23,AX23,BB23) -> 0 | BI23: =SUMIFS('Livro Diario - FC'!$L$11:$L1028,'Livro Diario - FC'!$E$11:$E1028,C23,'Livro Diario - FC'!$D$11:$D1028,">="&$BK$8,'Livro Diario - FC'!$D$11:$D1028,"<="&$BK$9) -> 0
C24: DESPESAS/CUSTOS VARIÁVEIS | D24: =SUM(D25+D35) -> 10707.89 | E24: =SUM(E25+E35) -> 10707.89 | F24: =IF(E$11=0,"",E24/E$11) -> 1.3810039 | G24: =IF(A24=0,"",E24/A24-1) | I24: =SUM(I25+I35) -> 0 | J24: =SUM(J25+J35) -> 0 | K24: =IF(J$11=0,"",J24/J$11) | L24: =IF(E24=0,"",J24/E24-1) -> -1 | N24: =SUM(N25+N35) -> 0 | O24: =SUM(O25+O35) -> 0 | P24: =IF(O$11=0,"",O24/O$11) | Q24: =IF(J24=0,"",O24/J24-1) | S24: =SUM(S25+S35) -> 0 | T24: =SUM(T25+T35) -> 0 | U24: =IF(T$11=0,"",T24/T$11) | V24: =IF(O24=0,"",T24/O24-1) | X24: =SUM(X25+X35) -> 0 | Y24: =SUM(Y25+Y35) -> 0 | Z24: =IF(Y$11=0,"",Y24/Y$11) | AA24: =IF(T24=0,"",Y24/T24-1) | AC24: =SUM(AC25+AC35) -> 0 | AD24: =SUM(AD25+AD35) -> 0 | AE24: =IF(AD$11=0,"",AD24/AD$11) | AF24: =IF(Y24=0,"",AD24/Y24-1) | AG24: =SUM(AG25+AG35) -> 0 | AH24: =SUM(AH25+AH35) -> 0 | AI24: =IF(AH$11=0,"",AH24/AH$11) | AJ24: =IF(AD24=0,"",AH24/AD24-1) | AK24: =SUM(AK25+AK35) -> 0 | AL24: =SUM(AL25+AL35) -> 0 | AM24: =IF(AL$11=0,"",AL24/AL$11) | AN24: =IF(AH24=0,"",AL24/AH24-1) | AO24: =SUM(AO25+AO35) -> 0 | AP24: =SUM(AP25+AP35) -> 0 | AQ24: =IF(AP$11=0,"",AP24/AP$11) | AR24: =IF(AL24=0,"",AP24/AL24-1) | AS24: =SUM(AS25+AS35) -> 0 | AT24: =SUM(AT25+AT35) -> 0 | AU24: =IF(AT$11=0,"",AT24/AT$11) | AV24: =IF(AP24=0,"",AT24/AP24-1) | AW24: =SUM(AW25+AW35) -> 0 | AX24: =SUM(AX25+AX35) -> 0 | AY24: =IF(AX$11=0,"",AX24/AX$11) | AZ24: =IF(AT24=0,"",AX24/AT24-1) | BA24: =SUM(BA25+BA35) -> 0 | BB24: =SUM(BB25+BB35) -> 0 | BC24: =IF(BB$11=0,"",BB24/BB$11) | BD24: =IF(AX24=0,"",BB24/AX24-1) | BE24: =SUM(D24,I24,N24,S24,X24,AC24,AG24,AK24,AO24,AS24,AW24,BA24) -> 10707.89 | BF24: =SUM(E24,J24,O24,T24,Y24,AD24,AH24,AL24,AP24,AT24,AX24,BB24) -> 10707.89 | BG24: =IF(BF$11=0,"",BF24/BF$11) -> 1.3810039 | BI24: =SUM(BI25,BI35,BI43,BI47) -> 0 | BJ24: =IF(BI$11=0,"",BI24/BI$11)
C25: 4.1 Custos Tributários e Financeiros | D25: =SUMIFS('Livro Diario - FC'!$J$11:$J1028,'Livro Diario - FC'!$E$11:$E1028,$C$25,'Livro Diario - FC'!$D$11:$D1028,">=01/01"&$C$7,'Livro Diario - FC'!$D$11:$D1028,"<=31/01"&$C$7)+SUM(D26:D30) -> 0 | E25: =SUMIFS('Livro Diario - FC'!$L$11:$L1028,'Livro Diario - FC'!$E$11:$E1028,$C$25,'Livro Diario - FC'!$D$11:$D1028,">=01/01"&$C$7,'Livro Diario - FC'!$D$11:$D1028,"<=31/01"&$C$7)+SUM(E26:E30) -> 0 | F25: =IF(E$11=0,"",E25/E$11) -> 0 | G25: =IF(A25=0,"",E25/A25-1) | I25: =SUMIFS('Livro Diario - FC'!$J$11:$J1028,'Livro Diario - FC'!$E$11:$E1028,$C$25,'Livro Diario - FC'!$D$11:$D1028,">=01/02"&$C$7,'Livro Diario - FC'!$D$11:$D1028,"<=29/02"&$C$7)+SUM(I26:I30) -> 0 | J25: =SUMIFS('Livro Diario - FC'!$L$11:$L1028,'Livro Diario - FC'!$E$11:$E1028,$C$25,'Livro Diario - FC'!$D$11:$D1028,">=01/02"&$C$7,'Livro Diario - FC'!$D$11:$D1028,"<=29/02"&$C$7)+SUM(J26:J30) -> 0 | K25: =IF(J$11=0,"",J25/J$11) | L25: =IF(E25=0,"",J25/E25-1) | N25: =SUMIFS('Livro Diario - FC'!$J$11:$J1028,'Livro Diario - FC'!$E$11:$E1028,$C$25,'Livro Diario - FC'!$D$11:$D1028,">=01/03"&$C$7,'Livro Diario - FC'!$D$11:$D1028,"<=31/03"&$C$7)+SUM(N26:N30) -> 0 | O25: =SUMIFS('Livro Diario - FC'!$L$11:$L1028,'Livro Diario - FC'!$E$11:$E1028,$C$25,'Livro Diario - FC'!$D$11:$D1028,">=01/03"&$C$7,'Livro Diario - FC'!$D$11:$D1028,"<=31/03"&$C$7)+SUM(O26:O30) -> 0 | P25: =IF(O$11=0,"",O25/O$11) | Q25: =IF(J25=0,"",O25/J25-1) | S25: =SUMIFS('Livro Diario - FC'!$J$11:$J1028,'Livro Diario - FC'!$E$11:$E1028,$C$25,'Livro Diario - FC'!$D$11:$D1028,">=01/04"&$C$7,'Livro Diario - FC'!$D$11:$D1028,"<=30/04"&$C$7)+SUM(S26:S30) -> 0 | T25: =SUMIFS('Livro Diario - FC'!$L$11:$L1028,'Livro Diario - FC'!$E$11:$E1028,$C$25,'Livro Diario - FC'!$D$11:$D1028,">=01/04"&$C$7,'Livro Diario - FC'!$D$11:$D1028,"<=30/04"&$C$7)+SUM(T26:T30) -> 0 | U25: =IF(T$11=0,"",T25/T$11) | V25: =IF(O25=0,"",T25/O25-1) | X25: =SUMIFS('Livro Diario - FC'!$J$11:$J1028,'Livro Diario - FC'!$E$11:$E1028,$C$25,'Livro Diario - FC'!$D$11:$D1028,">=01/05"&$C$7,'Livro Diario - FC'!$D$11:$D1028,"<=31/05"&$C$7)+SUM(X26:X30) -> 0 | Y25: =SUMIFS('Livro Diario - FC'!$L$11:$L1028,'Livro Diario - FC'!$E$11:$E1028,$C$25,'Livro Diario - FC'!$D$11:$D1028,">=01/05"&$C$7,'Livro Diario - FC'!$D$11:$D1028,"<=31/05"&$C$7)+SUM(Y26:Y30) -> 0 | Z25: =IF(Y$11=0,"",Y25/Y$11) | AA25: =IF(T25=0,"",Y25/T25-1) | AC25: =SUMIFS('Livro Diario - FC'!$J$11:$J1028,'Livro Diario - FC'!$E$11:$E1028,$C$25,'Livro Diario - FC'!$D$11:$D1028,">=01/06"&$C$7,'Livro Diario - FC'!$D$11:$D1028,"<=30/06"&$C$7)+SUM(AC26:AC30) -> 0 | AD25: =SUMIFS('Livro Diario - FC'!$L$11:$L1028,'Livro Diario - FC'!$E$11:$E1028,$C$25,'Livro Diario - FC'!$D$11:$D1028,">=01/06"&$C$7,'Livro Diario - FC'!$D$11:$D1028,"<=30/06"&$C$7)+SUM(AD26:AD30) -> 0 | AE25: =IF(AD$11=0,"",AD25/AD$11) | AF25: =IF(Y25=0,"",AD25/Y25-1) | AG25: =SUMIFS('Livro Diario - FC'!$J$11:$J1028,'Livro Diario - FC'!$E$11:$E1028,$C$25,'Livro Diario - FC'!$D$11:$D1028,">=01/07"&$C$7,'Livro Diario - FC'!$D$11:$D1028,"<=31/07"&$C$7)+SUM(AG26:AG30) -> 0 | AH25: =SUMIFS('Livro Diario - FC'!$L$11:$L1028,'Livro Diario - FC'!$E$11:$E1028,$C$25,'Livro Diario - FC'!$D$11:$D1028,">=01/07"&$C$7,'Livro Diario - FC'!$D$11:$D1028,"<=31/07"&$C$7)+SUM(AH26:AH30) -> 0 | AI25: =IF(AH$11=0,"",AH25/AH$11) | AJ25: =IF(AD25=0,"",AH25/AD25-1) | AK25: =SUMIFS('Livro Diario - FC'!$J$11:$J1028,'Livro Diario - FC'!$E$11:$E1028,$C$25,'Livro Diario - FC'!$D$11:$D1028,">=01/08"&$C$7,'Livro Diario - FC'!$D$11:$D1028,"<=31/08"&$C$7)+SUM(AK26:AK30) -> 0 | AL25: =SUMIFS('Livro Diario - FC'!$L$11:$L1028,'Livro Diario - FC'!$E$11:$E1028,$C$25,'Livro Diario - FC'!$D$11:$D1028,">=01/08"&$C$7,'Livro Diario - FC'!$D$11:$D1028,"<=31/08"&$C$7)+SUM(AL26:AL30) -> 0 | AM25: =IF(AL$11=0,"",AL25/AL$11) | AN25: =IF(AH25=0,"",AL25/AH25-1) | AO25: =SUMIFS('Livro Diario - FC'!$J$11:$J1028,'Livro Diario - FC'!$E$11:$E1028,$C$25,'Livro Diario - FC'!$D$11:$D1028,">=01/09"&$C$7,'Livro Diario - FC'!$D$11:$D1028,"<=30/09"&$C$7)+SUM(AO26:AO30) -> 0 | AP25: =SUMIFS('Livro Diario - FC'!$L$11:$L1028,'Livro Diario - FC'!$E$11:$E1028,$C$25,'Livro Diario - FC'!$D$11:$D1028,">=01/09"&$C$7,'Livro Diario - FC'!$D$11:$D1028,"<=30/09"&$C$7)+SUM(AP26:AP30) -> 0 | AQ25: =IF(AP$11=0,"",AP25/AP$11) | AR25: =IF(AL25=0,"",AP25/AL25-1) | AS25: =SUMIFS('Livro Diario - FC'!$J$11:$J1028,'Livro Diario - FC'!$E$11:$E1028,$C$25,'Livro Diario - FC'!$D$11:$D1028,">=01/10"&$C$7,'Livro Diario - FC'!$D$11:$D1028,"<=31/10"&$C$7)+SUM(AS26:AS30) -> 0 | AT25: =SUMIFS('Livro Diario - FC'!$L$11:$L1028,'Livro Diario - FC'!$E$11:$E1028,$C$25,'Livro Diario - FC'!$D$11:$D1028,">=01/10"&$C$7,'Livro Diario - FC'!$D$11:$D1028,"<=31/10"&$C$7)+SUM(AT26:AT30) -> 0 | AU25: =IF(AT$11=0,"",AT25/AT$11) | AV25: =IF(AP25=0,"",AT25/AP25-1) | AW25: =SUMIFS('Livro Diario - FC'!$J$11:$J1028,'Livro Diario - FC'!$E$11:$E1028,$C$25,'Livro Diario - FC'!$D$11:$D1028,">=01/11"&$C$7,'Livro Diario - FC'!$D$11:$D1028,"<=30/11"&$C$7)+SUM(AW26:AW30) -> 0 | AX25: =SUMIFS('Livro Diario - FC'!$L$11:$L1028,'Livro Diario - FC'!$E$11:$E1028,$C$25,'Livro Diario - FC'!$D$11:$D1028,">=01/11"&$C$7,'Livro Diario - FC'!$D$11:$D1028,"<=30/11"&$C$7)+SUM(AX26:AX30) -> 0 | AY25: =IF(AX$11=0,"",AX25/AX$11) | AZ25: =IF(AT25=0,"",AX25/AT25-1) | BA25: =SUMIFS('Livro Diario - FC'!$J$11:$J1028,'Livro Diario - FC'!$E$11:$E1028,$C$25,'Livro Diario - FC'!$D$11:$D1028,">=01/12"&$C$7,'Livro Diario - FC'!$D$11:$D1028,"<=31/12"&$C$7)+SUM(BA26:BA30) -> 0 | BB25: =SUMIFS('Livro Diario - FC'!$L$11:$L1028,'Livro Diario - FC'!$E$11:$E1028,$C$25,'Livro Diario - FC'!$D$11:$D1028,">=01/12"&$C$7,'Livro Diario - FC'!$D$11:$D1028,"<=31/12"&$C$7)+SUM(BB26:BB30) -> 0 | BC25: =IF(BB$11=0,"",BB25/BB$11) | BD25: =IF(AX25=0,"",BB25/AX25-1) | BE25: =SUM(D25,I25,N25,S25,X25,AC25,AG25,AK25,AO25,AS25,AW25,BA25) -> 0 | BF25: =SUM(E25,J25,O25,T25,Y25,AD25,AH25,AL25,AP25,AT25,AX25,BB25) -> 0 | BG25: =IF(BF$11=0,"",BF25/BF$11) -> 0 | BI25: =SUMIFS('Livro Diario - FC'!$M$11:$M1028,'Livro Diario - FC'!$E$11:$E1028,C25,'Livro Diario - FC'!$D$11:$D1028,">="&$BK$8,'Livro Diario - FC'!$D$11:$D1028,"<="&$BK$9)+SUM(BI26:BI30) -> 0 | BJ25: =IF(BI$11=0,"",BI25/BI$11)
C26: ='Livro Diario - FC'!AE29 -> 4.1.1 Simples Federal | D26: =SUMIFS('Livro Diario - FC'!$K$11:$K1028,'Livro Diario - FC'!$E$11:$E1028,$C$26,'Livro Diario - FC'!$D$11:$D1028,">=01/01"&$C$7,'Livro Diario - FC'!$D$11:$D1028,"<=31/01"&$C$7) -> 0 | E26: =SUMIFS('Livro Diario - FC'!$M$11:$M1028,'Livro Diario - FC'!$E$11:$E1028,$C$26,'Livro Diario - FC'!$D$11:$D1028,">=01/01"&$C$7,'Livro Diario - FC'!$D$11:$D1028,"<=31/01"&$C$7) -> 0 | I26: =SUMIFS('Livro Diario - FC'!$K$11:$K1028,'Livro Diario - FC'!$E$11:$E1028,$C$26,'Livro Diario - FC'!$D$11:$D1028,">=01/02"&$C$7,'Livro Diario - FC'!$D$11:$D1028,"<=29/02"&$C$7) -> 0 | J26: =SUMIFS('Livro Diario - FC'!$M$11:$M1028,'Livro Diario - FC'!$E$11:$E1028,$C$26,'Livro Diario - FC'!$D$11:$D1028,">=01/02"&$C$7,'Livro Diario - FC'!$D$11:$D1028,"<=29/02"&$C$7) -> 0 | N26: =SUMIFS('Livro Diario - FC'!$K$11:$K1028,'Livro Diario - FC'!$E$11:$E1028,$C$26,'Livro Diario - FC'!$D$11:$D1028,">=01/03"&$C$7,'Livro Diario - FC'!$D$11:$D1028,"<=31/03"&$C$7) -> 0 | O26: =SUMIFS('Livro Diario - FC'!$M$11:$M1028,'Livro Diario - FC'!$E$11:$E1028,$C$26,'Livro Diario - FC'!$D$11:$D1028,">=01/03"&$C$7,'Livro Diario - FC'!$D$11:$D1028,"<=31/03"&$C$7) -> 0 | S26: =SUMIFS('Livro Diario - FC'!$K$11:$K1028,'Livro Diario - FC'!$E$11:$E1028,$C$26,'Livro Diario - FC'!$D$11:$D1028,">=01/04"&$C$7,'Livro Diario - FC'!$D$11:$D1028,"<=30/04"&$C$7) -> 0 | T26: =SUMIFS('Livro Diario - FC'!$M$11:$M1028,'Livro Diario - FC'!$E$11:$E1028,$C$26,'Livro Diario - FC'!$D$11:$D1028,">=01/04"&$C$7,'Livro Diario - FC'!$D$11:$D1028,"<=30/04"&$C$7) -> 0 | X26: =SUMIFS('Livro Diario - FC'!$K$11:$K1028,'Livro Diario - FC'!$E$11:$E1028,$C$26,'Livro Diario - FC'!$D$11:$D1028,">=01/05"&$C$7,'Livro Diario - FC'!$D$11:$D1028,"<=31/05"&$C$7) -> 0 | Y26: =SUMIFS('Livro Diario - FC'!$M$11:$M1028,'Livro Diario - FC'!$E$11:$E1028,$C$26,'Livro Diario - FC'!$D$11:$D1028,">=01/05"&$C$7,'Livro Diario - FC'!$D$11:$D1028,"<=31/05"&$C$7) -> 0 | AC26: =SUMIFS('Livro Diario - FC'!$K$11:$K1028,'Livro Diario - FC'!$E$11:$E1028,$C$26,'Livro Diario - FC'!$D$11:$D1028,">=01/06"&$C$7,'Livro Diario - FC'!$D$11:$D1028,"<=30/06"&$C$7) -> 0 | AD26: =SUMIFS('Livro Diario - FC'!$M$11:$M1028,'Livro Diario - FC'!$E$11:$E1028,$C$26,'Livro Diario - FC'!$D$11:$D1028,">=01/06"&$C$7,'Livro Diario - FC'!$D$11:$D1028,"<=30/06"&$C$7) -> 0 | AG26: =SUMIFS('Livro Diario - FC'!$K$11:$K1028,'Livro Diario - FC'!$E$11:$E1028,$C$26,'Livro Diario - FC'!$D$11:$D1028,">=01/07"&$C$7,'Livro Diario - FC'!$D$11:$D1028,"<=31/07"&$C$7) -> 0 | AH26: =SUMIFS('Livro Diario - FC'!$M$11:$M1028,'Livro Diario - FC'!$E$11:$E1028,$C$26,'Livro Diario - FC'!$D$11:$D1028,">=01/07"&$C$7,'Livro Diario - FC'!$D$11:$D1028,"<=31/07"&$C$7) -> 0 | AK26: =SUMIFS('Livro Diario - FC'!$K$11:$K1028,'Livro Diario - FC'!$E$11:$E1028,$C$26,'Livro Diario - FC'!$D$11:$D1028,">=01/08"&$C$7,'Livro Diario - FC'!$D$11:$D1028,"<=31/08"&$C$7) -> 0 | AL26: =SUMIFS('Livro Diario - FC'!$M$11:$M1028,'Livro Diario - FC'!$E$11:$E1028,$C$26,'Livro Diario - FC'!$D$11:$D1028,">=01/08"&$C$7,'Livro Diario - FC'!$D$11:$D1028,"<=31/08"&$C$7) -> 0 | AO26: =SUMIFS('Livro Diario - FC'!$K$11:$K1028,'Livro Diario - FC'!$E$11:$E1028,$C$26,'Livro Diario - FC'!$D$11:$D1028,">=01/09"&$C$7,'Livro Diario - FC'!$D$11:$D1028,"<=30/09"&$C$7) -> 0 | AP26: =SUMIFS('Livro Diario - FC'!$M$11:$M1028,'Livro Diario - FC'!$E$11:$E1028,$C$26,'Livro Diario - FC'!$D$11:$D1028,">=01/09"&$C$7,'Livro Diario - FC'!$D$11:$D1028,"<=30/09"&$C$7) -> 0 | AS26: =SUMIFS('Livro Diario - FC'!$K$11:$K1028,'Livro Diario - FC'!$E$11:$E1028,$C$26,'Livro Diario - FC'!$D$11:$D1028,">=01/10"&$C$7,'Livro Diario - FC'!$D$11:$D1028,"<=31/10"&$C$7) -> 0 | AT26: =SUMIFS('Livro Diario - FC'!$M$11:$M1028,'Livro Diario - FC'!$E$11:$E1028,$C$26,'Livro Diario - FC'!$D$11:$D1028,">=01/10"&$C$7,'Livro Diario - FC'!$D$11:$D1028,"<=31/10"&$C$7) -> 0 | AW26: =SUMIFS('Livro Diario - FC'!$K$11:$K1028,'Livro Diario - FC'!$E$11:$E1028,$C$26,'Livro Diario - FC'!$D$11:$D1028,">=01/11"&$C$7,'Livro Diario - FC'!$D$11:$D1028,"<=30/11"&$C$7) -> 0 | AX26: =SUMIFS('Livro Diario - FC'!$M$11:$M1028,'Livro Diario - FC'!$E$11:$E1028,$C$26,'Livro Diario - FC'!$D$11:$D1028,">=01/11"&$C$7,'Livro Diario - FC'!$D$11:$D1028,"<=30/11"&$C$7) -> 0 | BA26: =SUMIFS('Livro Diario - FC'!$K$11:$K1028,'Livro Diario - FC'!$E$11:$E1028,$C$26,'Livro Diario - FC'!$D$11:$D1028,">=01/12"&$C$7,'Livro Diario - FC'!$D$11:$D1028,"<=31/12"&$C$7) -> 0 | BB26: =SUMIFS('Livro Diario - FC'!$M$11:$M1028,'Livro Diario - FC'!$E$11:$E1028,$C$26,'Livro Diario - FC'!$D$11:$D1028,">=01/12"&$C$7,'Livro Diario - FC'!$D$11:$D1028,"<=31/12"&$C$7) -> 0 | BE26: =SUM(D26,I26,N26,S26,X26,AC26,AG26,AK26,AO26,AS26,AW26,BA26) -> 0 | BF26: =SUM(E26,J26,O26,T26,Y26,AD26,AH26,AL26,AP26,AT26,AX26,BB26) -> 0 | BI26: =SUMIFS('Livro Diario - FC'!$M$11:$M1028,'Livro Diario - FC'!$E$11:$E1028,C26,'Livro Diario - FC'!$D$11:$D1028,">="&$BK$8,'Livro Diario - FC'!$D$11:$D1028,"<="&$BK$9) -> 0
C27: ='Livro Diario - FC'!AE30 -> 4.1.2 Mercantil | D27: =SUMIFS('Livro Diario - FC'!$K$11:$K1028,'Livro Diario - FC'!$E$11:$E1028,$C$27,'Livro Diario - FC'!$D$11:$D1028,">=01/01"&$C$7,'Livro Diario - FC'!$D$11:$D1028,"<=31/01"&$C$7) -> 0 | E27: =SUMIFS('Livro Diario - FC'!$M$11:$M1028,'Livro Diario - FC'!$E$11:$E1028,$C$27,'Livro Diario - FC'!$D$11:$D1028,">=01/01"&$C$7,'Livro Diario - FC'!$D$11:$D1028,"<=31/01"&$C$7) -> 0 | I27: =SUMIFS('Livro Diario - FC'!$K$11:$K1028,'Livro Diario - FC'!$E$11:$E1028,$C$27,'Livro Diario - FC'!$D$11:$D1028,">=01/02"&$C$7,'Livro Diario - FC'!$D$11:$D1028,"<=29/02"&$C$7) -> 0 | J27: =SUMIFS('Livro Diario - FC'!$M$11:$M1028,'Livro Diario - FC'!$E$11:$E1028,$C$27,'Livro Diario - FC'!$D$11:$D1028,">=01/02"&$C$7,'Livro Diario - FC'!$D$11:$D1028,"<=29/02"&$C$7) -> 0 | N27: =SUMIFS('Livro Diario - FC'!$K$11:$K1028,'Livro Diario - FC'!$E$11:$E1028,$C$27,'Livro Diario - FC'!$D$11:$D1028,">=01/03"&$C$7,'Livro Diario - FC'!$D$11:$D1028,"<=31/03"&$C$7) -> 0 | O27: =SUMIFS('Livro Diario - FC'!$M$11:$M1028,'Livro Diario - FC'!$E$11:$E1028,$C$27,'Livro Diario - FC'!$D$11:$D1028,">=01/03"&$C$7,'Livro Diario - FC'!$D$11:$D1028,"<=31/03"&$C$7) -> 0 | S27: =SUMIFS('Livro Diario - FC'!$K$11:$K1028,'Livro Diario - FC'!$E$11:$E1028,$C$27,'Livro Diario - FC'!$D$11:$D1028,">=01/04"&$C$7,'Livro Diario - FC'!$D$11:$D1028,"<=30/04"&$C$7) -> 0 | T27: =SUMIFS('Livro Diario - FC'!$M$11:$M1028,'Livro Diario - FC'!$E$11:$E1028,$C$27,'Livro Diario - FC'!$D$11:$D1028,">=01/04"&$C$7,'Livro Diario - FC'!$D$11:$D1028,"<=30/04"&$C$7) -> 0 | X27: =SUMIFS('Livro Diario - FC'!$K$11:$K1028,'Livro Diario - FC'!$E$11:$E1028,$C$27,'Livro Diario - FC'!$D$11:$D1028,">=01/05"&$C$7,'Livro Diario - FC'!$D$11:$D1028,"<=31/05"&$C$7) -> 0 | Y27: =SUMIFS('Livro Diario - FC'!$M$11:$M1028,'Livro Diario - FC'!$E$11:$E1028,$C$27,'Livro Diario - FC'!$D$11:$D1028,">=01/05"&$C$7,'Livro Diario - FC'!$D$11:$D1028,"<=31/05"&$C$7) -> 0 | AC27: =SUMIFS('Livro Diario - FC'!$K$11:$K1028,'Livro Diario - FC'!$E$11:$E1028,$C$27,'Livro Diario - FC'!$D$11:$D1028,">=01/06"&$C$7,'Livro Diario - FC'!$D$11:$D1028,"<=30/06"&$C$7) -> 0 | AD27: =SUMIFS('Livro Diario - FC'!$M$11:$M1028,'Livro Diario - FC'!$E$11:$E1028,$C$27,'Livro Diario - FC'!$D$11:$D1028,">=01/06"&$C$7,'Livro Diario - FC'!$D$11:$D1028,"<=30/06"&$C$7) -> 0 | AG27: =SUMIFS('Livro Diario - FC'!$K$11:$K1028,'Livro Diario - FC'!$E$11:$E1028,$C$27,'Livro Diario - FC'!$D$11:$D1028,">=01/07"&$C$7,'Livro Diario - FC'!$D$11:$D1028,"<=31/07"&$C$7) -> 0 | AH27: =SUMIFS('Livro Diario - FC'!$M$11:$M1028,'Livro Diario - FC'!$E$11:$E1028,$C$27,'Livro Diario - FC'!$D$11:$D1028,">=01/07"&$C$7,'Livro Diario - FC'!$D$11:$D1028,"<=31/07"&$C$7) -> 0 | AK27: =SUMIFS('Livro Diario - FC'!$K$11:$K1028,'Livro Diario - FC'!$E$11:$E1028,$C$27,'Livro Diario - FC'!$D$11:$D1028,">=01/08"&$C$7,'Livro Diario - FC'!$D$11:$D1028,"<=31/08"&$C$7) -> 0 | AL27: =SUMIFS('Livro Diario - FC'!$M$11:$M1028,'Livro Diario - FC'!$E$11:$E1028,$C$27,'Livro Diario - FC'!$D$11:$D1028,">=01/08"&$C$7,'Livro Diario - FC'!$D$11:$D1028,"<=31/08"&$C$7) -> 0 | AO27: =SUMIFS('Livro Diario - FC'!$K$11:$K1028,'Livro Diario - FC'!$E$11:$E1028,$C$27,'Livro Diario - FC'!$D$11:$D1028,">=01/09"&$C$7,'Livro Diario - FC'!$D$11:$D1028,"<=30/09"&$C$7) -> 0 | AP27: =SUMIFS('Livro Diario - FC'!$M$11:$M1028,'Livro Diario - FC'!$E$11:$E1028,$C$27,'Livro Diario - FC'!$D$11:$D1028,">=01/09"&$C$7,'Livro Diario - FC'!$D$11:$D1028,"<=30/09"&$C$7) -> 0 | AS27: =SUMIFS('Livro Diario - FC'!$K$11:$K1028,'Livro Diario - FC'!$E$11:$E1028,$C$27,'Livro Diario - FC'!$D$11:$D1028,">=01/10"&$C$7,'Livro Diario - FC'!$D$11:$D1028,"<=31/10"&$C$7) -> 0 | AT27: =SUMIFS('Livro Diario - FC'!$M$11:$M1028,'Livro Diario - FC'!$E$11:$E1028,$C$27,'Livro Diario - FC'!$D$11:$D1028,">=01/10"&$C$7,'Livro Diario - FC'!$D$11:$D1028,"<=31/10"&$C$7) -> 0 | AW27: =SUMIFS('Livro Diario - FC'!$K$11:$K1028,'Livro Diario - FC'!$E$11:$E1028,$C$27,'Livro Diario - FC'!$D$11:$D1028,">=01/11"&$C$7,'Livro Diario - FC'!$D$11:$D1028,"<=30/11"&$C$7) -> 0 | AX27: =SUMIFS('Livro Diario - FC'!$M$11:$M1028,'Livro Diario - FC'!$E$11:$E1028,$C$27,'Livro Diario - FC'!$D$11:$D1028,">=01/11"&$C$7,'Livro Diario - FC'!$D$11:$D1028,"<=30/11"&$C$7) -> 0 | BA27: =SUMIFS('Livro Diario - FC'!$K$11:$K1028,'Livro Diario - FC'!$E$11:$E1028,$C$27,'Livro Diario - FC'!$D$11:$D1028,">=01/12"&$C$7,'Livro Diario - FC'!$D$11:$D1028,"<=31/12"&$C$7) -> 0 | BB27: =SUMIFS('Livro Diario - FC'!$M$11:$M1028,'Livro Diario - FC'!$E$11:$E1028,$C$27,'Livro Diario - FC'!$D$11:$D1028,">=01/12"&$C$7,'Livro Diario - FC'!$D$11:$D1028,"<=31/12"&$C$7) -> 0 | BE27: =SUM(D27,I27,N27,S27,X27,AC27,AG27,AK27,AO27,AS27,AW27,BA27) -> 0 | BF27: =SUM(E27,J27,O27,T27,Y27,AD27,AH27,AL27,AP27,AT27,AX27,BB27) -> 0 | BI27: =SUMIFS('Livro Diario - FC'!$M$11:$M1028,'Livro Diario - FC'!$E$11:$E1028,C27,'Livro Diario - FC'!$D$11:$D1028,">="&$BK$8,'Livro Diario - FC'!$D$11:$D1028,"<="&$BK$9) -> 0
C28: ='Livro Diario - FC'!AE31 -> 4.1.3 IPTU | D28: =SUMIFS('Livro Diario - FC'!$K$11:$K1028,'Livro Diario - FC'!$E$11:$E1028,$C$28,'Livro Diario - FC'!$D$11:$D1028,">=01/01"&$C$7,'Livro Diario - FC'!$D$11:$D1028,"<=31/01"&$C$7) -> 0 | E28: =SUMIFS('Livro Diario - FC'!$M$11:$M1028,'Livro Diario - FC'!$E$11:$E1028,$C$28,'Livro Diario - FC'!$D$11:$D1028,">=01/01"&$C$7,'Livro Diario - FC'!$D$11:$D1028,"<=31/01"&$C$7) -> 0 | I28: =SUMIFS('Livro Diario - FC'!$K$11:$K1028,'Livro Diario - FC'!$E$11:$E1028,$C$28,'Livro Diario - FC'!$D$11:$D1028,">=01/02"&$C$7,'Livro Diario - FC'!$D$11:$D1028,"<=29/02"&$C$7) -> 0 | J28: =SUMIFS('Livro Diario - FC'!$M$11:$M1028,'Livro Diario - FC'!$E$11:$E1028,$C$28,'Livro Diario - FC'!$D$11:$D1028,">=01/02"&$C$7,'Livro Diario - FC'!$D$11:$D1028,"<=29/02"&$C$7) -> 0 | N28: =SUMIFS('Livro Diario - FC'!$K$11:$K1028,'Livro Diario - FC'!$E$11:$E1028,$C$28,'Livro Diario - FC'!$D$11:$D1028,">=01/03"&$C$7,'Livro Diario - FC'!$D$11:$D1028,"<=31/03"&$C$7) -> 0 | O28: =SUMIFS('Livro Diario - FC'!$M$11:$M1028,'Livro Diario - FC'!$E$11:$E1028,$C$28,'Livro Diario - FC'!$D$11:$D1028,">=01/03"&$C$7,'Livro Diario - FC'!$D$11:$D1028,"<=31/03"&$C$7) -> 0 | S28: =SUMIFS('Livro Diario - FC'!$K$11:$K1028,'Livro Diario - FC'!$E$11:$E1028,$C$28,'Livro Diario - FC'!$D$11:$D1028,">=01/04"&$C$7,'Livro Diario - FC'!$D$11:$D1028,"<=30/04"&$C$7) -> 0 | T28: =SUMIFS('Livro Diario - FC'!$M$11:$M1028,'Livro Diario - FC'!$E$11:$E1028,$C$28,'Livro Diario - FC'!$D$11:$D1028,">=01/04"&$C$7,'Livro Diario - FC'!$D$11:$D1028,"<=30/04"&$C$7) -> 0 | X28: =SUMIFS('Livro Diario - FC'!$K$11:$K1028,'Livro Diario - FC'!$E$11:$E1028,$C$28,'Livro Diario - FC'!$D$11:$D1028,">=01/05"&$C$7,'Livro Diario - FC'!$D$11:$D1028,"<=31/05"&$C$7) -> 0 | Y28: =SUMIFS('Livro Diario - FC'!$M$11:$M1028,'Livro Diario - FC'!$E$11:$E1028,$C$28,'Livro Diario - FC'!$D$11:$D1028,">=01/05"&$C$7,'Livro Diario - FC'!$D$11:$D1028,"<=31/05"&$C$7) -> 0 | AC28: =SUMIFS('Livro Diario - FC'!$K$11:$K1028,'Livro Diario - FC'!$E$11:$E1028,$C$28,'Livro Diario - FC'!$D$11:$D1028,">=01/06"&$C$7,'Livro Diario - FC'!$D$11:$D1028,"<=30/06"&$C$7) -> 0 | AD28: =SUMIFS('Livro Diario - FC'!$M$11:$M1028,'Livro Diario - FC'!$E$11:$E1028,$C$28,'Livro Diario - FC'!$D$11:$D1028,">=01/06"&$C$7,'Livro Diario - FC'!$D$11:$D1028,"<=30/06"&$C$7) -> 0 | AG28: =SUMIFS('Livro Diario - FC'!$K$11:$K1028,'Livro Diario - FC'!$E$11:$E1028,$C$28,'Livro Diario - FC'!$D$11:$D1028,">=01/07"&$C$7,'Livro Diario - FC'!$D$11:$D1028,"<=31/07"&$C$7) -> 0 | AH28: =SUMIFS('Livro Diario - FC'!$M$11:$M1028,'Livro Diario - FC'!$E$11:$E1028,$C$28,'Livro Diario - FC'!$D$11:$D1028,">=01/07"&$C$7,'Livro Diario - FC'!$D$11:$D1028,"<=31/07"&$C$7) -> 0 | AK28: =SUMIFS('Livro Diario - FC'!$K$11:$K1028,'Livro Diario - FC'!$E$11:$E1028,$C$28,'Livro Diario - FC'!$D$11:$D1028,">=01/08"&$C$7,'Livro Diario - FC'!$D$11:$D1028,"<=31/08"&$C$7) -> 0 | AL28: =SUMIFS('Livro Diario - FC'!$M$11:$M1028,'Livro Diario - FC'!$E$11:$E1028,$C$28,'Livro Diario - FC'!$D$11:$D1028,">=01/08"&$C$7,'Livro Diario - FC'!$D$11:$D1028,"<=31/08"&$C$7) -> 0 | AO28: =SUMIFS('Livro Diario - FC'!$K$11:$K1028,'Livro Diario - FC'!$E$11:$E1028,$C$28,'Livro Diario - FC'!$D$11:$D1028,">=01/09"&$C$7,'Livro Diario - FC'!$D$11:$D1028,"<=30/09"&$C$7) -> 0 | AP28: =SUMIFS('Livro Diario - FC'!$M$11:$M1028,'Livro Diario - FC'!$E$11:$E1028,$C$28,'Livro Diario - FC'!$D$11:$D1028,">=01/09"&$C$7,'Livro Diario - FC'!$D$11:$D1028,"<=30/09"&$C$7) -> 0 | AS28: =SUMIFS('Livro Diario - FC'!$K$11:$K1028,'Livro Diario - FC'!$E$11:$E1028,$C$28,'Livro Diario - FC'!$D$11:$D1028,">=01/10"&$C$7,'Livro Diario - FC'!$D$11:$D1028,"<=31/10"&$C$7) -> 0 | AT28: =SUMIFS('Livro Diario - FC'!$M$11:$M1028,'Livro Diario - FC'!$E$11:$E1028,$C$28,'Livro Diario - FC'!$D$11:$D1028,">=01/10"&$C$7,'Livro Diario - FC'!$D$11:$D1028,"<=31/10"&$C$7) -> 0 | AW28: =SUMIFS('Livro Diario - FC'!$K$11:$K1028,'Livro Diario - FC'!$E$11:$E1028,$C$28,'Livro Diario - FC'!$D$11:$D1028,">=01/11"&$C$7,'Livro Diario - FC'!$D$11:$D1028,"<=30/11"&$C$7) -> 0 | AX28: =SUMIFS('Livro Diario - FC'!$M$11:$M1028,'Livro Diario - FC'!$E$11:$E1028,$C$28,'Livro Diario - FC'!$D$11:$D1028,">=01/11"&$C$7,'Livro Diario - FC'!$D$11:$D1028,"<=30/11"&$C$7) -> 0 | BA28: =SUMIFS('Livro Diario - FC'!$K$11:$K1028,'Livro Diario - FC'!$E$11:$E1028,$C$28,'Livro Diario - FC'!$D$11:$D1028,">=01/12"&$C$7,'Livro Diario - FC'!$D$11:$D1028,"<=31/12"&$C$7) -> 0 | BB28: =SUMIFS('Livro Diario - FC'!$M$11:$M1028,'Livro Diario - FC'!$E$11:$E1028,$C$28,'Livro Diario - FC'!$D$11:$D1028,">=01/12"&$C$7,'Livro Diario - FC'!$D$11:$D1028,"<=31/12"&$C$7) -> 0 | BE28: =SUM(D28,I28,N28,S28,X28,AC28,AG28,AK28,AO28,AS28,AW28,BA28) -> 0 | BF28: =SUM(E28,J28,O28,T28,Y28,AD28,AH28,AL28,AP28,AT28,AX28,BB28) -> 0 | BI28: =SUMIFS('Livro Diario - FC'!$M$11:$M1028,'Livro Diario - FC'!$E$11:$E1028,C28,'Livro Diario - FC'!$D$11:$D1028,">="&$BK$8,'Livro Diario - FC'!$D$11:$D1028,"<="&$BK$9) -> 0
C29: ='Livro Diario - FC'!AE32 -> 4.1.4 FGTS | D29: =SUMIFS('Livro Diario - FC'!$K$11:$K1028,'Livro Diario - FC'!$E$11:$E1028,$C$29,'Livro Diario - FC'!$D$11:$D1028,">=01/01"&$C$7,'Livro Diario - FC'!$D$11:$D1028,"<=31/01"&$C$7) -> 0 | E29: =SUMIFS('Livro Diario - FC'!$M$11:$M1028,'Livro Diario - FC'!$E$11:$E1028,$C$29,'Livro Diario - FC'!$D$11:$D1028,">=01/01"&$C$7,'Livro Diario - FC'!$D$11:$D1028,"<=31/01"&$C$7) -> 0 | I29: =SUMIFS('Livro Diario - FC'!$K$11:$K1028,'Livro Diario - FC'!$E$11:$E1028,$C$29,'Livro Diario - FC'!$D$11:$D1028,">=01/02"&$C$7,'Livro Diario - FC'!$D$11:$D1028,"<=29/02"&$C$7) -> 0 | J29: =SUMIFS('Livro Diario - FC'!$M$11:$M1028,'Livro Diario - FC'!$E$11:$E1028,$C$29,'Livro Diario - FC'!$D$11:$D1028,">=01/02"&$C$7,'Livro Diario - FC'!$D$11:$D1028,"<=29/02"&$C$7) -> 0 | N29: =SUMIFS('Livro Diario - FC'!$K$11:$K1028,'Livro Diario - FC'!$E$11:$E1028,$C$29,'Livro Diario - FC'!$D$11:$D1028,">=01/03"&$C$7,'Livro Diario - FC'!$D$11:$D1028,"<=31/03"&$C$7) -> 0 | O29: =SUMIFS('Livro Diario - FC'!$M$11:$M1028,'Livro Diario - FC'!$E$11:$E1028,$C$29,'Livro Diario - FC'!$D$11:$D1028,">=01/03"&$C$7,'Livro Diario - FC'!$D$11:$D1028,"<=31/03"&$C$7) -> 0 | S29: =SUMIFS('Livro Diario - FC'!$K$11:$K1028,'Livro Diario - FC'!$E$11:$E1028,$C$29,'Livro Diario - FC'!$D$11:$D1028,">=01/04"&$C$7,'Livro Diario - FC'!$D$11:$D1028,"<=30/04"&$C$7) -> 0 | T29: =SUMIFS('Livro Diario - FC'!$M$11:$M1028,'Livro Diario - FC'!$E$11:$E1028,$C$29,'Livro Diario - FC'!$D$11:$D1028,">=01/04"&$C$7,'Livro Diario - FC'!$D$11:$D1028,"<=30/04"&$C$7) -> 0 | X29: =SUMIFS('Livro Diario - FC'!$K$11:$K1028,'Livro Diario - FC'!$E$11:$E1028,$C$29,'Livro Diario - FC'!$D$11:$D1028,">=01/05"&$C$7,'Livro Diario - FC'!$D$11:$D1028,"<=31/05"&$C$7) -> 0 | Y29: =SUMIFS('Livro Diario - FC'!$M$11:$M1028,'Livro Diario - FC'!$E$11:$E1028,$C$29,'Livro Diario - FC'!$D$11:$D1028,">=01/05"&$C$7,'Livro Diario - FC'!$D$11:$D1028,"<=31/05"&$C$7) -> 0 | AC29: =SUMIFS('Livro Diario - FC'!$K$11:$K1028,'Livro Diario - FC'!$E$11:$E1028,$C$29,'Livro Diario - FC'!$D$11:$D1028,">=01/06"&$C$7,'Livro Diario - FC'!$D$11:$D1028,"<=30/06"&$C$7) -> 0 | AD29: =SUMIFS('Livro Diario - FC'!$M$11:$M1028,'Livro Diario - FC'!$E$11:$E1028,$C$29,'Livro Diario - FC'!$D$11:$D1028,">=01/06"&$C$7,'Livro Diario - FC'!$D$11:$D1028,"<=30/06"&$C$7) -> 0 | AG29: =SUMIFS('Livro Diario - FC'!$K$11:$K1028,'Livro Diario - FC'!$E$11:$E1028,$C$29,'Livro Diario - FC'!$D$11:$D1028,">=01/07"&$C$7,'Livro Diario - FC'!$D$11:$D1028,"<=31/07"&$C$7) -> 0 | AH29: =SUMIFS('Livro Diario - FC'!$M$11:$M1028,'Livro Diario - FC'!$E$11:$E1028,$C$29,'Livro Diario - FC'!$D$11:$D1028,">=01/07"&$C$7,'Livro Diario - FC'!$D$11:$D1028,"<=31/07"&$C$7) -> 0 | AK29: =SUMIFS('Livro Diario - FC'!$K$11:$K1028,'Livro Diario - FC'!$E$11:$E1028,$C$29,'Livro Diario - FC'!$D$11:$D1028,">=01/08"&$C$7,'Livro Diario - FC'!$D$11:$D1028,"<=31/08"&$C$7) -> 0 | AL29: =SUMIFS('Livro Diario - FC'!$M$11:$M1028,'Livro Diario - FC'!$E$11:$E1028,$C$29,'Livro Diario - FC'!$D$11:$D1028,">=01/08"&$C$7,'Livro Diario - FC'!$D$11:$D1028,"<=31/08"&$C$7) -> 0 | AO29: =SUMIFS('Livro Diario - FC'!$K$11:$K1028,'Livro Diario - FC'!$E$11:$E1028,$C$29,'Livro Diario - FC'!$D$11:$D1028,">=01/09"&$C$7,'Livro Diario - FC'!$D$11:$D1028,"<=30/09"&$C$7) -> 0 | AP29: =SUMIFS('Livro Diario - FC'!$M$11:$M1028,'Livro Diario - FC'!$E$11:$E1028,$C$29,'Livro Diario - FC'!$D$11:$D1028,">=01/09"&$C$7,'Livro Diario - FC'!$D$11:$D1028,"<=30/09"&$C$7) -> 0 | AS29: =SUMIFS('Livro Diario - FC'!$K$11:$K1028,'Livro Diario - FC'!$E$11:$E1028,$C$29,'Livro Diario - FC'!$D$11:$D1028,">=01/10"&$C$7,'Livro Diario - FC'!$D$11:$D1028,"<=31/10"&$C$7) -> 0 | AT29: =SUMIFS('Livro Diario - FC'!$M$11:$M1028,'Livro Diario - FC'!$E$11:$E1028,$C$29,'Livro Diario - FC'!$D$11:$D1028,">=01/10"&$C$7,'Livro Diario - FC'!$D$11:$D1028,"<=31/10"&$C$7) -> 0 | AW29: =SUMIFS('Livro Diario - FC'!$K$11:$K1028,'Livro Diario - FC'!$E$11:$E1028,$C$29,'Livro Diario - FC'!$D$11:$D1028,">=01/11"&$C$7,'Livro Diario - FC'!$D$11:$D1028,"<=30/11"&$C$7) -> 0 | AX29: =SUMIFS('Livro Diario - FC'!$M$11:$M1028,'Livro Diario - FC'!$E$11:$E1028,$C$29,'Livro Diario - FC'!$D$11:$D1028,">=01/11"&$C$7,'Livro Diario - FC'!$D$11:$D1028,"<=30/11"&$C$7) -> 0 | BA29: =SUMIFS('Livro Diario - FC'!$K$11:$K1028,'Livro Diario - FC'!$E$11:$E1028,$C$29,'Livro Diario - FC'!$D$11:$D1028,">=01/12"&$C$7,'Livro Diario - FC'!$D$11:$D1028,"<=31/12"&$C$7) -> 0 | BB29: =SUMIFS('Livro Diario - FC'!$M$11:$M1028,'Livro Diario - FC'!$E$11:$E1028,$C$29,'Livro Diario - FC'!$D$11:$D1028,">=01/12"&$C$7,'Livro Diario - FC'!$D$11:$D1028,"<=31/12"&$C$7) -> 0 | BE29: =SUM(D29,I29,N29,S29,X29,AC29,AG29,AK29,AO29,AS29,AW29,BA29) -> 0 | BF29: =SUM(E29,J29,O29,T29,Y29,AD29,AH29,AL29,AP29,AT29,AX29,BB29) -> 0 | BI29: =SUMIFS('Livro Diario - FC'!$M$11:$M1028,'Livro Diario - FC'!$E$11:$E1028,C29,'Livro Diario - FC'!$D$11:$D1028,">="&$BK$8,'Livro Diario - FC'!$D$11:$D1028,"<="&$BK$9) -> 0
C30: ='Livro Diario - FC'!AE33 -> 4.1.5 INSS | D30: =SUMIFS('Livro Diario - FC'!$K$11:$K1028,'Livro Diario - FC'!$E$11:$E1028,$C$30,'Livro Diario - FC'!$D$11:$D1028,">=01/01"&$C$7,'Livro Diario - FC'!$D$11:$D1028,"<=31/01"&$C$7) -> 0 | E30: =SUMIFS('Livro Diario - FC'!$M$11:$M1028,'Livro Diario - FC'!$E$11:$E1028,$C$30,'Livro Diario - FC'!$D$11:$D1028,">=01/01"&$C$7,'Livro Diario - FC'!$D$11:$D1028,"<=31/01"&$C$7) -> 0 | I30: =SUMIFS('Livro Diario - FC'!$K$11:$K1028,'Livro Diario - FC'!$E$11:$E1028,$C$30,'Livro Diario - FC'!$D$11:$D1028,">=01/02"&$C$7,'Livro Diario - FC'!$D$11:$D1028,"<=29/02"&$C$7) -> 0 | J30: =SUMIFS('Livro Diario - FC'!$M$11:$M1028,'Livro Diario - FC'!$E$11:$E1028,$C$30,'Livro Diario - FC'!$D$11:$D1028,">=01/02"&$C$7,'Livro Diario - FC'!$D$11:$D1028,"<=29/02"&$C$7) -> 0 | N30: =SUMIFS('Livro Diario - FC'!$K$11:$K1028,'Livro Diario - FC'!$E$11:$E1028,$C$30,'Livro Diario - FC'!$D$11:$D1028,">=01/03"&$C$7,'Livro Diario - FC'!$D$11:$D1028,"<=31/03"&$C$7) -> 0 | O30: =SUMIFS('Livro Diario - FC'!$M$11:$M1028,'Livro Diario - FC'!$E$11:$E1028,$C$30,'Livro Diario - FC'!$D$11:$D1028,">=01/03"&$C$7,'Livro Diario - FC'!$D$11:$D1028,"<=31/03"&$C$7) -> 0 | S30: =SUMIFS('Livro Diario - FC'!$K$11:$K1028,'Livro Diario - FC'!$E$11:$E1028,$C$30,'Livro Diario - FC'!$D$11:$D1028,">=01/04"&$C$7,'Livro Diario - FC'!$D$11:$D1028,"<=30/04"&$C$7) -> 0 | T30: =SUMIFS('Livro Diario - FC'!$M$11:$M1028,'Livro Diario - FC'!$E$11:$E1028,$C$30,'Livro Diario - FC'!$D$11:$D1028,">=01/04"&$C$7,'Livro Diario - FC'!$D$11:$D1028,"<=30/04"&$C$7) -> 0 | X30: =SUMIFS('Livro Diario - FC'!$K$11:$K1028,'Livro Diario - FC'!$E$11:$E1028,$C$30,'Livro Diario - FC'!$D$11:$D1028,">=01/05"&$C$7,'Livro Diario - FC'!$D$11:$D1028,"<=31/05"&$C$7) -> 0 | Y30: =SUMIFS('Livro Diario - FC'!$M$11:$M1028,'Livro Diario - FC'!$E$11:$E1028,$C$30,'Livro Diario - FC'!$D$11:$D1028,">=01/05"&$C$7,'Livro Diario - FC'!$D$11:$D1028,"<=31/05"&$C$7) -> 0 | AC30: =SUMIFS('Livro Diario - FC'!$K$11:$K1028,'Livro Diario - FC'!$E$11:$E1028,$C$30,'Livro Diario - FC'!$D$11:$D1028,">=01/06"&$C$7,'Livro Diario - FC'!$D$11:$D1028,"<=30/06"&$C$7) -> 0 | AD30: =SUMIFS('Livro Diario - FC'!$M$11:$M1028,'Livro Diario - FC'!$E$11:$E1028,$C$30,'Livro Diario - FC'!$D$11:$D1028,">=01/06"&$C$7,'Livro Diario - FC'!$D$11:$D1028,"<=30/06"&$C$7) -> 0 | AG30: =SUMIFS('Livro Diario - FC'!$K$11:$K1028,'Livro Diario - FC'!$E$11:$E1028,$C$30,'Livro Diario - FC'!$D$11:$D1028,">=01/07"&$C$7,'Livro Diario - FC'!$D$11:$D1028,"<=31/07"&$C$7) -> 0 | AH30: =SUMIFS('Livro Diario - FC'!$M$11:$M1028,'Livro Diario - FC'!$E$11:$E1028,$C$30,'Livro Diario - FC'!$D$11:$D1028,">=01/07"&$C$7,'Livro Diario - FC'!$D$11:$D1028,"<=31/07"&$C$7) -> 0 | AK30: =SUMIFS('Livro Diario - FC'!$K$11:$K1028,'Livro Diario - FC'!$E$11:$E1028,$C$30,'Livro Diario - FC'!$D$11:$D1028,">=01/08"&$C$7,'Livro Diario - FC'!$D$11:$D1028,"<=31/08"&$C$7) -> 0 | AL30: =SUMIFS('Livro Diario - FC'!$M$11:$M1028,'Livro Diario - FC'!$E$11:$E1028,$C$30,'Livro Diario - FC'!$D$11:$D1028,">=01/08"&$C$7,'Livro Diario - FC'!$D$11:$D1028,"<=31/08"&$C$7) -> 0 | AO30: =SUMIFS('Livro Diario - FC'!$K$11:$K1028,'Livro Diario - FC'!$E$11:$E1028,$C$30,'Livro Diario - FC'!$D$11:$D1028,">=01/09"&$C$7,'Livro Diario - FC'!$D$11:$D1028,"<=30/09"&$C$7) -> 0 | AP30: =SUMIFS('Livro Diario - FC'!$M$11:$M1028,'Livro Diario - FC'!$E$11:$E1028,$C$30,'Livro Diario - FC'!$D$11:$D1028,">=01/09"&$C$7,'Livro Diario - FC'!$D$11:$D1028,"<=30/09"&$C$7) -> 0 | AS30: =SUMIFS('Livro Diario - FC'!$K$11:$K1028,'Livro Diario - FC'!$E$11:$E1028,$C$30,'Livro Diario - FC'!$D$11:$D1028,">=01/10"&$C$7,'Livro Diario - FC'!$D$11:$D1028,"<=31/10"&$C$7) -> 0 | AT30: =SUMIFS('Livro Diario - FC'!$M$11:$M1028,'Livro Diario - FC'!$E$11:$E1028,$C$30,'Livro Diario - FC'!$D$11:$D1028,">=01/10"&$C$7,'Livro Diario - FC'!$D$11:$D1028,"<=31/10"&$C$7) -> 0 | AW30: =SUMIFS('Livro Diario - FC'!$K$11:$K1028,'Livro Diario - FC'!$E$11:$E1028,$C$30,'Livro Diario - FC'!$D$11:$D1028,">=01/11"&$C$7,'Livro Diario - FC'!$D$11:$D1028,"<=30/11"&$C$7) -> 0 | AX30: =SUMIFS('Livro Diario - FC'!$M$11:$M1028,'Livro Diario - FC'!$E$11:$E1028,$C$30,'Livro Diario - FC'!$D$11:$D1028,">=01/11"&$C$7,'Livro Diario - FC'!$D$11:$D1028,"<=30/11"&$C$7) -> 0 | BA30: =SUMIFS('Livro Diario - FC'!$K$11:$K1028,'Livro Diario - FC'!$E$11:$E1028,$C$30,'Livro Diario - FC'!$D$11:$D1028,">=01/12"&$C$7,'Livro Diario - FC'!$D$11:$D1028,"<=31/12"&$C$7) -> 0 | BB30: =SUMIFS('Livro Diario - FC'!$M$11:$M1028,'Livro Diario - FC'!$E$11:$E1028,$C$30,'Livro Diario - FC'!$D$11:$D1028,">=01/12"&$C$7,'Livro Diario - FC'!$D$11:$D1028,"<=31/12"&$C$7) -> 0 | BE30: =SUM(D30,I30,N30,S30,X30,AC30,AG30,AK30,AO30,AS30,AW30,BA30) -> 0 | BF30: =SUM(E30,J30,O30,T30,Y30,AD30,AH30,AL30,AP30,AT30,AX30,BB30) -> 0 | BI30: =SUMIFS('Livro Diario - FC'!$M$11:$M1028,'Livro Diario - FC'!$E$11:$E1028,C30,'Livro Diario - FC'!$D$11:$D1028,">="&$BK$8,'Livro Diario - FC'!$D$11:$D1028,"<="&$BK$9) -> 0
C31: ='Livro Diario - FC'!AE34 -> 4.1.6 Parcelamento Imposto | D31: =SUMIFS('Livro Diario - FC'!$K$11:$K1028,'Livro Diario - FC'!$E$11:$E1028,$C$30,'Livro Diario - FC'!$D$11:$D1028,">=01/01"&$C$7,'Livro Diario - FC'!$D$11:$D1028,"<=31/01"&$C$7) -> 0 | E31: =SUMIFS('Livro Diario - FC'!$M$11:$M1028,'Livro Diario - FC'!$E$11:$E1028,$C$30,'Livro Diario - FC'!$D$11:$D1028,">=01/01"&$C$7,'Livro Diario - FC'!$D$11:$D1028,"<=31/01"&$C$7) -> 0 | I31: =SUMIFS('Livro Diario - FC'!$K$11:$K1028,'Livro Diario - FC'!$E$11:$E1028,$C$30,'Livro Diario - FC'!$D$11:$D1028,">=01/02"&$C$7,'Livro Diario - FC'!$D$11:$D1028,"<=29/02"&$C$7) -> 0 | J31: =SUMIFS('Livro Diario - FC'!$M$11:$M1028,'Livro Diario - FC'!$E$11:$E1028,$C$30,'Livro Diario - FC'!$D$11:$D1028,">=01/02"&$C$7,'Livro Diario - FC'!$D$11:$D1028,"<=29/02"&$C$7) -> 0 | N31: =SUMIFS('Livro Diario - FC'!$K$11:$K1028,'Livro Diario - FC'!$E$11:$E1028,$C$30,'Livro Diario - FC'!$D$11:$D1028,">=01/03"&$C$7,'Livro Diario - FC'!$D$11:$D1028,"<=31/03"&$C$7) -> 0 | O31: =SUMIFS('Livro Diario - FC'!$M$11:$M1028,'Livro Diario - FC'!$E$11:$E1028,$C$30,'Livro Diario - FC'!$D$11:$D1028,">=01/03"&$C$7,'Livro Diario - FC'!$D$11:$D1028,"<=31/03"&$C$7) -> 0 | S31: =SUMIFS('Livro Diario - FC'!$K$11:$K1028,'Livro Diario - FC'!$E$11:$E1028,$C$30,'Livro Diario - FC'!$D$11:$D1028,">=01/04"&$C$7,'Livro Diario - FC'!$D$11:$D1028,"<=30/04"&$C$7) -> 0 | T31: =SUMIFS('Livro Diario - FC'!$M$11:$M1028,'Livro Diario - FC'!$E$11:$E1028,$C$30,'Livro Diario - FC'!$D$11:$D1028,">=01/04"&$C$7,'Livro Diario - FC'!$D$11:$D1028,"<=30/04"&$C$7) -> 0 | X31: =SUMIFS('Livro Diario - FC'!$K$11:$K1028,'Livro Diario - FC'!$E$11:$E1028,$C$30,'Livro Diario - FC'!$D$11:$D1028,">=01/05"&$C$7,'Livro Diario - FC'!$D$11:$D1028,"<=31/05"&$C$7) -> 0 | Y31: =SUMIFS('Livro Diario - FC'!$M$11:$M1028,'Livro Diario - FC'!$E$11:$E1028,$C$30,'Livro Diario - FC'!$D$11:$D1028,">=01/05"&$C$7,'Livro Diario - FC'!$D$11:$D1028,"<=31/05"&$C$7) -> 0 | AC31: =SUMIFS('Livro Diario - FC'!$K$11:$K1028,'Livro Diario - FC'!$E$11:$E1028,$C$30,'Livro Diario - FC'!$D$11:$D1028,">=01/06"&$C$7,'Livro Diario - FC'!$D$11:$D1028,"<=30/06"&$C$7) -> 0 | AD31: =SUMIFS('Livro Diario - FC'!$M$11:$M1028,'Livro Diario - FC'!$E$11:$E1028,$C$30,'Livro Diario - FC'!$D$11:$D1028,">=01/06"&$C$7,'Livro Diario - FC'!$D$11:$D1028,"<=30/06"&$C$7) -> 0 | AG31: =SUMIFS('Livro Diario - FC'!$K$11:$K1028,'Livro Diario - FC'!$E$11:$E1028,$C$30,'Livro Diario - FC'!$D$11:$D1028,">=01/07"&$C$7,'Livro Diario - FC'!$D$11:$D1028,"<=31/07"&$C$7) -> 0 | AH31: =SUMIFS('Livro Diario - FC'!$M$11:$M1028,'Livro Diario - FC'!$E$11:$E1028,$C$30,'Livro Diario - FC'!$D$11:$D1028,">=01/07"&$C$7,'Livro Diario - FC'!$D$11:$D1028,"<=31/07"&$C$7) -> 0 | AK31: =SUMIFS('Livro Diario - FC'!$K$11:$K1028,'Livro Diario - FC'!$E$11:$E1028,$C$30,'Livro Diario - FC'!$D$11:$D1028,">=01/08"&$C$7,'Livro Diario - FC'!$D$11:$D1028,"<=31/08"&$C$7) -> 0 | AL31: =SUMIFS('Livro Diario - FC'!$M$11:$M1028,'Livro Diario - FC'!$E$11:$E1028,$C$30,'Livro Diario - FC'!$D$11:$D1028,">=01/08"&$C$7,'Livro Diario - FC'!$D$11:$D1028,"<=31/08"&$C$7) -> 0 | AO31: =SUMIFS('Livro Diario - FC'!$K$11:$K1028,'Livro Diario - FC'!$E$11:$E1028,$C$30,'Livro Diario - FC'!$D$11:$D1028,">=01/09"&$C$7,'Livro Diario - FC'!$D$11:$D1028,"<=30/09"&$C$7) -> 0 | AP31: =SUMIFS('Livro Diario - FC'!$M$11:$M1028,'Livro Diario - FC'!$E$11:$E1028,$C$30,'Livro Diario - FC'!$D$11:$D1028,">=01/09"&$C$7,'Livro Diario - FC'!$D$11:$D1028,"<=30/09"&$C$7) -> 0 | AS31: =SUMIFS('Livro Diario - FC'!$K$11:$K1028,'Livro Diario - FC'!$E$11:$E1028,$C$30,'Livro Diario - FC'!$D$11:$D1028,">=01/10"&$C$7,'Livro Diario - FC'!$D$11:$D1028,"<=31/10"&$C$7) -> 0 | AT31: =SUMIFS('Livro Diario - FC'!$M$11:$M1028,'Livro Diario - FC'!$E$11:$E1028,$C$30,'Livro Diario - FC'!$D$11:$D1028,">=01/10"&$C$7,'Livro Diario - FC'!$D$11:$D1028,"<=31/10"&$C$7) -> 0 | AW31: =SUMIFS('Livro Diario - FC'!$K$11:$K1028,'Livro Diario - FC'!$E$11:$E1028,$C$30,'Livro Diario - FC'!$D$11:$D1028,">=01/11"&$C$7,'Livro Diario - FC'!$D$11:$D1028,"<=30/11"&$C$7) -> 0 | AX31: =SUMIFS('Livro Diario - FC'!$M$11:$M1028,'Livro Diario - FC'!$E$11:$E1028,$C$30,'Livro Diario - FC'!$D$11:$D1028,">=01/11"&$C$7,'Livro Diario - FC'!$D$11:$D1028,"<=30/11"&$C$7) -> 0 | BA31: =SUMIFS('Livro Diario - FC'!$K$11:$K1028,'Livro Diario - FC'!$E$11:$E1028,$C$30,'Livro Diario - FC'!$D$11:$D1028,">=01/12"&$C$7,'Livro Diario - FC'!$D$11:$D1028,"<=31/12"&$C$7) -> 0 | BB31: =SUMIFS('Livro Diario - FC'!$M$11:$M1028,'Livro Diario - FC'!$E$11:$E1028,$C$30,'Livro Diario - FC'!$D$11:$D1028,">=01/12"&$C$7,'Livro Diario - FC'!$D$11:$D1028,"<=31/12"&$C$7) -> 0 | BE31: =SUM(D31,I31,N31,S31,X31,AC31,AG31,AK31,AO31,AS31,AW31,BA31) -> 0 | BF31: =SUM(E31,J31,O31,T31,Y31,AD31,AH31,AL31,AP31,AT31,AX31,BB31) -> 0 | BI31: =SUMIFS('Livro Diario - FC'!$M$11:$M1028,'Livro Diario - FC'!$E$11:$E1028,C31,'Livro Diario - FC'!$D$11:$D1028,">="&$BK$8,'Livro Diario - FC'!$D$11:$D1028,"<="&$BK$9) -> 0
C32: ='Livro Diario - FC'!AE35 -> 4.1.7 Parcelamento Imposto | D32: =SUMIFS('Livro Diario - FC'!$K$11:$K1028,'Livro Diario - FC'!$E$11:$E1028,$C$30,'Livro Diario - FC'!$D$11:$D1028,">=01/01"&$C$7,'Livro Diario - FC'!$D$11:$D1028,"<=31/01"&$C$7) -> 0 | E32: =SUMIFS('Livro Diario - FC'!$M$11:$M1028,'Livro Diario - FC'!$E$11:$E1028,$C$30,'Livro Diario - FC'!$D$11:$D1028,">=01/01"&$C$7,'Livro Diario - FC'!$D$11:$D1028,"<=31/01"&$C$7) -> 0 | I32: =SUMIFS('Livro Diario - FC'!$K$11:$K1028,'Livro Diario - FC'!$E$11:$E1028,$C$30,'Livro Diario - FC'!$D$11:$D1028,">=01/02"&$C$7,'Livro Diario - FC'!$D$11:$D1028,"<=29/02"&$C$7) -> 0 | J32: =SUMIFS('Livro Diario - FC'!$M$11:$M1028,'Livro Diario - FC'!$E$11:$E1028,$C$30,'Livro Diario - FC'!$D$11:$D1028,">=01/02"&$C$7,'Livro Diario - FC'!$D$11:$D1028,"<=29/02"&$C$7) -> 0 | N32: =SUMIFS('Livro Diario - FC'!$K$11:$K1028,'Livro Diario - FC'!$E$11:$E1028,$C$30,'Livro Diario - FC'!$D$11:$D1028,">=01/03"&$C$7,'Livro Diario - FC'!$D$11:$D1028,"<=31/03"&$C$7) -> 0 | O32: =SUMIFS('Livro Diario - FC'!$M$11:$M1028,'Livro Diario - FC'!$E$11:$E1028,$C$30,'Livro Diario - FC'!$D$11:$D1028,">=01/03"&$C$7,'Livro Diario - FC'!$D$11:$D1028,"<=31/03"&$C$7) -> 0 | S32: =SUMIFS('Livro Diario - FC'!$K$11:$K1028,'Livro Diario - FC'!$E$11:$E1028,$C$30,'Livro Diario - FC'!$D$11:$D1028,">=01/04"&$C$7,'Livro Diario - FC'!$D$11:$D1028,"<=30/04"&$C$7) -> 0 | T32: =SUMIFS('Livro Diario - FC'!$M$11:$M1028,'Livro Diario - FC'!$E$11:$E1028,$C$30,'Livro Diario - FC'!$D$11:$D1028,">=01/04"&$C$7,'Livro Diario - FC'!$D$11:$D1028,"<=30/04"&$C$7) -> 0 | X32: =SUMIFS('Livro Diario - FC'!$K$11:$K1028,'Livro Diario - FC'!$E$11:$E1028,$C$30,'Livro Diario - FC'!$D$11:$D1028,">=01/05"&$C$7,'Livro Diario - FC'!$D$11:$D1028,"<=31/05"&$C$7) -> 0 | Y32: =SUMIFS('Livro Diario - FC'!$M$11:$M1028,'Livro Diario - FC'!$E$11:$E1028,$C$30,'Livro Diario - FC'!$D$11:$D1028,">=01/05"&$C$7,'Livro Diario - FC'!$D$11:$D1028,"<=31/05"&$C$7) -> 0 | AC32: =SUMIFS('Livro Diario - FC'!$K$11:$K1028,'Livro Diario - FC'!$E$11:$E1028,$C$30,'Livro Diario - FC'!$D$11:$D1028,">=01/06"&$C$7,'Livro Diario - FC'!$D$11:$D1028,"<=30/06"&$C$7) -> 0 | AD32: =SUMIFS('Livro Diario - FC'!$M$11:$M1028,'Livro Diario - FC'!$E$11:$E1028,$C$30,'Livro Diario - FC'!$D$11:$D1028,">=01/06"&$C$7,'Livro Diario - FC'!$D$11:$D1028,"<=30/06"&$C$7) -> 0 | AG32: =SUMIFS('Livro Diario - FC'!$K$11:$K1028,'Livro Diario - FC'!$E$11:$E1028,$C$30,'Livro Diario - FC'!$D$11:$D1028,">=01/07"&$C$7,'Livro Diario - FC'!$D$11:$D1028,"<=31/07"&$C$7) -> 0 | AH32: =SUMIFS('Livro Diario - FC'!$M$11:$M1028,'Livro Diario - FC'!$E$11:$E1028,$C$30,'Livro Diario - FC'!$D$11:$D1028,">=01/07"&$C$7,'Livro Diario - FC'!$D$11:$D1028,"<=31/07"&$C$7) -> 0 | AK32: =SUMIFS('Livro Diario - FC'!$K$11:$K1028,'Livro Diario - FC'!$E$11:$E1028,$C$30,'Livro Diario - FC'!$D$11:$D1028,">=01/08"&$C$7,'Livro Diario - FC'!$D$11:$D1028,"<=31/08"&$C$7) -> 0 | AL32: =SUMIFS('Livro Diario - FC'!$M$11:$M1028,'Livro Diario - FC'!$E$11:$E1028,$C$30,'Livro Diario - FC'!$D$11:$D1028,">=01/08"&$C$7,'Livro Diario - FC'!$D$11:$D1028,"<=31/08"&$C$7) -> 0 | AO32: =SUMIFS('Livro Diario - FC'!$K$11:$K1028,'Livro Diario - FC'!$E$11:$E1028,$C$30,'Livro Diario - FC'!$D$11:$D1028,">=01/09"&$C$7,'Livro Diario - FC'!$D$11:$D1028,"<=30/09"&$C$7) -> 0 | AP32: =SUMIFS('Livro Diario - FC'!$M$11:$M1028,'Livro Diario - FC'!$E$11:$E1028,$C$30,'Livro Diario - FC'!$D$11:$D1028,">=01/09"&$C$7,'Livro Diario - FC'!$D$11:$D1028,"<=30/09"&$C$7) -> 0 | AS32: =SUMIFS('Livro Diario - FC'!$K$11:$K1028,'Livro Diario - FC'!$E$11:$E1028,$C$30,'Livro Diario - FC'!$D$11:$D1028,">=01/10"&$C$7,'Livro Diario - FC'!$D$11:$D1028,"<=31/10"&$C$7) -> 0 | AT32: =SUMIFS('Livro Diario - FC'!$M$11:$M1028,'Livro Diario - FC'!$E$11:$E1028,$C$30,'Livro Diario - FC'!$D$11:$D1028,">=01/10"&$C$7,'Livro Diario - FC'!$D$11:$D1028,"<=31/10"&$C$7) -> 0 | AW32: =SUMIFS('Livro Diario - FC'!$K$11:$K1028,'Livro Diario - FC'!$E$11:$E1028,$C$30,'Livro Diario - FC'!$D$11:$D1028,">=01/11"&$C$7,'Livro Diario - FC'!$D$11:$D1028,"<=30/11"&$C$7) -> 0 | AX32: =SUMIFS('Livro Diario - FC'!$M$11:$M1028,'Livro Diario - FC'!$E$11:$E1028,$C$30,'Livro Diario - FC'!$D$11:$D1028,">=01/11"&$C$7,'Livro Diario - FC'!$D$11:$D1028,"<=30/11"&$C$7) -> 0 | BA32: =SUMIFS('Livro Diario - FC'!$K$11:$K1028,'Livro Diario - FC'!$E$11:$E1028,$C$30,'Livro Diario - FC'!$D$11:$D1028,">=01/12"&$C$7,'Livro Diario - FC'!$D$11:$D1028,"<=31/12"&$C$7) -> 0 | BB32: =SUMIFS('Livro Diario - FC'!$M$11:$M1028,'Livro Diario - FC'!$E$11:$E1028,$C$30,'Livro Diario - FC'!$D$11:$D1028,">=01/12"&$C$7,'Livro Diario - FC'!$D$11:$D1028,"<=31/12"&$C$7) -> 0 | BE32: =SUM(D32,I32,N32,S32,X32,AC32,AG32,AK32,AO32,AS32,AW32,BA32) -> 0 | BF32: =SUM(E32,J32,O32,T32,Y32,AD32,AH32,AL32,AP32,AT32,AX32,BB32) -> 0 | BI32: =SUMIFS('Livro Diario - FC'!$M$11:$M1028,'Livro Diario - FC'!$E$11:$E1028,C32,'Livro Diario - FC'!$D$11:$D1028,">="&$BK$8,'Livro Diario - FC'!$D$11:$D1028,"<="&$BK$9) -> 0
C33: ='Livro Diario - FC'!AE36 -> 4.1.8 . | D33: =SUMIFS('Livro Diario - FC'!$K$11:$K1028,'Livro Diario - FC'!$E$11:$E1028,$C$30,'Livro Diario - FC'!$D$11:$D1028,">=01/01"&$C$7,'Livro Diario - FC'!$D$11:$D1028,"<=31/01"&$C$7) -> 0 | E33: =SUMIFS('Livro Diario - FC'!$M$11:$M1028,'Livro Diario - FC'!$E$11:$E1028,$C$30,'Livro Diario - FC'!$D$11:$D1028,">=01/01"&$C$7,'Livro Diario - FC'!$D$11:$D1028,"<=31/01"&$C$7) -> 0 | I33: =SUMIFS('Livro Diario - FC'!$K$11:$K1028,'Livro Diario - FC'!$E$11:$E1028,$C$30,'Livro Diario - FC'!$D$11:$D1028,">=01/02"&$C$7,'Livro Diario - FC'!$D$11:$D1028,"<=29/02"&$C$7) -> 0 | J33: =SUMIFS('Livro Diario - FC'!$M$11:$M1028,'Livro Diario - FC'!$E$11:$E1028,$C$30,'Livro Diario - FC'!$D$11:$D1028,">=01/02"&$C$7,'Livro Diario - FC'!$D$11:$D1028,"<=29/02"&$C$7) -> 0 | N33: =SUMIFS('Livro Diario - FC'!$K$11:$K1028,'Livro Diario - FC'!$E$11:$E1028,$C$30,'Livro Diario - FC'!$D$11:$D1028,">=01/03"&$C$7,'Livro Diario - FC'!$D$11:$D1028,"<=31/03"&$C$7) -> 0 | O33: =SUMIFS('Livro Diario - FC'!$M$11:$M1028,'Livro Diario - FC'!$E$11:$E1028,$C$30,'Livro Diario - FC'!$D$11:$D1028,">=01/03"&$C$7,'Livro Diario - FC'!$D$11:$D1028,"<=31/03"&$C$7) -> 0 | S33: =SUMIFS('Livro Diario - FC'!$K$11:$K1028,'Livro Diario - FC'!$E$11:$E1028,$C$30,'Livro Diario - FC'!$D$11:$D1028,">=01/04"&$C$7,'Livro Diario - FC'!$D$11:$D1028,"<=30/04"&$C$7) -> 0 | T33: =SUMIFS('Livro Diario - FC'!$M$11:$M1028,'Livro Diario - FC'!$E$11:$E1028,$C$30,'Livro Diario - FC'!$D$11:$D1028,">=01/04"&$C$7,'Livro Diario - FC'!$D$11:$D1028,"<=30/04"&$C$7) -> 0 | X33: =SUMIFS('Livro Diario - FC'!$K$11:$K1028,'Livro Diario - FC'!$E$11:$E1028,$C$30,'Livro Diario - FC'!$D$11:$D1028,">=01/05"&$C$7,'Livro Diario - FC'!$D$11:$D1028,"<=31/05"&$C$7) -> 0 | Y33: =SUMIFS('Livro Diario - FC'!$M$11:$M1028,'Livro Diario - FC'!$E$11:$E1028,$C$30,'Livro Diario - FC'!$D$11:$D1028,">=01/05"&$C$7,'Livro Diario - FC'!$D$11:$D1028,"<=31/05"&$C$7) -> 0 | AC33: =SUMIFS('Livro Diario - FC'!$K$11:$K1028,'Livro Diario - FC'!$E$11:$E1028,$C$30,'Livro Diario - FC'!$D$11:$D1028,">=01/06"&$C$7,'Livro Diario - FC'!$D$11:$D1028,"<=30/06"&$C$7) -> 0 | AD33: =SUMIFS('Livro Diario - FC'!$M$11:$M1028,'Livro Diario - FC'!$E$11:$E1028,$C$30,'Livro Diario - FC'!$D$11:$D1028,">=01/06"&$C$7,'Livro Diario - FC'!$D$11:$D1028,"<=30/06"&$C$7) -> 0 | AG33: =SUMIFS('Livro Diario - FC'!$K$11:$K1028,'Livro Diario - FC'!$E$11:$E1028,$C$30,'Livro Diario - FC'!$D$11:$D1028,">=01/07"&$C$7,'Livro Diario - FC'!$D$11:$D1028,"<=31/07"&$C$7) -> 0 | AH33: =SUMIFS('Livro Diario - FC'!$M$11:$M1028,'Livro Diario - FC'!$E$11:$E1028,$C$30,'Livro Diario - FC'!$D$11:$D1028,">=01/07"&$C$7,'Livro Diario - FC'!$D$11:$D1028,"<=31/07"&$C$7) -> 0 | AK33: =SUMIFS('Livro Diario - FC'!$K$11:$K1028,'Livro Diario - FC'!$E$11:$E1028,$C$30,'Livro Diario - FC'!$D$11:$D1028,">=01/08"&$C$7,'Livro Diario - FC'!$D$11:$D1028,"<=31/08"&$C$7) -> 0 | AL33: =SUMIFS('Livro Diario - FC'!$M$11:$M1028,'Livro Diario - FC'!$E$11:$E1028,$C$30,'Livro Diario - FC'!$D$11:$D1028,">=01/08"&$C$7,'Livro Diario - FC'!$D$11:$D1028,"<=31/08"&$C$7) -> 0 | AO33: =SUMIFS('Livro Diario - FC'!$K$11:$K1028,'Livro Diario - FC'!$E$11:$E1028,$C$30,'Livro Diario - FC'!$D$11:$D1028,">=01/09"&$C$7,'Livro Diario - FC'!$D$11:$D1028,"<=30/09"&$C$7) -> 0 | AP33: =SUMIFS('Livro Diario - FC'!$M$11:$M1028,'Livro Diario - FC'!$E$11:$E1028,$C$30,'Livro Diario - FC'!$D$11:$D1028,">=01/09"&$C$7,'Livro Diario - FC'!$D$11:$D1028,"<=30/09"&$C$7) -> 0 | AS33: =SUMIFS('Livro Diario - FC'!$K$11:$K1028,'Livro Diario - FC'!$E$11:$E1028,$C$30,'Livro Diario - FC'!$D$11:$D1028,">=01/10"&$C$7,'Livro Diario - FC'!$D$11:$D1028,"<=31/10"&$C$7) -> 0 | AT33: =SUMIFS('Livro Diario - FC'!$M$11:$M1028,'Livro Diario - FC'!$E$11:$E1028,$C$30,'Livro Diario - FC'!$D$11:$D1028,">=01/10"&$C$7,'Livro Diario - FC'!$D$11:$D1028,"<=31/10"&$C$7) -> 0 | AW33: =SUMIFS('Livro Diario - FC'!$K$11:$K1028,'Livro Diario - FC'!$E$11:$E1028,$C$30,'Livro Diario - FC'!$D$11:$D1028,">=01/11"&$C$7,'Livro Diario - FC'!$D$11:$D1028,"<=30/11"&$C$7) -> 0 | AX33: =SUMIFS('Livro Diario - FC'!$M$11:$M1028,'Livro Diario - FC'!$E$11:$E1028,$C$30,'Livro Diario - FC'!$D$11:$D1028,">=01/11"&$C$7,'Livro Diario - FC'!$D$11:$D1028,"<=30/11"&$C$7) -> 0 | BA33: =SUMIFS('Livro Diario - FC'!$K$11:$K1028,'Livro Diario - FC'!$E$11:$E1028,$C$30,'Livro Diario - FC'!$D$11:$D1028,">=01/12"&$C$7,'Livro Diario - FC'!$D$11:$D1028,"<=31/12"&$C$7) -> 0 | BB33: =SUMIFS('Livro Diario - FC'!$M$11:$M1028,'Livro Diario - FC'!$E$11:$E1028,$C$30,'Livro Diario - FC'!$D$11:$D1028,">=01/12"&$C$7,'Livro Diario - FC'!$D$11:$D1028,"<=31/12"&$C$7) -> 0 | BE33: =SUM(D33,I33,N33,S33,X33,AC33,AG33,AK33,AO33,AS33,AW33,BA33) -> 0 | BF33: =SUM(E33,J33,O33,T33,Y33,AD33,AH33,AL33,AP33,AT33,AX33,BB33) -> 0 | BI33: =SUMIFS('Livro Diario - FC'!$M$11:$M1028,'Livro Diario - FC'!$E$11:$E1028,C33,'Livro Diario - FC'!$D$11:$D1028,">="&$BK$8,'Livro Diario - FC'!$D$11:$D1028,"<="&$BK$9) -> 0
C34: ='Livro Diario - FC'!AE37 -> 4.1.9 . | D34: =SUMIFS('Livro Diario - FC'!$K$11:$K1028,'Livro Diario - FC'!$E$11:$E1028,$C$30,'Livro Diario - FC'!$D$11:$D1028,">=01/01"&$C$7,'Livro Diario - FC'!$D$11:$D1028,"<=31/01"&$C$7) -> 0 | E34: =SUMIFS('Livro Diario - FC'!$M$11:$M1028,'Livro Diario - FC'!$E$11:$E1028,$C$30,'Livro Diario - FC'!$D$11:$D1028,">=01/01"&$C$7,'Livro Diario - FC'!$D$11:$D1028,"<=31/01"&$C$7) -> 0 | I34: =SUMIFS('Livro Diario - FC'!$K$11:$K1028,'Livro Diario - FC'!$E$11:$E1028,$C$30,'Livro Diario - FC'!$D$11:$D1028,">=01/02"&$C$7,'Livro Diario - FC'!$D$11:$D1028,"<=29/02"&$C$7) -> 0 | J34: =SUMIFS('Livro Diario - FC'!$M$11:$M1028,'Livro Diario - FC'!$E$11:$E1028,$C$30,'Livro Diario - FC'!$D$11:$D1028,">=01/02"&$C$7,'Livro Diario - FC'!$D$11:$D1028,"<=29/02"&$C$7) -> 0 | N34: =SUMIFS('Livro Diario - FC'!$K$11:$K1028,'Livro Diario - FC'!$E$11:$E1028,$C$30,'Livro Diario - FC'!$D$11:$D1028,">=01/03"&$C$7,'Livro Diario - FC'!$D$11:$D1028,"<=31/03"&$C$7) -> 0 | O34: =SUMIFS('Livro Diario - FC'!$M$11:$M1028,'Livro Diario - FC'!$E$11:$E1028,$C$30,'Livro Diario - FC'!$D$11:$D1028,">=01/03"&$C$7,'Livro Diario - FC'!$D$11:$D1028,"<=31/03"&$C$7) -> 0 | S34: =SUMIFS('Livro Diario - FC'!$K$11:$K1028,'Livro Diario - FC'!$E$11:$E1028,$C$30,'Livro Diario - FC'!$D$11:$D1028,">=01/04"&$C$7,'Livro Diario - FC'!$D$11:$D1028,"<=30/04"&$C$7) -> 0 | T34: =SUMIFS('Livro Diario - FC'!$M$11:$M1028,'Livro Diario - FC'!$E$11:$E1028,$C$30,'Livro Diario - FC'!$D$11:$D1028,">=01/04"&$C$7,'Livro Diario - FC'!$D$11:$D1028,"<=30/04"&$C$7) -> 0 | X34: =SUMIFS('Livro Diario - FC'!$K$11:$K1028,'Livro Diario - FC'!$E$11:$E1028,$C$30,'Livro Diario - FC'!$D$11:$D1028,">=01/05"&$C$7,'Livro Diario - FC'!$D$11:$D1028,"<=31/05"&$C$7) -> 0 | Y34: =SUMIFS('Livro Diario - FC'!$M$11:$M1028,'Livro Diario - FC'!$E$11:$E1028,$C$30,'Livro Diario - FC'!$D$11:$D1028,">=01/05"&$C$7,'Livro Diario - FC'!$D$11:$D1028,"<=31/05"&$C$7) -> 0 | AC34: =SUMIFS('Livro Diario - FC'!$K$11:$K1028,'Livro Diario - FC'!$E$11:$E1028,$C$30,'Livro Diario - FC'!$D$11:$D1028,">=01/06"&$C$7,'Livro Diario - FC'!$D$11:$D1028,"<=30/06"&$C$7) -> 0 | AD34: =SUMIFS('Livro Diario - FC'!$M$11:$M1028,'Livro Diario - FC'!$E$11:$E1028,$C$30,'Livro Diario - FC'!$D$11:$D1028,">=01/06"&$C$7,'Livro Diario - FC'!$D$11:$D1028,"<=30/06"&$C$7) -> 0 | AG34: =SUMIFS('Livro Diario - FC'!$K$11:$K1028,'Livro Diario - FC'!$E$11:$E1028,$C$30,'Livro Diario - FC'!$D$11:$D1028,">=01/07"&$C$7,'Livro Diario - FC'!$D$11:$D1028,"<=31/07"&$C$7) -> 0 | AH34: =SUMIFS('Livro Diario - FC'!$M$11:$M1028,'Livro Diario - FC'!$E$11:$E1028,$C$30,'Livro Diario - FC'!$D$11:$D1028,">=01/07"&$C$7,'Livro Diario - FC'!$D$11:$D1028,"<=31/07"&$C$7) -> 0 | AK34: =SUMIFS('Livro Diario - FC'!$K$11:$K1028,'Livro Diario - FC'!$E$11:$E1028,$C$30,'Livro Diario - FC'!$D$11:$D1028,">=01/08"&$C$7,'Livro Diario - FC'!$D$11:$D1028,"<=31/08"&$C$7) -> 0 | AL34: =SUMIFS('Livro Diario - FC'!$M$11:$M1028,'Livro Diario - FC'!$E$11:$E1028,$C$30,'Livro Diario - FC'!$D$11:$D1028,">=01/08"&$C$7,'Livro Diario - FC'!$D$11:$D1028,"<=31/08"&$C$7) -> 0 | AO34: =SUMIFS('Livro Diario - FC'!$K$11:$K1028,'Livro Diario - FC'!$E$11:$E1028,$C$30,'Livro Diario - FC'!$D$11:$D1028,">=01/09"&$C$7,'Livro Diario - FC'!$D$11:$D1028,"<=30/09"&$C$7) -> 0 | AP34: =SUMIFS('Livro Diario - FC'!$M$11:$M1028,'Livro Diario - FC'!$E$11:$E1028,$C$30,'Livro Diario - FC'!$D$11:$D1028,">=01/09"&$C$7,'Livro Diario - FC'!$D$11:$D1028,"<=30/09"&$C$7) -> 0 | AS34: =SUMIFS('Livro Diario - FC'!$K$11:$K1028,'Livro Diario - FC'!$E$11:$E1028,$C$30,'Livro Diario - FC'!$D$11:$D1028,">=01/10"&$C$7,'Livro Diario - FC'!$D$11:$D1028,"<=31/10"&$C$7) -> 0 | AT34: =SUMIFS('Livro Diario - FC'!$M$11:$M1028,'Livro Diario - FC'!$E$11:$E1028,$C$30,'Livro Diario - FC'!$D$11:$D1028,">=01/10"&$C$7,'Livro Diario - FC'!$D$11:$D1028,"<=31/10"&$C$7) -> 0 | AW34: =SUMIFS('Livro Diario - FC'!$K$11:$K1028,'Livro Diario - FC'!$E$11:$E1028,$C$30,'Livro Diario - FC'!$D$11:$D1028,">=01/11"&$C$7,'Livro Diario - FC'!$D$11:$D1028,"<=30/11"&$C$7) -> 0 | AX34: =SUMIFS('Livro Diario - FC'!$M$11:$M1028,'Livro Diario - FC'!$E$11:$E1028,$C$30,'Livro Diario - FC'!$D$11:$D1028,">=01/11"&$C$7,'Livro Diario - FC'!$D$11:$D1028,"<=30/11"&$C$7) -> 0 | BA34: =SUMIFS('Livro Diario - FC'!$K$11:$K1028,'Livro Diario - FC'!$E$11:$E1028,$C$30,'Livro Diario - FC'!$D$11:$D1028,">=01/12"&$C$7,'Livro Diario - FC'!$D$11:$D1028,"<=31/12"&$C$7) -> 0 | BB34: =SUMIFS('Livro Diario - FC'!$M$11:$M1028,'Livro Diario - FC'!$E$11:$E1028,$C$30,'Livro Diario - FC'!$D$11:$D1028,">=01/12"&$C$7,'Livro Diario - FC'!$D$11:$D1028,"<=31/12"&$C$7) -> 0 | BE34: =SUM(D34,I34,N34,S34,X34,AC34,AG34,AK34,AO34,AS34,AW34,BA34) -> 0 | BF34: =SUM(E34,J34,O34,T34,Y34,AD34,AH34,AL34,AP34,AT34,AX34,BB34) -> 0 | BI34: =SUMIFS('Livro Diario - FC'!$M$11:$M1028,'Livro Diario - FC'!$E$11:$E1028,C34,'Livro Diario - FC'!$D$11:$D1028,">="&$BK$8,'Livro Diario - FC'!$D$11:$D1028,"<="&$BK$9) -> 0
C35: CUSTOS COM PRODUTOS | D35: =SUMIFS('Livro Diario - FC'!$K$11:$K1028,'Livro Diario - FC'!$E$11:$E1028,$C$35,'Livro Diario - FC'!$D$11:$D1028,">=01/01"&$C$7,'Livro Diario - FC'!$D$11:$D1028,"<=31/01"&$C$7)+SUM(D36+D133+D149+D189+D206) -> 10707.89 | E35: =SUMIFS('Livro Diario - FC'!$K$11:$K1028,'Livro Diario - FC'!$E$11:$E1028,$C$35,'Livro Diario - FC'!$D$11:$D1028,">=01/01"&$C$7,'Livro Diario - FC'!$D$11:$D1028,"<=31/01"&$C$7)+SUM(E36+E133+E149+E189+E206) -> 10707.89 | F35: =IF(E$11=0,"",E35/E$11) -> 1.3810039 | G35: =IF(A35=0,"",E35/A35-1) | I35: =SUMIFS('Livro Diario - FC'!$K$11:$K1028,'Livro Diario - FC'!$E$11:$E1028,$C$35,'Livro Diario - FC'!$D$11:$D1028,">=01/02"&$C$7,'Livro Diario - FC'!$D$11:$D1028,"<=29/02"&$C$7)+SUM(I36+I133+I149+I189+I206) -> 0 | J35: =SUMIFS('Livro Diario - FC'!$K$11:$K1028,'Livro Diario - FC'!$E$11:$E1028,$C$35,'Livro Diario - FC'!$D$11:$D1028,">=01/02"&$C$7,'Livro Diario - FC'!$D$11:$D1028,"<=29/02"&$C$7)+SUM(J36+J133+J149+J189+J206) -> 0 | K35: =IF(J$11=0,"",J35/J$11) | L35: =IF(E35=0,"",J35/E35-1) -> -1 | N35: =SUMIFS('Livro Diario - FC'!$K$11:$K1028,'Livro Diario - FC'!$E$11:$E1028,$C$35,'Livro Diario - FC'!$D$11:$D1028,">=01/03"&$C$7,'Livro Diario - FC'!$D$11:$D1028,"<=31/03"&$C$7)+SUM(N36+N133+N149+N189+N206) -> 0 | O35: =SUMIFS('Livro Diario - FC'!$K$11:$K1028,'Livro Diario - FC'!$E$11:$E1028,$C$35,'Livro Diario - FC'!$D$11:$D1028,">=01/03"&$C$7,'Livro Diario - FC'!$D$11:$D1028,"<=31/03"&$C$7)+SUM(O36+O133+O149+O189+O206) -> 0 | P35: =IF(O$11=0,"",O35/O$11) | Q35: =IF(J35=0,"",O35/J35-1) | S35: =SUMIFS('Livro Diario - FC'!$K$11:$K1028,'Livro Diario - FC'!$E$11:$E1028,$C$35,'Livro Diario - FC'!$D$11:$D1028,">=01/04"&$C$7,'Livro Diario - FC'!$D$11:$D1028,"<=30/04"&$C$7)+SUM(S36+S133+S149+S189+S206) -> 0 | T35: =SUMIFS('Livro Diario - FC'!$K$11:$K1028,'Livro Diario - FC'!$E$11:$E1028,$C$35,'Livro Diario - FC'!$D$11:$D1028,">=01/04"&$C$7,'Livro Diario - FC'!$D$11:$D1028,"<=30/04"&$C$7)+SUM(T36+T133+T149+T189+T206) -> 0 | U35: =IF(T$11=0,"",T35/T$11) | V35: =IF(O35=0,"",T35/O35-1) | X35: =SUMIFS('Livro Diario - FC'!$K$11:$K1028,'Livro Diario - FC'!$E$11:$E1028,$C$35,'Livro Diario - FC'!$D$11:$D1028,">=01/05"&$C$7,'Livro Diario - FC'!$D$11:$D1028,"<=31/05"&$C$7)+SUM(X36+X133+X149+X189+X206) -> 0 | Y35: =SUMIFS('Livro Diario - FC'!$K$11:$K1028,'Livro Diario - FC'!$E$11:$E1028,$C$35,'Livro Diario - FC'!$D$11:$D1028,">=01/05"&$C$7,'Livro Diario - FC'!$D$11:$D1028,"<=31/05"&$C$7)+SUM(Y36+Y133+Y149+Y189+Y206) -> 0 | Z35: =IF(Y$11=0,"",Y35/Y$11) | AA35: =IF(T35=0,"",Y35/T35-1) | AC35: =SUMIFS('Livro Diario - FC'!$K$11:$K1028,'Livro Diario - FC'!$E$11:$E1028,$C$35,'Livro Diario - FC'!$D$11:$D1028,">=01/06"&$C$7,'Livro Diario - FC'!$D$11:$D1028,"<=30/06"&$C$7)+SUM(AC36+AC133+AC149+AC189+AC206) -> 0 | AD35: =SUMIFS('Livro Diario - FC'!$K$11:$K1028,'Livro Diario - FC'!$E$11:$E1028,$C$35,'Livro Diario - FC'!$D$11:$D1028,">=01/06"&$C$7,'Livro Diario - FC'!$D$11:$D1028,"<=30/06"&$C$7)+SUM(AD36+AD133+AD149+AD189+AD206) -> 0 | AE35: =IF(AD$11=0,"",AD35/AD$11) | AF35: =IF(Y35=0,"",AD35/Y35-1) | AG35: =SUMIFS('Livro Diario - FC'!$K$11:$K1028,'Livro Diario - FC'!$E$11:$E1028,$C$35,'Livro Diario - FC'!$D$11:$D1028,">=01/07"&$C$7,'Livro Diario - FC'!$D$11:$D1028,"<=31/07"&$C$7)+SUM(AG36+AG133+AG149+AG189+AG206) -> 0 | AH35: =SUMIFS('Livro Diario - FC'!$K$11:$K1028,'Livro Diario - FC'!$E$11:$E1028,$C$35,'Livro Diario - FC'!$D$11:$D1028,">=01/07"&$C$7,'Livro Diario - FC'!$D$11:$D1028,"<=31/07"&$C$7)+SUM(AH36+AH133+AH149+AH189+AH206) -> 0 | AI35: =IF(AH$11=0,"",AH35/AH$11) | AJ35: =IF(AD35=0,"",AH35/AD35-1) | AK35: =SUMIFS('Livro Diario - FC'!$K$11:$K1028,'Livro Diario - FC'!$E$11:$E1028,$C$35,'Livro Diario - FC'!$D$11:$D1028,">=01/08"&$C$7,'Livro Diario - FC'!$D$11:$D1028,"<=31/08"&$C$7)+SUM(AK36+AK133+AK149+AK189+AK206) -> 0 | AL35: =SUMIFS('Livro Diario - FC'!$K$11:$K1028,'Livro Diario - FC'!$E$11:$E1028,$C$35,'Livro Diario - FC'!$D$11:$D1028,">=01/08"&$C$7,'Livro Diario - FC'!$D$11:$D1028,"<=31/08"&$C$7)+SUM(AL36+AL133+AL149+AL189+AL206) -> 0 | AM35: =IF(AL$11=0,"",AL35/AL$11) | AN35: =IF(AH35=0,"",AL35/AH35-1) | AO35: =SUMIFS('Livro Diario - FC'!$K$11:$K1028,'Livro Diario - FC'!$E$11:$E1028,$C$35,'Livro Diario - FC'!$D$11:$D1028,">=01/09"&$C$7,'Livro Diario - FC'!$D$11:$D1028,"<=30/09"&$C$7)+SUM(AO36+AO133+AO149+AO189+AO206) -> 0 | AP35: =SUMIFS('Livro Diario - FC'!$K$11:$K1028,'Livro Diario - FC'!$E$11:$E1028,$C$35,'Livro Diario - FC'!$D$11:$D1028,">=01/09"&$C$7,'Livro Diario - FC'!$D$11:$D1028,"<=30/09"&$C$7)+SUM(AP36+AP133+AP149+AP189+AP206) -> 0 | AQ35: =IF(AP$11=0,"",AP35/AP$11) | AR35: =IF(AL35=0,"",AP35/AL35-1) | AS35: =SUMIFS('Livro Diario - FC'!$K$11:$K1028,'Livro Diario - FC'!$E$11:$E1028,$C$35,'Livro Diario - FC'!$D$11:$D1028,">=01/10"&$C$7,'Livro Diario - FC'!$D$11:$D1028,"<=31/10"&$C$7)+SUM(AS36+AS133+AS149+AS189+AS206) -> 0 | AT35: =SUMIFS('Livro Diario - FC'!$K$11:$K1028,'Livro Diario - FC'!$E$11:$E1028,$C$35,'Livro Diario - FC'!$D$11:$D1028,">=01/10"&$C$7,'Livro Diario - FC'!$D$11:$D1028,"<=31/10"&$C$7)+SUM(AT36+AT133+AT149+AT189+AT206) -> 0 | AU35: =IF(AT$11=0,"",AT35/AT$11) | AV35: =IF(AP35=0,"",AT35/AP35-1) | AW35: =SUMIFS('Livro Diario - FC'!$K$11:$K1028,'Livro Diario - FC'!$E$11:$E1028,$C$35,'Livro Diario - FC'!$D$11:$D1028,">=01/11"&$C$7,'Livro Diario - FC'!$D$11:$D1028,"<=30/11"&$C$7)+SUM(AW36+AW133+AW149+AW189+AW206) -> 0 | AX35: =SUMIFS('Livro Diario - FC'!$K$11:$K1028,'Livro Diario - FC'!$E$11:$E1028,$C$35,'Livro Diario - FC'!$D$11:$D1028,">=01/11"&$C$7,'Livro Diario - FC'!$D$11:$D1028,"<=30/11"&$C$7)+SUM(AX36+AX133+AX149+AX189+AX206) -> 0 | AY35: =IF(AX$11=0,"",AX35/AX$11) | AZ35: =IF(AT35=0,"",AX35/AT35-1) | BA35: =SUMIFS('Livro Diario - FC'!$K$11:$K1028,'Livro Diario - FC'!$E$11:$E1028,$C$35,'Livro Diario - FC'!$D$11:$D1028,">=01/12"&$C$7,'Livro Diario - FC'!$D$11:$D1028,"<=31/12"&$C$7)+SUM(BA36+BA133+BA149+BA189+BA206) -> 0 | BB35: =SUMIFS('Livro Diario - FC'!$K$11:$K1028,'Livro Diario - FC'!$E$11:$E1028,$C$35,'Livro Diario - FC'!$D$11:$D1028,">=01/12"&$C$7,'Livro Diario - FC'!$D$11:$D1028,"<=31/12"&$C$7)+SUM(BB36+BB133+BB149+BB189+BB206) -> 0 | BC35: =IF(BB$11=0,"",BB35/BB$11) | BD35: =IF(AX35=0,"",BB35/AX35-1) | BE35: =SUM(D35,I35,N35,S35,X35,AC35,AG35,AK35,AO35,AS35,AW35,BA35) -> 10707.89 | BF35: =SUM(E35,J35,O35,T35,Y35,AD35,AH35,AL35,AP35,AT35,AX35,BB35) -> 10707.89 | BG35: =IF(BF$11=0,"",BF35/BF$11) -> 1.3810039 | BI35: =SUMIFS('Livro Diario - FC'!$M$11:$M1028,'Livro Diario - FC'!$E$11:$E1028,C189,'Livro Diario - FC'!$D$11:$D1028,">="&$BK$8,'Livro Diario - FC'!$D$11:$D1028,"<="&$BK$9)+SUM(BI36+BI133+BI149+BI189+BI206) -> 0 | BJ35: =IF(BI$11=0,"",BI35/BI$11)
C36: INSUMOS | D36: =SUMIFS('Livro Diario - FC'!$J$11:$J1028,'Livro Diario - FC'!$E$11:$E1028,$C$36,'Livro Diario - FC'!$D$11:$D1028,">=01/01"&$C$7,'Livro Diario - FC'!$D$11:$D1028,"<=31/01"&$C$7)+SUM(D37:D120) -> 6219.78 | E36: =SUMIFS('Livro Diario - FC'!$L$11:$L1028,'Livro Diario - FC'!$E$11:$E1028,$C$36,'Livro Diario - FC'!$D$11:$D1028,">=01/01"&$C$7,'Livro Diario - FC'!$D$11:$D1028,"<=31/01"&$C$7)+SUM(E37:E120) -> 6219.78 | F36: =IF(E$11=0,"",E36/E$11) -> 0.80216929 | I36: =SUMIFS('Livro Diario - FC'!$J$11:$J1028,'Livro Diario - FC'!$E$11:$E1028,$C$36,'Livro Diario - FC'!$D$11:$D1028,">=01/02"&$C$7,'Livro Diario - FC'!$D$11:$D1028,"<=29/02"&$C$7)+SUM(I37:I120) -> 0 | J36: =SUMIFS('Livro Diario - FC'!$L$11:$L1028,'Livro Diario - FC'!$E$11:$E1028,$C$36,'Livro Diario - FC'!$D$11:$D1028,">=01/02"&$C$7,'Livro Diario - FC'!$D$11:$D1028,"<=29/02"&$C$7)+SUM(J37:J120) -> 0 | K36: =IF(J$11=0,"",J36/J$11) | N36: =SUMIFS('Livro Diario - FC'!$J$11:$J1028,'Livro Diario - FC'!$E$11:$E1028,$C$36,'Livro Diario - FC'!$D$11:$D1028,">=01/03"&$C$7,'Livro Diario - FC'!$D$11:$D1028,"<=31/03"&$C$7)+SUM(N37:N120) -> 0 | O36: =SUMIFS('Livro Diario - FC'!$L$11:$L1028,'Livro Diario - FC'!$E$11:$E1028,$C$36,'Livro Diario - FC'!$D$11:$D1028,">=01/03"&$C$7,'Livro Diario - FC'!$D$11:$D1028,"<=31/03"&$C$7)+SUM(O37:O120) -> 0 | P36: =IF(O$11=0,"",O36/O$11) | S36: =SUMIFS('Livro Diario - FC'!$J$11:$J1028,'Livro Diario - FC'!$E$11:$E1028,$C$36,'Livro Diario - FC'!$D$11:$D1028,">=01/04"&$C$7,'Livro Diario - FC'!$D$11:$D1028,"<=30/04"&$C$7)+SUM(S37:S120) -> 0 | T36: =SUMIFS('Livro Diario - FC'!$L$11:$L1028,'Livro Diario - FC'!$E$11:$E1028,$C$36,'Livro Diario - FC'!$D$11:$D1028,">=01/04"&$C$7,'Livro Diario - FC'!$D$11:$D1028,"<=30/04"&$C$7)+SUM(T37:T120) -> 0 | U36: =IF(T$11=0,"",T36/T$11) | X36: =SUMIFS('Livro Diario - FC'!$J$11:$J1028,'Livro Diario - FC'!$E$11:$E1028,$C$36,'Livro Diario - FC'!$D$11:$D1028,">=01/05"&$C$7,'Livro Diario - FC'!$D$11:$D1028,"<=31/05"&$C$7)+SUM(X37:X120) -> 0 | Y36: =SUMIFS('Livro Diario - FC'!$L$11:$L1028,'Livro Diario - FC'!$E$11:$E1028,$C$36,'Livro Diario - FC'!$D$11:$D1028,">=01/05"&$C$7,'Livro Diario - FC'!$D$11:$D1028,"<=31/05"&$C$7)+SUM(Y37:Y120) -> 0 | Z36: =IF(Y$11=0,"",Y36/Y$11) | AC36: =SUMIFS('Livro Diario - FC'!$J$11:$J1028,'Livro Diario - FC'!$E$11:$E1028,$C$36,'Livro Diario - FC'!$D$11:$D1028,">=01/06"&$C$7,'Livro Diario - FC'!$D$11:$D1028,"<=30/06"&$C$7)+SUM(AC37:AC120) -> 0 | AD36: =SUMIFS('Livro Diario - FC'!$L$11:$L1028,'Livro Diario - FC'!$E$11:$E1028,$C$36,'Livro Diario - FC'!$D$11:$D1028,">=01/06"&$C$7,'Livro Diario - FC'!$D$11:$D1028,"<=30/06"&$C$7)+SUM(AD37:AD120) -> 0 | AE36: =IF(AD$11=0,"",AD36/AD$11) | AG36: =SUMIFS('Livro Diario - FC'!$J$11:$J1028,'Livro Diario - FC'!$E$11:$E1028,$C$36,'Livro Diario - FC'!$D$11:$D1028,">=01/07"&$C$7,'Livro Diario - FC'!$D$11:$D1028,"<=31/07"&$C$7)+SUM(AG37:AG120) -> 0 | AH36: =SUMIFS('Livro Diario - FC'!$L$11:$L1028,'Livro Diario - FC'!$E$11:$E1028,$C$36,'Livro Diario - FC'!$D$11:$D1028,">=01/07"&$C$7,'Livro Diario - FC'!$D$11:$D1028,"<=31/07"&$C$7)+SUM(AH37:AH120) -> 0 | AI36: =IF(AH$11=0,"",AH36/AH$11) | AK36: =SUMIFS('Livro Diario - FC'!$J$11:$J1028,'Livro Diario - FC'!$E$11:$E1028,$C$36,'Livro Diario - FC'!$D$11:$D1028,">=01/08"&$C$7,'Livro Diario - FC'!$D$11:$D1028,"<=31/08"&$C$7)+SUM(AK37:AK120) -> 0 | AL36: =SUMIFS('Livro Diario - FC'!$L$11:$L1028,'Livro Diario - FC'!$E$11:$E1028,$C$36,'Livro Diario - FC'!$D$11:$D1028,">=01/08"&$C$7,'Livro Diario - FC'!$D$11:$D1028,"<=31/08"&$C$7)+SUM(AL37:AL120) -> 0 | AM36: =IF(AL$11=0,"",AL36/AL$11) | AO36: =SUMIFS('Livro Diario - FC'!$J$11:$J1028,'Livro Diario - FC'!$E$11:$E1028,$C$36,'Livro Diario - FC'!$D$11:$D1028,">=01/09"&$C$7,'Livro Diario - FC'!$D$11:$D1028,"<=30/09"&$C$7)+SUM(AO37:AO120) -> 0 | AP36: =SUMIFS('Livro Diario - FC'!$L$11:$L1028,'Livro Diario - FC'!$E$11:$E1028,$C$36,'Livro Diario - FC'!$D$11:$D1028,">=01/09"&$C$7,'Livro Diario - FC'!$D$11:$D1028,"<=30/09"&$C$7)+SUM(AP37:AP120) -> 0 | AQ36: =IF(AP$11=0,"",AP36/AP$11) | AS36: =SUMIFS('Livro Diario - FC'!$J$11:$J1028,'Livro Diario - FC'!$E$11:$E1028,$C$36,'Livro Diario - FC'!$D$11:$D1028,">=01/10"&$C$7,'Livro Diario - FC'!$D$11:$D1028,"<=31/10"&$C$7)+SUM(AS37:AS120) -> 0 | AT36: =SUMIFS('Livro Diario - FC'!$L$11:$L1028,'Livro Diario - FC'!$E$11:$E1028,$C$36,'Livro Diario - FC'!$D$11:$D1028,">=01/10"&$C$7,'Livro Diario - FC'!$D$11:$D1028,"<=31/10"&$C$7)+SUM(AT37:AT120) -> 0 | AU36: =IF(AT$11=0,"",AT36/AT$11) | AW36: =SUMIFS('Livro Diario - FC'!$J$11:$J1028,'Livro Diario - FC'!$E$11:$E1028,$C$36,'Livro Diario - FC'!$D$11:$D1028,">=01/11"&$C$7,'Livro Diario - FC'!$D$11:$D1028,"<=30/11"&$C$7)+SUM(AW37:AW120) -> 0 | AX36: =SUMIFS('Livro Diario - FC'!$L$11:$L1028,'Livro Diario - FC'!$E$11:$E1028,$C$36,'Livro Diario - FC'!$D$11:$D1028,">=01/11"&$C$7,'Livro Diario - FC'!$D$11:$D1028,"<=30/11"&$C$7)+SUM(AX37:AX120) -> 0 | AY36: =IF(AX$11=0,"",AX36/AX$11) | BA36: =SUMIFS('Livro Diario - FC'!$J$11:$J1028,'Livro Diario - FC'!$E$11:$E1028,$C$36,'Livro Diario - FC'!$D$11:$D1028,">=01/12"&$C$7,'Livro Diario - FC'!$D$11:$D1028,"<=31/12"&$C$7)+SUM(BA37:BA120) -> 0 | BB36: =SUMIFS('Livro Diario - FC'!$L$11:$L1028,'Livro Diario - FC'!$E$11:$E1028,$C$36,'Livro Diario - FC'!$D$11:$D1028,">=01/12"&$C$7,'Livro Diario - FC'!$D$11:$D1028,"<=31/12"&$C$7)+SUM(BB37:BB120) -> 0 | BC36: =IF(BB$11=0,"",BB36/BB$11) | BE36: =SUM(D36,I36,N36,S36,X36,AC36,AG36,AK36,AO36,AS36,AW36,BA36) -> 6219.78 | BF36: =SUM(E36,J36,O36,T36,Y36,AD36,AH36,AL36,AP36,AT36,AX36,BB36) -> 6219.78 | BI36: =SUMIFS('Livro Diario - FC'!$M$11:$M1028,'Livro Diario - FC'!$E$11:$E1028,C36,'Livro Diario - FC'!$D$11:$D1028,">="&$BK$8,'Livro Diario - FC'!$D$11:$D1028,"<="&$BK$9)+SUM(BI37:BI120) -> 0
C37: ='Livro Diario - FC'!AE40 -> Macarrão | D37: =SUMIFS('Livro Diario - FC'!$K$11:$K1028,'Livro Diario - FC'!$E$11:$E1028,$C$37,'Livro Diario - FC'!$D$11:$D1028,">=01/01"&$C$7,'Livro Diario - FC'!$D$11:$D1028,"<=31/01"&$C$7) -> 333.25 | E37: =SUMIFS('Livro Diario - FC'!$M$11:$M1028,'Livro Diario - FC'!$E$11:$E1028,$C$37,'Livro Diario - FC'!$D$11:$D1028,">=01/01"&$C$7,'Livro Diario - FC'!$D$11:$D1028,"<=31/01"&$C$7) -> 333.25 | I37: =SUMIFS('Livro Diario - FC'!$K$11:$K1028,'Livro Diario - FC'!$E$11:$E1028,$C$37,'Livro Diario - FC'!$D$11:$D1028,">=01/02"&$C$7,'Livro Diario - FC'!$D$11:$D1028,"<=29/02"&$C$7) -> 0 | J37: =SUMIFS('Livro Diario - FC'!$M$11:$M1028,'Livro Diario - FC'!$E$11:$E1028,$C$37,'Livro Diario - FC'!$D$11:$D1028,">=01/02"&$C$7,'Livro Diario - FC'!$D$11:$D1028,"<=29/02"&$C$7) -> 0 | N37: =SUMIFS('Livro Diario - FC'!$K$11:$K1028,'Livro Diario - FC'!$E$11:$E1028,$C$37,'Livro Diario - FC'!$D$11:$D1028,">=01/03"&$C$7,'Livro Diario - FC'!$D$11:$D1028,"<=31/03"&$C$7) -> 0 | O37: =SUMIFS('Livro Diario - FC'!$M$11:$M1028,'Livro Diario - FC'!$E$11:$E1028,$C$37,'Livro Diario - FC'!$D$11:$D1028,">=01/03"&$C$7,'Livro Diario - FC'!$D$11:$D1028,"<=31/03"&$C$7) -> 0 | S37: =SUMIFS('Livro Diario - FC'!$K$11:$K1028,'Livro Diario - FC'!$E$11:$E1028,$C$37,'Livro Diario - FC'!$D$11:$D1028,">=01/04"&$C$7,'Livro Diario - FC'!$D$11:$D1028,"<=30/04"&$C$7) -> 0 | T37: =SUMIFS('Livro Diario - FC'!$M$11:$M1028,'Livro Diario - FC'!$E$11:$E1028,$C$37,'Livro Diario - FC'!$D$11:$D1028,">=01/04"&$C$7,'Livro Diario - FC'!$D$11:$D1028,"<=30/04"&$C$7) -> 0 | X37: =SUMIFS('Livro Diario - FC'!$K$11:$K1028,'Livro Diario - FC'!$E$11:$E1028,$C$37,'Livro Diario - FC'!$D$11:$D1028,">=01/05"&$C$7,'Livro Diario - FC'!$D$11:$D1028,"<=31/05"&$C$7) -> 0 | Y37: =SUMIFS('Livro Diario - FC'!$M$11:$M1028,'Livro Diario - FC'!$E$11:$E1028,$C$37,'Livro Diario - FC'!$D$11:$D1028,">=01/05"&$C$7,'Livro Diario - FC'!$D$11:$D1028,"<=31/05"&$C$7) -> 0 | AC37: =SUMIFS('Livro Diario - FC'!$K$11:$K1028,'Livro Diario - FC'!$E$11:$E1028,$C$37,'Livro Diario - FC'!$D$11:$D1028,">=01/06"&$C$7,'Livro Diario - FC'!$D$11:$D1028,"<=30/06"&$C$7) -> 0 | AD37: =SUMIFS('Livro Diario - FC'!$M$11:$M1028,'Livro Diario - FC'!$E$11:$E1028,$C$37,'Livro Diario - FC'!$D$11:$D1028,">=01/06"&$C$7,'Livro Diario - FC'!$D$11:$D1028,"<=30/06"&$C$7) -> 0 | AG37: =SUMIFS('Livro Diario - FC'!$K$11:$K1028,'Livro Diario - FC'!$E$11:$E1028,$C$37,'Livro Diario - FC'!$D$11:$D1028,">=01/07"&$C$7,'Livro Diario - FC'!$D$11:$D1028,"<=31/07"&$C$7) -> 0 | AH37: =SUMIFS('Livro Diario - FC'!$M$11:$M1028,'Livro Diario - FC'!$E$11:$E1028,$C$37,'Livro Diario - FC'!$D$11:$D1028,">=01/07"&$C$7,'Livro Diario - FC'!$D$11:$D1028,"<=31/07"&$C$7) -> 0 | AK37: =SUMIFS('Livro Diario - FC'!$K$11:$K1028,'Livro Diario - FC'!$E$11:$E1028,$C$37,'Livro Diario - FC'!$D$11:$D1028,">=01/08"&$C$7,'Livro Diario - FC'!$D$11:$D1028,"<=31/08"&$C$7) -> 0 | AL37: =SUMIFS('Livro Diario - FC'!$M$11:$M1028,'Livro Diario - FC'!$E$11:$E1028,$C$37,'Livro Diario - FC'!$D$11:$D1028,">=01/08"&$C$7,'Livro Diario - FC'!$D$11:$D1028,"<=31/08"&$C$7) -> 0 | AO37: =SUMIFS('Livro Diario - FC'!$K$11:$K1028,'Livro Diario - FC'!$E$11:$E1028,$C$37,'Livro Diario - FC'!$D$11:$D1028,">=01/09"&$C$7,'Livro Diario - FC'!$D$11:$D1028,"<=30/09"&$C$7) -> 0 | AP37: =SUMIFS('Livro Diario - FC'!$M$11:$M1028,'Livro Diario - FC'!$E$11:$E1028,$C$37,'Livro Diario - FC'!$D$11:$D1028,">=01/09"&$C$7,'Livro Diario - FC'!$D$11:$D1028,"<=30/09"&$C$7) -> 0 | AS37: =SUMIFS('Livro Diario - FC'!$K$11:$K1028,'Livro Diario - FC'!$E$11:$E1028,$C$37,'Livro Diario - FC'!$D$11:$D1028,">=01/10"&$C$7,'Livro Diario - FC'!$D$11:$D1028,"<=31/10"&$C$7) -> 0 | AT37: =SUMIFS('Livro Diario - FC'!$M$11:$M1028,'Livro Diario - FC'!$E$11:$E1028,$C$37,'Livro Diario - FC'!$D$11:$D1028,">=01/10"&$C$7,'Livro Diario - FC'!$D$11:$D1028,"<=31/10"&$C$7) -> 0 | AW37: =SUMIFS('Livro Diario - FC'!$K$11:$K1028,'Livro Diario - FC'!$E$11:$E1028,$C$37,'Livro Diario - FC'!$D$11:$D1028,">=01/11"&$C$7,'Livro Diario - FC'!$D$11:$D1028,"<=30/11"&$C$7) -> 0 | AX37: =SUMIFS('Livro Diario - FC'!$M$11:$M1028,'Livro Diario - FC'!$E$11:$E1028,$C$37,'Livro Diario - FC'!$D$11:$D1028,">=01/11"&$C$7,'Livro Diario - FC'!$D$11:$D1028,"<=30/11"&$C$7) -> 0 | BA37: =SUMIFS('Livro Diario - FC'!$K$11:$K1028,'Livro Diario - FC'!$E$11:$E1028,$C$37,'Livro Diario - FC'!$D$11:$D1028,">=01/12"&$C$7,'Livro Diario - FC'!$D$11:$D1028,"<=31/12"&$C$7) -> 0 | BB37: =SUMIFS('Livro Diario - FC'!$M$11:$M1028,'Livro Diario - FC'!$E$11:$E1028,$C$37,'Livro Diario - FC'!$D$11:$D1028,">=01/12"&$C$7,'Livro Diario - FC'!$D$11:$D1028,"<=31/12"&$C$7) -> 0 | BE37: =SUM(D37,I37,N37,S37,X37,AC37,AG37,AK37,AO37,AS37,AW37,BA37) -> 333.25 | BF37: =SUM(E37,J37,O37,T37,Y37,AD37,AH37,AL37,AP37,AT37,AX37,BB37) -> 333.25 | BI37: =SUMIFS('Livro Diario - FC'!$M$11:$M1028,'Livro Diario - FC'!$E$11:$E1028,C37,'Livro Diario - FC'!$D$11:$D1028,">="&$BK$8,'Livro Diario - FC'!$D$11:$D1028,"<="&$BK$9) -> 0
C38: ='Livro Diario - FC'!AE41 -> Arroz | D38: =SUMIFS('Livro Diario - FC'!$K$11:$K1028,'Livro Diario - FC'!$E$11:$E1028,$C$38,'Livro Diario - FC'!$D$11:$D1028,">=01/01"&$C$7,'Livro Diario - FC'!$D$11:$D1028,"<=31/01"&$C$7) -> 203.07 | E38: =SUMIFS('Livro Diario - FC'!$M$11:$M1028,'Livro Diario - FC'!$E$11:$E1028,$C$38,'Livro Diario - FC'!$D$11:$D1028,">=01/01"&$C$7,'Livro Diario - FC'!$D$11:$D1028,"<=31/01"&$C$7) -> 203.07 | I38: =SUMIFS('Livro Diario - FC'!$K$11:$K1028,'Livro Diario - FC'!$E$11:$E1028,$C$38,'Livro Diario - FC'!$D$11:$D1028,">=01/02"&$C$7,'Livro Diario - FC'!$D$11:$D1028,"<=29/02"&$C$7) -> 0 | J38: =SUMIFS('Livro Diario - FC'!$M$11:$M1028,'Livro Diario - FC'!$E$11:$E1028,$C$38,'Livro Diario - FC'!$D$11:$D1028,">=01/02"&$C$7,'Livro Diario - FC'!$D$11:$D1028,"<=29/02"&$C$7) -> 0 | N38: =SUMIFS('Livro Diario - FC'!$K$11:$K1028,'Livro Diario - FC'!$E$11:$E1028,$C$38,'Livro Diario - FC'!$D$11:$D1028,">=01/03"&$C$7,'Livro Diario - FC'!$D$11:$D1028,"<=31/03"&$C$7) -> 0 | O38: =SUMIFS('Livro Diario - FC'!$M$11:$M1028,'Livro Diario - FC'!$E$11:$E1028,$C$38,'Livro Diario - FC'!$D$11:$D1028,">=01/03"&$C$7,'Livro Diario - FC'!$D$11:$D1028,"<=31/03"&$C$7) -> 0 | S38: =SUMIFS('Livro Diario - FC'!$K$11:$K1028,'Livro Diario - FC'!$E$11:$E1028,$C$38,'Livro Diario - FC'!$D$11:$D1028,">=01/04"&$C$7,'Livro Diario - FC'!$D$11:$D1028,"<=30/04"&$C$7) -> 0 | T38: =SUMIFS('Livro Diario - FC'!$M$11:$M1028,'Livro Diario - FC'!$E$11:$E1028,$C$38,'Livro Diario - FC'!$D$11:$D1028,">=01/04"&$C$7,'Livro Diario - FC'!$D$11:$D1028,"<=30/04"&$C$7) -> 0 | X38: =SUMIFS('Livro Diario - FC'!$K$11:$K1028,'Livro Diario - FC'!$E$11:$E1028,$C$38,'Livro Diario - FC'!$D$11:$D1028,">=01/05"&$C$7,'Livro Diario - FC'!$D$11:$D1028,"<=31/05"&$C$7) -> 0 | Y38: =SUMIFS('Livro Diario - FC'!$M$11:$M1028,'Livro Diario - FC'!$E$11:$E1028,$C$38,'Livro Diario - FC'!$D$11:$D1028,">=01/05"&$C$7,'Livro Diario - FC'!$D$11:$D1028,"<=31/05"&$C$7) -> 0 | AC38: =SUMIFS('Livro Diario - FC'!$K$11:$K1028,'Livro Diario - FC'!$E$11:$E1028,$C$38,'Livro Diario - FC'!$D$11:$D1028,">=01/06"&$C$7,'Livro Diario - FC'!$D$11:$D1028,"<=30/06"&$C$7) -> 0 | AD38: =SUMIFS('Livro Diario - FC'!$M$11:$M1028,'Livro Diario - FC'!$E$11:$E1028,$C$38,'Livro Diario - FC'!$D$11:$D1028,">=01/06"&$C$7,'Livro Diario - FC'!$D$11:$D1028,"<=30/06"&$C$7) -> 0 | AG38: =SUMIFS('Livro Diario - FC'!$K$11:$K1028,'Livro Diario - FC'!$E$11:$E1028,$C$38,'Livro Diario - FC'!$D$11:$D1028,">=01/07"&$C$7,'Livro Diario - FC'!$D$11:$D1028,"<=31/07"&$C$7) -> 0 | AH38: =SUMIFS('Livro Diario - FC'!$M$11:$M1028,'Livro Diario - FC'!$E$11:$E1028,$C$38,'Livro Diario - FC'!$D$11:$D1028,">=01/07"&$C$7,'Livro Diario - FC'!$D$11:$D1028,"<=31/07"&$C$7) -> 0 | AK38: =SUMIFS('Livro Diario - FC'!$K$11:$K1028,'Livro Diario - FC'!$E$11:$E1028,$C$38,'Livro Diario - FC'!$D$11:$D1028,">=01/08"&$C$7,'Livro Diario - FC'!$D$11:$D1028,"<=31/08"&$C$7) -> 0 | AL38: =SUMIFS('Livro Diario - FC'!$M$11:$M1028,'Livro Diario - FC'!$E$11:$E1028,$C$38,'Livro Diario - FC'!$D$11:$D1028,">=01/08"&$C$7,'Livro Diario - FC'!$D$11:$D1028,"<=31/08"&$C$7) -> 0 | AO38: =SUMIFS('Livro Diario - FC'!$K$11:$K1028,'Livro Diario - FC'!$E$11:$E1028,$C$38,'Livro Diario - FC'!$D$11:$D1028,">=01/09"&$C$7,'Livro Diario - FC'!$D$11:$D1028,"<=30/09"&$C$7) -> 0 | AP38: =SUMIFS('Livro Diario - FC'!$M$11:$M1028,'Livro Diario - FC'!$E$11:$E1028,$C$38,'Livro Diario - FC'!$D$11:$D1028,">=01/09"&$C$7,'Livro Diario - FC'!$D$11:$D1028,"<=30/09"&$C$7) -> 0 | AS38: =SUMIFS('Livro Diario - FC'!$K$11:$K1028,'Livro Diario - FC'!$E$11:$E1028,$C$38,'Livro Diario - FC'!$D$11:$D1028,">=01/10"&$C$7,'Livro Diario - FC'!$D$11:$D1028,"<=31/10"&$C$7) -> 0 | AT38: =SUMIFS('Livro Diario - FC'!$M$11:$M1028,'Livro Diario - FC'!$E$11:$E1028,$C$38,'Livro Diario - FC'!$D$11:$D1028,">=01/10"&$C$7,'Livro Diario - FC'!$D$11:$D1028,"<=31/10"&$C$7) -> 0 | AW38: =SUMIFS('Livro Diario - FC'!$K$11:$K1028,'Livro Diario - FC'!$E$11:$E1028,$C$38,'Livro Diario - FC'!$D$11:$D1028,">=01/11"&$C$7,'Livro Diario - FC'!$D$11:$D1028,"<=30/11"&$C$7) -> 0 | AX38: =SUMIFS('Livro Diario - FC'!$M$11:$M1028,'Livro Diario - FC'!$E$11:$E1028,$C$38,'Livro Diario - FC'!$D$11:$D1028,">=01/11"&$C$7,'Livro Diario - FC'!$D$11:$D1028,"<=30/11"&$C$7) -> 0 | BA38: =SUMIFS('Livro Diario - FC'!$K$11:$K1028,'Livro Diario - FC'!$E$11:$E1028,$C$38,'Livro Diario - FC'!$D$11:$D1028,">=01/12"&$C$7,'Livro Diario - FC'!$D$11:$D1028,"<=31/12"&$C$7) -> 0 | BB38: =SUMIFS('Livro Diario - FC'!$M$11:$M1028,'Livro Diario - FC'!$E$11:$E1028,$C$38,'Livro Diario - FC'!$D$11:$D1028,">=01/12"&$C$7,'Livro Diario - FC'!$D$11:$D1028,"<=31/12"&$C$7) -> 0 | BE38: =SUM(D38,I38,N38,S38,X38,AC38,AG38,AK38,AO38,AS38,AW38,BA38) -> 203.07 | BF38: =SUM(E38,J38,O38,T38,Y38,AD38,AH38,AL38,AP38,AT38,AX38,BB38) -> 203.07 | BI38: =SUMIFS('Livro Diario - FC'!$M$11:$M1028,'Livro Diario - FC'!$E$11:$E1028,C38,'Livro Diario - FC'!$D$11:$D1028,">="&$BK$8,'Livro Diario - FC'!$D$11:$D1028,"<="&$BK$9) -> 0
C39: ='Livro Diario - FC'!AE42 -> Feijão mulato | D39: =SUMIFS('Livro Diario - FC'!$K$11:$K1028,'Livro Diario - FC'!$E$11:$E1028,$C$39,'Livro Diario - FC'!$D$11:$D1028,">=01/01"&$C$7,'Livro Diario - FC'!$D$11:$D1028,"<=31/01"&$C$7) -> 148.95 | E39: =SUMIFS('Livro Diario - FC'!$M$11:$M1028,'Livro Diario - FC'!$E$11:$E1028,$C$39,'Livro Diario - FC'!$D$11:$D1028,">=01/01"&$C$7,'Livro Diario - FC'!$D$11:$D1028,"<=31/01"&$C$7) -> 148.95 | I39: =SUMIFS('Livro Diario - FC'!$K$11:$K1028,'Livro Diario - FC'!$E$11:$E1028,$C$39,'Livro Diario - FC'!$D$11:$D1028,">=01/02"&$C$7,'Livro Diario - FC'!$D$11:$D1028,"<=29/02"&$C$7) -> 0 | J39: =SUMIFS('Livro Diario - FC'!$M$11:$M1028,'Livro Diario - FC'!$E$11:$E1028,$C$39,'Livro Diario - FC'!$D$11:$D1028,">=01/02"&$C$7,'Livro Diario - FC'!$D$11:$D1028,"<=29/02"&$C$7) -> 0 | N39: =SUMIFS('Livro Diario - FC'!$K$11:$K1028,'Livro Diario - FC'!$E$11:$E1028,$C$39,'Livro Diario - FC'!$D$11:$D1028,">=01/03"&$C$7,'Livro Diario - FC'!$D$11:$D1028,"<=31/03"&$C$7) -> 0 | O39: =SUMIFS('Livro Diario - FC'!$M$11:$M1028,'Livro Diario - FC'!$E$11:$E1028,$C$39,'Livro Diario - FC'!$D$11:$D1028,">=01/03"&$C$7,'Livro Diario - FC'!$D$11:$D1028,"<=31/03"&$C$7) -> 0 | S39: =SUMIFS('Livro Diario - FC'!$K$11:$K1028,'Livro Diario - FC'!$E$11:$E1028,$C$39,'Livro Diario - FC'!$D$11:$D1028,">=01/04"&$C$7,'Livro Diario - FC'!$D$11:$D1028,"<=30/04"&$C$7) -> 0 | T39: =SUMIFS('Livro Diario - FC'!$M$11:$M1028,'Livro Diario - FC'!$E$11:$E1028,$C$39,'Livro Diario - FC'!$D$11:$D1028,">=01/04"&$C$7,'Livro Diario - FC'!$D$11:$D1028,"<=30/04"&$C$7) -> 0 | X39: =SUMIFS('Livro Diario - FC'!$K$11:$K1028,'Livro Diario - FC'!$E$11:$E1028,$C$39,'Livro Diario - FC'!$D$11:$D1028,">=01/05"&$C$7,'Livro Diario - FC'!$D$11:$D1028,"<=31/05"&$C$7) -> 0 | Y39: =SUMIFS('Livro Diario - FC'!$M$11:$M1028,'Livro Diario - FC'!$E$11:$E1028,$C$39,'Livro Diario - FC'!$D$11:$D1028,">=01/05"&$C$7,'Livro Diario - FC'!$D$11:$D1028,"<=31/05"&$C$7) -> 0 | AC39: =SUMIFS('Livro Diario - FC'!$K$11:$K1028,'Livro Diario - FC'!$E$11:$E1028,$C$39,'Livro Diario - FC'!$D$11:$D1028,">=01/06"&$C$7,'Livro Diario - FC'!$D$11:$D1028,"<=30/06"&$C$7) -> 0 | AD39: =SUMIFS('Livro Diario - FC'!$M$11:$M1028,'Livro Diario - FC'!$E$11:$E1028,$C$39,'Livro Diario - FC'!$D$11:$D1028,">=01/06"&$C$7,'Livro Diario - FC'!$D$11:$D1028,"<=30/06"&$C$7) -> 0 | AG39: =SUMIFS('Livro Diario - FC'!$K$11:$K1028,'Livro Diario - FC'!$E$11:$E1028,$C$39,'Livro Diario - FC'!$D$11:$D1028,">=01/07"&$C$7,'Livro Diario - FC'!$D$11:$D1028,"<=31/07"&$C$7) -> 0 | AH39: =SUMIFS('Livro Diario - FC'!$M$11:$M1028,'Livro Diario - FC'!$E$11:$E1028,$C$39,'Livro Diario - FC'!$D$11:$D1028,">=01/07"&$C$7,'Livro Diario - FC'!$D$11:$D1028,"<=31/07"&$C$7) -> 0 | AK39: =SUMIFS('Livro Diario - FC'!$K$11:$K1028,'Livro Diario - FC'!$E$11:$E1028,$C$39,'Livro Diario - FC'!$D$11:$D1028,">=01/08"&$C$7,'Livro Diario - FC'!$D$11:$D1028,"<=31/08"&$C$7) -> 0 | AL39: =SUMIFS('Livro Diario - FC'!$M$11:$M1028,'Livro Diario - FC'!$E$11:$E1028,$C$39,'Livro Diario - FC'!$D$11:$D1028,">=01/08"&$C$7,'Livro Diario - FC'!$D$11:$D1028,"<=31/08"&$C$7) -> 0 | AO39: =SUMIFS('Livro Diario - FC'!$K$11:$K1028,'Livro Diario - FC'!$E$11:$E1028,$C$39,'Livro Diario - FC'!$D$11:$D1028,">=01/09"&$C$7,'Livro Diario - FC'!$D$11:$D1028,"<=30/09"&$C$7) -> 0 | AP39: =SUMIFS('Livro Diario - FC'!$M$11:$M1028,'Livro Diario - FC'!$E$11:$E1028,$C$39,'Livro Diario - FC'!$D$11:$D1028,">=01/09"&$C$7,'Livro Diario - FC'!$D$11:$D1028,"<=30/09"&$C$7) -> 0 | AS39: =SUMIFS('Livro Diario - FC'!$K$11:$K1028,'Livro Diario - FC'!$E$11:$E1028,$C$39,'Livro Diario - FC'!$D$11:$D1028,">=01/10"&$C$7,'Livro Diario - FC'!$D$11:$D1028,"<=31/10"&$C$7) -> 0 | AT39: =SUMIFS('Livro Diario - FC'!$M$11:$M1028,'Livro Diario - FC'!$E$11:$E1028,$C$39,'Livro Diario - FC'!$D$11:$D1028,">=01/10"&$C$7,'Livro Diario - FC'!$D$11:$D1028,"<=31/10"&$C$7) -> 0 | AW39: =SUMIFS('Livro Diario - FC'!$K$11:$K1028,'Livro Diario - FC'!$E$11:$E1028,$C$39,'Livro Diario - FC'!$D$11:$D1028,">=01/11"&$C$7,'Livro Diario - FC'!$D$11:$D1028,"<=30/11"&$C$7) -> 0 | AX39: =SUMIFS('Livro Diario - FC'!$M$11:$M1028,'Livro Diario - FC'!$E$11:$E1028,$C$39,'Livro Diario - FC'!$D$11:$D1028,">=01/11"&$C$7,'Livro Diario - FC'!$D$11:$D1028,"<=30/11"&$C$7) -> 0 | BA39: =SUMIFS('Livro Diario - FC'!$K$11:$K1028,'Livro Diario - FC'!$E$11:$E1028,$C$39,'Livro Diario - FC'!$D$11:$D1028,">=01/12"&$C$7,'Livro Diario - FC'!$D$11:$D1028,"<=31/12"&$C$7) -> 0 | BB39: =SUMIFS('Livro Diario - FC'!$M$11:$M1028,'Livro Diario - FC'!$E$11:$E1028,$C$39,'Livro Diario - FC'!$D$11:$D1028,">=01/12"&$C$7,'Livro Diario - FC'!$D$11:$D1028,"<=31/12"&$C$7) -> 0 | BE39: =SUM(D39,I39,N39,S39,X39,AC39,AG39,AK39,AO39,AS39,AW39,BA39) -> 148.95 | BF39: =SUM(E39,J39,O39,T39,Y39,AD39,AH39,AL39,AP39,AT39,AX39,BB39) -> 148.95 | BI39: =SUMIFS('Livro Diario - FC'!$M$11:$M1028,'Livro Diario - FC'!$E$11:$E1028,C39,'Livro Diario - FC'!$D$11:$D1028,">="&$BK$8,'Livro Diario - FC'!$D$11:$D1028,"<="&$BK$9) -> 0
C40: ='Livro Diario - FC'!AE43 -> Feijão Preto | D40: =SUMIFS('Livro Diario - FC'!$K$11:$K1028,'Livro Diario - FC'!$E$11:$E1028,$C$40,'Livro Diario - FC'!$D$11:$D1028,">=01/01"&$C$7,'Livro Diario - FC'!$D$11:$D1028,"<=31/01"&$C$7) -> 120.07 | E40: =SUMIFS('Livro Diario - FC'!$M$11:$M1028,'Livro Diario - FC'!$E$11:$E1028,$C$40,'Livro Diario - FC'!$D$11:$D1028,">=01/01"&$C$7,'Livro Diario - FC'!$D$11:$D1028,"<=31/01"&$C$7) -> 120.07 | I40: =SUMIFS('Livro Diario - FC'!$K$11:$K1028,'Livro Diario - FC'!$E$11:$E1028,$C$40,'Livro Diario - FC'!$D$11:$D1028,">=01/02"&$C$7,'Livro Diario - FC'!$D$11:$D1028,"<=29/02"&$C$7) -> 0 | J40: =SUMIFS('Livro Diario - FC'!$M$11:$M1028,'Livro Diario - FC'!$E$11:$E1028,$C$40,'Livro Diario - FC'!$D$11:$D1028,">=01/02"&$C$7,'Livro Diario - FC'!$D$11:$D1028,"<=29/02"&$C$7) -> 0 | N40: =SUMIFS('Livro Diario - FC'!$K$11:$K1028,'Livro Diario - FC'!$E$11:$E1028,$C$40,'Livro Diario - FC'!$D$11:$D1028,">=01/03"&$C$7,'Livro Diario - FC'!$D$11:$D1028,"<=31/03"&$C$7) -> 0 | O40: =SUMIFS('Livro Diario - FC'!$M$11:$M1028,'Livro Diario - FC'!$E$11:$E1028,$C$40,'Livro Diario - FC'!$D$11:$D1028,">=01/03"&$C$7,'Livro Diario - FC'!$D$11:$D1028,"<=31/03"&$C$7) -> 0 | S40: =SUMIFS('Livro Diario - FC'!$K$11:$K1028,'Livro Diario - FC'!$E$11:$E1028,$C$40,'Livro Diario - FC'!$D$11:$D1028,">=01/04"&$C$7,'Livro Diario - FC'!$D$11:$D1028,"<=30/04"&$C$7) -> 0 | T40: =SUMIFS('Livro Diario - FC'!$M$11:$M1028,'Livro Diario - FC'!$E$11:$E1028,$C$40,'Livro Diario - FC'!$D$11:$D1028,">=01/04"&$C$7,'Livro Diario - FC'!$D$11:$D1028,"<=30/04"&$C$7) -> 0 | X40: =SUMIFS('Livro Diario - FC'!$K$11:$K1028,'Livro Diario - FC'!$E$11:$E1028,$C$40,'Livro Diario - FC'!$D$11:$D1028,">=01/05"&$C$7,'Livro Diario - FC'!$D$11:$D1028,"<=31/05"&$C$7) -> 0 | Y40: =SUMIFS('Livro Diario - FC'!$M$11:$M1028,'Livro Diario - FC'!$E$11:$E1028,$C$40,'Livro Diario - FC'!$D$11:$D1028,">=01/05"&$C$7,'Livro Diario - FC'!$D$11:$D1028,"<=31/05"&$C$7) -> 0 | AC40: =SUMIFS('Livro Diario - FC'!$K$11:$K1028,'Livro Diario - FC'!$E$11:$E1028,$C$40,'Livro Diario - FC'!$D$11:$D1028,">=01/06"&$C$7,'Livro Diario - FC'!$D$11:$D1028,"<=30/06"&$C$7) -> 0 | AD40: =SUMIFS('Livro Diario - FC'!$M$11:$M1028,'Livro Diario - FC'!$E$11:$E1028,$C$40,'Livro Diario - FC'!$D$11:$D1028,">=01/06"&$C$7,'Livro Diario - FC'!$D$11:$D1028,"<=30/06"&$C$7) -> 0 | AG40: =SUMIFS('Livro Diario - FC'!$K$11:$K1028,'Livro Diario - FC'!$E$11:$E1028,$C$40,'Livro Diario - FC'!$D$11:$D1028,">=01/07"&$C$7,'Livro Diario - FC'!$D$11:$D1028,"<=31/07"&$C$7) -> 0 | AH40: =SUMIFS('Livro Diario - FC'!$M$11:$M1028,'Livro Diario - FC'!$E$11:$E1028,$C$40,'Livro Diario - FC'!$D$11:$D1028,">=01/07"&$C$7,'Livro Diario - FC'!$D$11:$D1028,"<=31/07"&$C$7) -> 0 | AK40: =SUMIFS('Livro Diario - FC'!$K$11:$K1028,'Livro Diario - FC'!$E$11:$E1028,$C$40,'Livro Diario - FC'!$D$11:$D1028,">=01/08"&$C$7,'Livro Diario - FC'!$D$11:$D1028,"<=31/08"&$C$7) -> 0 | AL40: =SUMIFS('Livro Diario - FC'!$M$11:$M1028,'Livro Diario - FC'!$E$11:$E1028,$C$40,'Livro Diario - FC'!$D$11:$D1028,">=01/08"&$C$7,'Livro Diario - FC'!$D$11:$D1028,"<=31/08"&$C$7) -> 0 | AO40: =SUMIFS('Livro Diario - FC'!$K$11:$K1028,'Livro Diario - FC'!$E$11:$E1028,$C$40,'Livro Diario - FC'!$D$11:$D1028,">=01/09"&$C$7,'Livro Diario - FC'!$D$11:$D1028,"<=30/09"&$C$7) -> 0 | AP40: =SUMIFS('Livro Diario - FC'!$M$11:$M1028,'Livro Diario - FC'!$E$11:$E1028,$C$40,'Livro Diario - FC'!$D$11:$D1028,">=01/09"&$C$7,'Livro Diario - FC'!$D$11:$D1028,"<=30/09"&$C$7) -> 0 | AS40: =SUMIFS('Livro Diario - FC'!$K$11:$K1028,'Livro Diario - FC'!$E$11:$E1028,$C$40,'Livro Diario - FC'!$D$11:$D1028,">=01/10"&$C$7,'Livro Diario - FC'!$D$11:$D1028,"<=31/10"&$C$7) -> 0 | AT40: =SUMIFS('Livro Diario - FC'!$M$11:$M1028,'Livro Diario - FC'!$E$11:$E1028,$C$40,'Livro Diario - FC'!$D$11:$D1028,">=01/10"&$C$7,'Livro Diario - FC'!$D$11:$D1028,"<=31/10"&$C$7) -> 0 | AW40: =SUMIFS('Livro Diario - FC'!$K$11:$K1028,'Livro Diario - FC'!$E$11:$E1028,$C$40,'Livro Diario - FC'!$D$11:$D1028,">=01/11"&$C$7,'Livro Diario - FC'!$D$11:$D1028,"<=30/11"&$C$7) -> 0 | AX40: =SUMIFS('Livro Diario - FC'!$M$11:$M1028,'Livro Diario - FC'!$E$11:$E1028,$C$40,'Livro Diario - FC'!$D$11:$D1028,">=01/11"&$C$7,'Livro Diario - FC'!$D$11:$D1028,"<=30/11"&$C$7) -> 0 | BA40: =SUMIFS('Livro Diario - FC'!$K$11:$K1028,'Livro Diario - FC'!$E$11:$E1028,$C$40,'Livro Diario - FC'!$D$11:$D1028,">=01/12"&$C$7,'Livro Diario - FC'!$D$11:$D1028,"<=31/12"&$C$7) -> 0 | BB40: =SUMIFS('Livro Diario - FC'!$M$11:$M1028,'Livro Diario - FC'!$E$11:$E1028,$C$40,'Livro Diario - FC'!$D$11:$D1028,">=01/12"&$C$7,'Livro Diario - FC'!$D$11:$D1028,"<=31/12"&$C$7) -> 0 | BE40: =SUM(D40,I40,N40,S40,X40,AC40,AG40,AK40,AO40,AS40,AW40,BA40) -> 120.07 | BF40: =SUM(E40,J40,O40,T40,Y40,AD40,AH40,AL40,AP40,AT40,AX40,BB40) -> 120.07 | BI40: =SUMIFS('Livro Diario - FC'!$M$11:$M1028,'Livro Diario - FC'!$E$11:$E1028,C40,'Livro Diario - FC'!$D$11:$D1028,">="&$BK$8,'Livro Diario - FC'!$D$11:$D1028,"<="&$BK$9) -> 0
C41: ='Livro Diario - FC'!AE44 -> Feijão macassar | D41: =SUMIFS('Livro Diario - FC'!$K$11:$K1028,'Livro Diario - FC'!$E$11:$E1028,$C$41,'Livro Diario - FC'!$D$11:$D1028,">=01/01"&$C$7,'Livro Diario - FC'!$D$11:$D1028,"<=31/01"&$C$7) -> 70.9 | E41: =SUMIFS('Livro Diario - FC'!$M$11:$M1028,'Livro Diario - FC'!$E$11:$E1028,$C$41,'Livro Diario - FC'!$D$11:$D1028,">=01/01"&$C$7,'Livro Diario - FC'!$D$11:$D1028,"<=31/01"&$C$7) -> 70.9 | I41: =SUMIFS('Livro Diario - FC'!$K$11:$K1028,'Livro Diario - FC'!$E$11:$E1028,$C$41,'Livro Diario - FC'!$D$11:$D1028,">=01/02"&$C$7,'Livro Diario - FC'!$D$11:$D1028,"<=29/02"&$C$7) -> 0 | J41: =SUMIFS('Livro Diario - FC'!$M$11:$M1028,'Livro Diario - FC'!$E$11:$E1028,$C$41,'Livro Diario - FC'!$D$11:$D1028,">=01/02"&$C$7,'Livro Diario - FC'!$D$11:$D1028,"<=29/02"&$C$7) -> 0 | N41: =SUMIFS('Livro Diario - FC'!$K$11:$K1028,'Livro Diario - FC'!$E$11:$E1028,$C$41,'Livro Diario - FC'!$D$11:$D1028,">=01/03"&$C$7,'Livro Diario - FC'!$D$11:$D1028,"<=31/03"&$C$7) -> 0 | O41: =SUMIFS('Livro Diario - FC'!$M$11:$M1028,'Livro Diario - FC'!$E$11:$E1028,$C$41,'Livro Diario - FC'!$D$11:$D1028,">=01/03"&$C$7,'Livro Diario - FC'!$D$11:$D1028,"<=31/03"&$C$7) -> 0 | S41: =SUMIFS('Livro Diario - FC'!$K$11:$K1028,'Livro Diario - FC'!$E$11:$E1028,$C$41,'Livro Diario - FC'!$D$11:$D1028,">=01/04"&$C$7,'Livro Diario - FC'!$D$11:$D1028,"<=30/04"&$C$7) -> 0 | T41: =SUMIFS('Livro Diario - FC'!$M$11:$M1028,'Livro Diario - FC'!$E$11:$E1028,$C$41,'Livro Diario - FC'!$D$11:$D1028,">=01/04"&$C$7,'Livro Diario - FC'!$D$11:$D1028,"<=30/04"&$C$7) -> 0 | X41: =SUMIFS('Livro Diario - FC'!$K$11:$K1028,'Livro Diario - FC'!$E$11:$E1028,$C$41,'Livro Diario - FC'!$D$11:$D1028,">=01/05"&$C$7,'Livro Diario - FC'!$D$11:$D1028,"<=31/05"&$C$7) -> 0 | Y41: =SUMIFS('Livro Diario - FC'!$M$11:$M1028,'Livro Diario - FC'!$E$11:$E1028,$C$41,'Livro Diario - FC'!$D$11:$D1028,">=01/05"&$C$7,'Livro Diario - FC'!$D$11:$D1028,"<=31/05"&$C$7) -> 0 | AC41: =SUMIFS('Livro Diario - FC'!$K$11:$K1028,'Livro Diario - FC'!$E$11:$E1028,$C$41,'Livro Diario - FC'!$D$11:$D1028,">=01/06"&$C$7,'Livro Diario - FC'!$D$11:$D1028,"<=30/06"&$C$7) -> 0 | AD41: =SUMIFS('Livro Diario - FC'!$M$11:$M1028,'Livro Diario - FC'!$E$11:$E1028,$C$41,'Livro Diario - FC'!$D$11:$D1028,">=01/06"&$C$7,'Livro Diario - FC'!$D$11:$D1028,"<=30/06"&$C$7) -> 0 | AG41: =SUMIFS('Livro Diario - FC'!$K$11:$K1028,'Livro Diario - FC'!$E$11:$E1028,$C$41,'Livro Diario - FC'!$D$11:$D1028,">=01/07"&$C$7,'Livro Diario - FC'!$D$11:$D1028,"<=31/07"&$C$7) -> 0 | AH41: =SUMIFS('Livro Diario - FC'!$M$11:$M1028,'Livro Diario - FC'!$E$11:$E1028,$C$41,'Livro Diario - FC'!$D$11:$D1028,">=01/07"&$C$7,'Livro Diario - FC'!$D$11:$D1028,"<=31/07"&$C$7) -> 0 | AK41: =SUMIFS('Livro Diario - FC'!$K$11:$K1028,'Livro Diario - FC'!$E$11:$E1028,$C$41,'Livro Diario - FC'!$D$11:$D1028,">=01/08"&$C$7,'Livro Diario - FC'!$D$11:$D1028,"<=31/08"&$C$7) -> 0 | AL41: =SUMIFS('Livro Diario - FC'!$M$11:$M1028,'Livro Diario - FC'!$E$11:$E1028,$C$41,'Livro Diario - FC'!$D$11:$D1028,">=01/08"&$C$7,'Livro Diario - FC'!$D$11:$D1028,"<=31/08"&$C$7) -> 0 | AO41: =SUMIFS('Livro Diario - FC'!$K$11:$K1028,'Livro Diario - FC'!$E$11:$E1028,$C$41,'Livro Diario - FC'!$D$11:$D1028,">=01/09"&$C$7,'Livro Diario - FC'!$D$11:$D1028,"<=30/09"&$C$7) -> 0 | AP41: =SUMIFS('Livro Diario - FC'!$M$11:$M1028,'Livro Diario - FC'!$E$11:$E1028,$C$41,'Livro Diario - FC'!$D$11:$D1028,">=01/09"&$C$7,'Livro Diario - FC'!$D$11:$D1028,"<=30/09"&$C$7) -> 0 | AS41: =SUMIFS('Livro Diario - FC'!$K$11:$K1028,'Livro Diario - FC'!$E$11:$E1028,$C$41,'Livro Diario - FC'!$D$11:$D1028,">=01/10"&$C$7,'Livro Diario - FC'!$D$11:$D1028,"<=31/10"&$C$7) -> 0 | AT41: =SUMIFS('Livro Diario - FC'!$M$11:$M1028,'Livro Diario - FC'!$E$11:$E1028,$C$41,'Livro Diario - FC'!$D$11:$D1028,">=01/10"&$C$7,'Livro Diario - FC'!$D$11:$D1028,"<=31/10"&$C$7) -> 0 | AW41: =SUMIFS('Livro Diario - FC'!$K$11:$K1028,'Livro Diario - FC'!$E$11:$E1028,$C$41,'Livro Diario - FC'!$D$11:$D1028,">=01/11"&$C$7,'Livro Diario - FC'!$D$11:$D1028,"<=30/11"&$C$7) -> 0 | AX41: =SUMIFS('Livro Diario - FC'!$M$11:$M1028,'Livro Diario - FC'!$E$11:$E1028,$C$41,'Livro Diario - FC'!$D$11:$D1028,">=01/11"&$C$7,'Livro Diario - FC'!$D$11:$D1028,"<=30/11"&$C$7) -> 0 | BA41: =SUMIFS('Livro Diario - FC'!$K$11:$K1028,'Livro Diario - FC'!$E$11:$E1028,$C$41,'Livro Diario - FC'!$D$11:$D1028,">=01/12"&$C$7,'Livro Diario - FC'!$D$11:$D1028,"<=31/12"&$C$7) -> 0 | BB41: =SUMIFS('Livro Diario - FC'!$M$11:$M1028,'Livro Diario - FC'!$E$11:$E1028,$C$41,'Livro Diario - FC'!$D$11:$D1028,">=01/12"&$C$7,'Livro Diario - FC'!$D$11:$D1028,"<=31/12"&$C$7) -> 0 | BE41: =SUM(D41,I41,N41,S41,X41,AC41,AG41,AK41,AO41,AS41,AW41,BA41) -> 70.9 | BF41: =SUM(E41,J41,O41,T41,Y41,AD41,AH41,AL41,AP41,AT41,AX41,BB41) -> 70.9 | BI41: =SUMIFS('Livro Diario - FC'!$M$11:$M1028,'Livro Diario - FC'!$E$11:$E1028,C41,'Livro Diario - FC'!$D$11:$D1028,">="&$BK$8,'Livro Diario - FC'!$D$11:$D1028,"<="&$BK$9) -> 0
C42: ='Livro Diario - FC'!AE45 -> Sal | D42: =SUMIFS('Livro Diario - FC'!$K$11:$K1028,'Livro Diario - FC'!$E$11:$E1028,$C$42,'Livro Diario - FC'!$D$11:$D1028,">=01/01"&$C$7,'Livro Diario - FC'!$D$11:$D1028,"<=31/01"&$C$7) -> 17.99 | E42: =SUMIFS('Livro Diario - FC'!$M$11:$M1028,'Livro Diario - FC'!$E$11:$E1028,$C$42,'Livro Diario - FC'!$D$11:$D1028,">=01/01"&$C$7,'Livro Diario - FC'!$D$11:$D1028,"<=31/01"&$C$7) -> 17.99 | I42: =SUMIFS('Livro Diario - FC'!$K$11:$K1028,'Livro Diario - FC'!$E$11:$E1028,$C$42,'Livro Diario - FC'!$D$11:$D1028,">=01/02"&$C$7,'Livro Diario - FC'!$D$11:$D1028,"<=29/02"&$C$7) -> 0 | J42: =SUMIFS('Livro Diario - FC'!$M$11:$M1028,'Livro Diario - FC'!$E$11:$E1028,$C$42,'Livro Diario - FC'!$D$11:$D1028,">=01/02"&$C$7,'Livro Diario - FC'!$D$11:$D1028,"<=29/02"&$C$7) -> 0 | N42: =SUMIFS('Livro Diario - FC'!$K$11:$K1028,'Livro Diario - FC'!$E$11:$E1028,$C$42,'Livro Diario - FC'!$D$11:$D1028,">=01/03"&$C$7,'Livro Diario - FC'!$D$11:$D1028,"<=31/03"&$C$7) -> 0 | O42: =SUMIFS('Livro Diario - FC'!$M$11:$M1028,'Livro Diario - FC'!$E$11:$E1028,$C$42,'Livro Diario - FC'!$D$11:$D1028,">=01/03"&$C$7,'Livro Diario - FC'!$D$11:$D1028,"<=31/03"&$C$7) -> 0 | S42: =SUMIFS('Livro Diario - FC'!$K$11:$K1028,'Livro Diario - FC'!$E$11:$E1028,$C$42,'Livro Diario - FC'!$D$11:$D1028,">=01/04"&$C$7,'Livro Diario - FC'!$D$11:$D1028,"<=30/04"&$C$7) -> 0 | T42: =SUMIFS('Livro Diario - FC'!$M$11:$M1028,'Livro Diario - FC'!$E$11:$E1028,$C$42,'Livro Diario - FC'!$D$11:$D1028,">=01/04"&$C$7,'Livro Diario - FC'!$D$11:$D1028,"<=30/04"&$C$7) -> 0 | X42: =SUMIFS('Livro Diario - FC'!$K$11:$K1028,'Livro Diario - FC'!$E$11:$E1028,$C$42,'Livro Diario - FC'!$D$11:$D1028,">=01/05"&$C$7,'Livro Diario - FC'!$D$11:$D1028,"<=31/05"&$C$7) -> 0 | Y42: =SUMIFS('Livro Diario - FC'!$M$11:$M1028,'Livro Diario - FC'!$E$11:$E1028,$C$42,'Livro Diario - FC'!$D$11:$D1028,">=01/05"&$C$7,'Livro Diario - FC'!$D$11:$D1028,"<=31/05"&$C$7) -> 0 | AC42: =SUMIFS('Livro Diario - FC'!$K$11:$K1028,'Livro Diario - FC'!$E$11:$E1028,$C$42,'Livro Diario - FC'!$D$11:$D1028,">=01/06"&$C$7,'Livro Diario - FC'!$D$11:$D1028,"<=30/06"&$C$7) -> 0 | AD42: =SUMIFS('Livro Diario - FC'!$M$11:$M1028,'Livro Diario - FC'!$E$11:$E1028,$C$42,'Livro Diario - FC'!$D$11:$D1028,">=01/06"&$C$7,'Livro Diario - FC'!$D$11:$D1028,"<=30/06"&$C$7) -> 0 | AG42: =SUMIFS('Livro Diario - FC'!$K$11:$K1028,'Livro Diario - FC'!$E$11:$E1028,$C$42,'Livro Diario - FC'!$D$11:$D1028,">=01/07"&$C$7,'Livro Diario - FC'!$D$11:$D1028,"<=31/07"&$C$7) -> 0 | AH42: =SUMIFS('Livro Diario - FC'!$M$11:$M1028,'Livro Diario - FC'!$E$11:$E1028,$C$42,'Livro Diario - FC'!$D$11:$D1028,">=01/07"&$C$7,'Livro Diario - FC'!$D$11:$D1028,"<=31/07"&$C$7) -> 0 | AK42: =SUMIFS('Livro Diario - FC'!$K$11:$K1028,'Livro Diario - FC'!$E$11:$E1028,$C$42,'Livro Diario - FC'!$D$11:$D1028,">=01/08"&$C$7,'Livro Diario - FC'!$D$11:$D1028,"<=31/08"&$C$7) -> 0 | AL42: =SUMIFS('Livro Diario - FC'!$M$11:$M1028,'Livro Diario - FC'!$E$11:$E1028,$C$42,'Livro Diario - FC'!$D$11:$D1028,">=01/08"&$C$7,'Livro Diario - FC'!$D$11:$D1028,"<=31/08"&$C$7) -> 0 | AO42: =SUMIFS('Livro Diario - FC'!$K$11:$K1028,'Livro Diario - FC'!$E$11:$E1028,$C$42,'Livro Diario - FC'!$D$11:$D1028,">=01/09"&$C$7,'Livro Diario - FC'!$D$11:$D1028,"<=30/09"&$C$7) -> 0 | AP42: =SUMIFS('Livro Diario - FC'!$M$11:$M1028,'Livro Diario - FC'!$E$11:$E1028,$C$42,'Livro Diario - FC'!$D$11:$D1028,">=01/09"&$C$7,'Livro Diario - FC'!$D$11:$D1028,"<=30/09"&$C$7) -> 0 | AS42: =SUMIFS('Livro Diario - FC'!$K$11:$K1028,'Livro Diario - FC'!$E$11:$E1028,$C$42,'Livro Diario - FC'!$D$11:$D1028,">=01/10"&$C$7,'Livro Diario - FC'!$D$11:$D1028,"<=31/10"&$C$7) -> 0 | AT42: =SUMIFS('Livro Diario - FC'!$M$11:$M1028,'Livro Diario - FC'!$E$11:$E1028,$C$42,'Livro Diario - FC'!$D$11:$D1028,">=01/10"&$C$7,'Livro Diario - FC'!$D$11:$D1028,"<=31/10"&$C$7) -> 0 | AW42: =SUMIFS('Livro Diario - FC'!$K$11:$K1028,'Livro Diario - FC'!$E$11:$E1028,$C$42,'Livro Diario - FC'!$D$11:$D1028,">=01/11"&$C$7,'Livro Diario - FC'!$D$11:$D1028,"<=30/11"&$C$7) -> 0 | AX42: =SUMIFS('Livro Diario - FC'!$M$11:$M1028,'Livro Diario - FC'!$E$11:$E1028,$C$42,'Livro Diario - FC'!$D$11:$D1028,">=01/11"&$C$7,'Livro Diario - FC'!$D$11:$D1028,"<=30/11"&$C$7) -> 0 | BA42: =SUMIFS('Livro Diario - FC'!$K$11:$K1028,'Livro Diario - FC'!$E$11:$E1028,$C$42,'Livro Diario - FC'!$D$11:$D1028,">=01/12"&$C$7,'Livro Diario - FC'!$D$11:$D1028,"<=31/12"&$C$7) -> 0 | BB42: =SUMIFS('Livro Diario - FC'!$M$11:$M1028,'Livro Diario - FC'!$E$11:$E1028,$C$42,'Livro Diario - FC'!$D$11:$D1028,">=01/12"&$C$7,'Livro Diario - FC'!$D$11:$D1028,"<=31/12"&$C$7) -> 0 | BE42: =SUM(D42,I42,N42,S42,X42,AC42,AG42,AK42,AO42,AS42,AW42,BA42) -> 17.99 | BF42: =SUM(E42,J42,O42,T42,Y42,AD42,AH42,AL42,AP42,AT42,AX42,BB42) -> 17.99 | BI42: =SUMIFS('Livro Diario - FC'!$M$11:$M1028,'Livro Diario - FC'!$E$11:$E1028,C42,'Livro Diario - FC'!$D$11:$D1028,">="&$BK$8,'Livro Diario - FC'!$D$11:$D1028,"<="&$BK$9) -> 0
